Workbook
Name Customer_ID: #REF!
Name Month: #REF!
Name raphic5: #REF!
Name Slicer_AGENCY: #N/A
Name Slicer_PROJECT_NAME: #N/A

Sheet ChartsDataSheet
A1: Gauge Chart Name: | B1: AV | C1: 1 | D1: 2 | E1: 3 | F1: min | G1: max | H1: diff | I1: Format | J1: Decimals | K1: Labels size | L1: AV size | M1: ref 2E | N1: ref 1E | O1: color 1 | P1: color 2 | Q1: color 3 | R1: Skin | S1: Sheet Name | T1: Sheet Index | U1: Attached | V1: Reference | W1: color AV | X1: Description | Y1: Size | Z1: PV | AA1: 1 | AB1: 2 | AC1: 3 | AD1: min | AE1: max | AF1: diff | AG1: TextBoxDiff | AH1: color PV | AI1: ref 4S | AJ1: ref 4E | AK1: ref 5E | AL1: ref 6E | AM1: ref 7E | AN1: ref 8E | AO1: ref 9E | AP1: ref 10E | AQ1: ref 11E | AR1: ref 12E | AS1: color 4 | AT1: color 5 | AU1: color 6 | AV1: color 7 | AW1: color 8 | AX1: color 9 | AY1: color 10 | AZ1: color 11 | BA1: color 12 | BB1: Zones Count | BC1: Hform | BD1: Reverse? | BE1: 1 | BF1: 2 | BG1: 3 | BH1: 1 | BI1: 2 | BJ1: 3 | BK1: color LB | BL1: color A | BM1: color D | CW1: Variance Chart Name: | CX1: Sheet Name | CY1: Sheet Index | CZ1: Attached | DA1: Reference | DB1: Data 1 | DC1: Data 2 | DD1: Diff | DE1: Series 1 | DF1: Series 2 | DG1: Data 1 | DH1: Data 2 | DI1: Diff | DJ1: Series 1 | DK1: Series 2 | BES1: Sales Funnel Chart Name: | BET1: Sheet Name | BEU1: Sheet Index | BEV1: Attached | BEW1: Reference | BEX1: Series 1 | BIO1: TL Chart Name: | BIP1: AV | BIQ1: Green | BIR1: Yellow | BIS1: AV Val. | BIT1: Size 1 | BIU1: Size 2 | BIV1: Size 3 | BIW1: Format | BIX1: Decimals | BIY1: ForeColor | BIZ1: Border | BJA1: Off Light | BJB1: Text | BJC1: Color 1 | BJD1: Color 2 | BJE1: Color 3 | BJF1: Model | BJG1: Sheet Name | BJH1: Sheet Index | BJI1: Attached | BJJ1: Reference | BJK1: Minim | BJL1: Maxim | BUC1: VarianceActualHorizontal: | BUD1: Sheet Name | BUE1: Sheet Index | BUF1: Attached | BUG1: Reference | BXY1: WaterFallChart Name: | BXZ1: Sheet Name | BYA1: Sheet Index | BYB1: Attached | BYC1: Reference | BYD1: Labels | BYE1: Values | BYF1: Cumulative | BYG1: Start - End | BYH1: Before | BYI1: After | BYJ1: Data label position | CBU1: MekkoChart Name: | CBV1: Sheet Name | CBW1: Sheet Index | CBX1: Attached | CBY1: Reference | CFQ1: OrgChart Name: | CFR1: Sheet Name | CFS1: Sheet Index | CFT1: Attached | CFU1: Reference | CJM1: RadialBarChart Name: | CJN1: Sheet Name | CJO1: Sheet Index | CJP1: Attached | CJQ1: Reference | CJR1: MaxValue | CJS1: Value 1 | CJT1: Desc 1 | CJU1: v 1 | CJV1: i 1 | CJW1: Value 2 | CJX1: Desc 2 | CJY1: v 2 | CJZ1: i 2 | CKA1: Value 3 | CKB1: Desc 3 | CKC1: v 3 | CKD1: i 3 | CKE1: Value 4 | CKF1: Desc 4 | CKG1: v 4 | CKH1: i 4 | CKI1: Value 5 | CKJ1: Desc 5 | CKK1: v 5 | CKL1: i 5 | CKM1: Value 6 | CKN1: Desc 6 | CKO1: v 6 | CKP1: i 6 | CKQ1: Value 7 | CKR1: Desc 7 | CKS1: v 7 | CKT1: i 7 | CKU1: Value 8 | CKV1: Desc 8 | CKW1: v 8 | CKX1: i 8 | CKY1: Value 9 | CKZ1: Desc 9 | CLA1: v 9 | CLB1: i 9 | CLC1: Value 10 | CLD1: Desc 10 | CLE1: v 10 | CLF1: i 10 | CNI1: Sales Funnel2 Chart Name: | CNJ1: Sheet Name | CNK1: Sheet Index | CNL1: Attached | CNM1: Reference | CNN1: Colors | CNO1: DataText | CNP1: DataValue | CNQ1: x | CNR1: Label | CNS1: Value | CNT1: Low | CNU1: High | CNV1: x2 | CNW1: yLabel | CNX1: yPercent | CNY1: LabelPercent | CNZ1: xxx | COA1: xxx | COB1: xxx | CRE1: Ring Chart Name: | CRF1: Sheet Name | CRG1: Sheet Index | CRH1: Attached | CRI1: Reference | CRJ1: Value 1 | CRK1: Value 2 | CRL1: Color 1 | CRM1: Color 2 | CVA1: WindRoseChart Name: | CVB1: Sheet Name | CVC1: Sheet Index | CVD1: Attached | CVE1: Reference | CVF1: Cat 1 | CVG1: Cat 2 | CVH1: Cat 3 | CVI1: Cat 4 | CVJ1: Cat 5 | CVK1: Cat 6
CNI2: SF2_1 | CNJ2: =SUBSTITUTE(MID(_xlfn.FORMULATEXT(CNM2),2,FIND("!",_xlfn.FORMULATEXT(CNM2),1)-2), "'","") -> New Sankey | CNK2: =_xlfn.SHEET( 'New Sankey'!$NTP$1000000) -> 5 | CNM2: ='New Sankey'!$NTP$1000000 -> 0 | CNQ2: 1 | CNS2: =CNP3 -> 2723028.5 | CNT2: 0 | CNU2: =CNS2/2+CNS2/2 -> 2723028.5 | CNW2: =(CNU2/2)-(CNU2/2)*6/100 -> 1279823.4 | CNX2: =(CNU2/2)+(CNU2/2)*7/100 -> 1456820.2
CNI3: SF2_1 | CNJ3: =SUBSTITUTE(MID(_xlfn.FORMULATEXT(CNM3),2,FIND("!",_xlfn.FORMULATEXT(CNM3),1)-2), "'","") -> New Sankey | CNK3: =_xlfn.SHEET( 'New Sankey'!$NTP$1000000) -> 5 | CNM3: ='New Sankey'!$NTP$1000000 -> 0 | CNN3: 12345678 | CNO3: ='New Sankey'!$K$2 -> Aster PPK | CNP3: ='New Sankey'!$L$2 -> 2723028.5 | CNQ3: =CNQ2+1 -> 2 | CNR3: =CONCATENATE(CNO3," ",CNP3) -> Aster PPK 2723028.4668 | CNS3: =CNP3 -> 2723028.5 | CNT3: =CNS2/2-CNS3/2 -> 0 | CNU3: =CNS2/2+CNS3/2 -> 2723028.5 | CNV3: =CNQ2+1/2 -> 1.5 | CNW3: =CNW2 -> 1279823.4 | CNX3: =CNX2 -> 1456820.2 | CNY3: =CNS3/CNS2 -> 1
CNI4: SF2_1 | CNJ4: =SUBSTITUTE(MID(_xlfn.FORMULATEXT(CNM4),2,FIND("!",_xlfn.FORMULATEXT(CNM4),1)-2), "'","") -> New Sankey | CNK4: =_xlfn.SHEET( 'New Sankey'!$NTP$1000000) -> 5 | CNM4: ='New Sankey'!$NTP$1000000 -> 0 | CNN4: 12345678 | CNO4: ='New Sankey'!$K$3 -> Cantor Asia Media | CNP4: ='New Sankey'!$L$3 -> 1746051.4 | CNQ4: =CNQ3+1 -> 3 | CNR4: =CONCATENATE(CNO4," ",CNP4) -> Cantor Asia Media 1746051.3834 | CNS4: =CNP4 -> 1746051.4 | CNT4: =CNS2/2-CNS4/2 -> 488488.54 | CNU4: =CNS2/2+CNS4/2 -> 2234539.9 | CNV4: =CNQ3+1/2 -> 2.5 | CNW4: =CNW3 -> 1279823.4 | CNX4: =CNX3 -> 1456820.2 | CNY4: =CNS4/CNS2 -> 0.64121672
CNI5: SF2_1 | CNJ5: =SUBSTITUTE(MID(_xlfn.FORMULATEXT(CNM5),2,FIND("!",_xlfn.FORMULATEXT(CNM5),1)-2), "'","") -> New Sankey | CNK5: =_xlfn.SHEET( 'New Sankey'!$NTP$1000000) -> 5 | CNM5: ='New Sankey'!$NTP$1000000 -> 0 | CNN5: 12345678 | CNO5: ='New Sankey'!$K$4 -> Geoffrey Monty Allen | CNP5: ='New Sankey'!$L$4 -> 920570.16 | CNQ5: =CNQ4+1 -> 4 | CNR5: =CONCATENATE(CNO5," ",CNP5) -> Geoffrey Monty Allen 920570.1642 | CNS5: =CNP5 -> 920570.16 | CNT5: =CNS2/2-CNS5/2 -> 901229.15 | CNU5: =CNS2/2+CNS5/2 -> 1821799.3 | CNV5: =CNQ4+1/2 -> 3.5 | CNW5: =CNW4 -> 1279823.4 | CNX5: =CNX4 -> 1456820.2 | CNY5: =CNS5/CNS2 -> 0.33806851
CNI6: SF2_1 | CNJ6: =SUBSTITUTE(MID(_xlfn.FORMULATEXT(CNM6),2,FIND("!",_xlfn.FORMULATEXT(CNM6),1)-2), "'","") -> New Sankey | CNK6: =_xlfn.SHEET( 'New Sankey'!$NTP$1000000) -> 5 | CNM6: ='New Sankey'!$NTP$1000000 -> 0 | CNN6: 12345678 | CNO6: ='New Sankey'!$K$5 -> Idea Manufacturing | CNP6: ='New Sankey'!$L$5 -> 0 | CNQ6: =CNQ5+1 -> 5 | CNR6: =CONCATENATE(CNO6," ",CNP6) -> Idea Manufacturing 0 | CNS6: =CNP6 -> 0 | CNT6: =CNS2/2-CNS6/2 -> 1361514.2 | CNU6: =CNS2/2+CNS6/2 -> 1361514.2 | CNV6: =CNQ5+1/2 -> 4.5 | CNW6: =CNW5 -> 1279823.4 | CNX6: =CNX5 -> 1456820.2 | CNY6: =CNS6/CNS2 -> 0
CNI7: SF2_1 | CNJ7: =SUBSTITUTE(MID(_xlfn.FORMULATEXT(CNM7),2,FIND("!",_xlfn.FORMULATEXT(CNM7),1)-2), "'","") -> New Sankey | CNK7: =_xlfn.SHEET( 'New Sankey'!$NTP$1000000) -> 5 | CNM7: ='New Sankey'!$NTP$1000000 -> 0 | CNN7: 12345678 | CNO7: ='New Sankey'!$K$6 -> Korea SMB | CNP7: ='New Sankey'!$L$6 -> 1691093.3 | CNQ7: =CNQ6+1 -> 6 | CNR7: =CONCATENATE(CNO7," ",CNP7) -> Korea SMB 1691093.3245 | CNS7: =CNP7 -> 1691093.3 | CNT7: =CNS2/2-CNS7/2 -> 515967.57 | CNU7: =CNS2/2+CNS7/2 -> 2207060.9 | CNV7: =CNQ6+1/2 -> 5.5 | CNW7: =CNW6 -> 1279823.4 | CNX7: =CNX6 -> 1456820.2 | CNY7: =CNS7/CNS2 -> 0.62103402
CNI8: SF2_1 | CNJ8: =SUBSTITUTE(MID(_xlfn.FORMULATEXT(CNM8),2,FIND("!",_xlfn.FORMULATEXT(CNM8),1)-2), "'","") -> New Sankey | CNK8: =_xlfn.SHEET( 'New Sankey'!$NTP$1000000) -> 5 | CNM8: ='New Sankey'!$NTP$1000000 -> 0 | CNN8: 12345678 | CNO8: ='New Sankey'!$K$7 -> Last Station Group | CNP8: ='New Sankey'!$L$7 -> 1378028.8 | CNQ8: =CNQ7+1 -> 7 | CNR8: =CONCATENATE(CNO8," ",CNP8) -> Last Station Group 1378028.8353 | CNS8: =CNP8 -> 1378028.8 | CNT8: =CNS2/2-CNS8/2 -> 672499.82 | CNU8: =CNS2/2+CNS8/2 -> 2050528.7 | CNV8: =CNQ7+1/2 -> 6.5 | CNW8: =CNW7 -> 1279823.4 | CNX8: =CNX7 -> 1456820.2 | CNY8: =CNS8/CNS2 -> 0.50606479
CNI9: SF2_1 | CNJ9: =SUBSTITUTE(MID(_xlfn.FORMULATEXT(CNM9),2,FIND("!",_xlfn.FORMULATEXT(CNM9),1)-2), "'","") -> New Sankey | CNK9: =_xlfn.SHEET( 'New Sankey'!$NTP$1000000) -> 5 | CNM9: ='New Sankey'!$NTP$1000000 -> 0 | CNN9: 12345678 | CNO9: ='New Sankey'!$K$8 -> Top Notch Creative | CNP9: ='New Sankey'!$L$8 -> 1943021.8 | CNQ9: =CNQ8+1 -> 8 | CNR9: =CONCATENATE(CNO9," ",CNP9) -> Top Notch Creative 1943021.7769 | CNS9: =CNP9 -> 1943021.8 | CNT9: =CNS2/2-CNS9/2 -> 390003.34 | CNU9: =CNS2/2+CNS9/2 -> 2333025.1 | CNV9: =CNQ8+1/2 -> 7.5 | CNW9: =CNW8 -> 1279823.4 | CNX9: =CNX8 -> 1456820.2 | CNY9: =CNS9/CNS2 -> 0.71355177
CNI10: SF2_1 | CNJ10: =SUBSTITUTE(MID(_xlfn.FORMULATEXT(CNM10),2,FIND("!",_xlfn.FORMULATEXT(CNM10),1)-2), "'","") -> New Sankey | CNK10: =_xlfn.SHEET( 'New Sankey'!$NTP$1000000) -> 5 | CNM10: ='New Sankey'!$NTP$1000000 -> 0 | CNO10: BUBBLE | CNQ10: =CNQ9+31/100 -> 8.31 | CNR10: =CNS9 -> 1943021.8 | CNS10: =CNS2/2 -> 1361514.2
CNI11: SF2_2 | CNJ11: =SUBSTITUTE(MID(_xlfn.FORMULATEXT(CNM11),2,FIND("!",_xlfn.FORMULATEXT(CNM11),1)-2), "'","") -> New Sankey | CNK11: =_xlfn.SHEET( 'New Sankey'!$NTP$1000000) -> 5 | CNM11: ='New Sankey'!$NTP$1000000 -> 0 | CNQ11: 1 | CNS11: =CNP12 -> 10000 | CNT11: 0 | CNU11: =CNS11/2+CNS11/2 -> 10000 | CNW11: =(CNU11/2)-(CNU11/2)*6/100 -> 4700 | CNX11: =(CNU11/2)+(CNU11/2)*7/100 -> 5350
CNI12: SF2_2 | CNJ12: =SUBSTITUTE(MID(_xlfn.FORMULATEXT(CNM12),2,FIND("!",_xlfn.FORMULATEXT(CNM12),1)-2), "'","") -> New Sankey | CNK12: =_xlfn.SHEET( 'New Sankey'!$NTP$1000000) -> 5 | CNM12: ='New Sankey'!$NTP$1000000 -> 0 | CNN12: 12345678 | CNO12: ='New Sankey'!$H$18 -> All Work | CNP12: ='New Sankey'!$I$18 -> 10000 | CNQ12: =CNQ11+1 -> 2 | CNR12: =CONCATENATE(CNO12," ",CNP12) -> All Work 10000 | CNS12: =CNP12 -> 10000 | CNT12: =CNS11/2-CNS12/2 -> 0 | CNU12: =CNS11/2+CNS12/2 -> 10000 | CNV12: =CNQ11+1/2 -> 1.5 | CNW12: =CNW11 -> 4700 | CNX12: =CNX11 -> 5350 | CNY12: =CNS12/CNS11 -> 1
CNI13: SF2_2 | CNJ13: =SUBSTITUTE(MID(_xlfn.FORMULATEXT(CNM13),2,FIND("!",_xlfn.FORMULATEXT(CNM13),1)-2), "'","") -> New Sankey | CNK13: =_xlfn.SHEET( 'New Sankey'!$NTP$1000000) -> 5 | CNM13: ='New Sankey'!$NTP$1000000 -> 0 | CNN13: 12345678 | CNO13: ='New Sankey'!$H$19 -> Awarded | CNP13: ='New Sankey'!$I$19 -> 3000 | CNQ13: =CNQ12+1 -> 3 | CNR13: =CONCATENATE(CNO13," ",CNP13) -> Awarded 3000 | CNS13: =CNP13 -> 3000 | CNT13: =CNS11/2-CNS13/2 -> 3500 | CNU13: =CNS11/2+CNS13/2 -> 6500 | CNV13: =CNQ12+1/2 -> 2.5 | CNW13: =CNW12 -> 4700 | CNX13: =CNX12 -> 5350 | CNY13: =CNS13/CNS11 -> 0.3
CNI14: SF2_2 | CNJ14: =SUBSTITUTE(MID(_xlfn.FORMULATEXT(CNM14),2,FIND("!",_xlfn.FORMULATEXT(CNM14),1)-2), "'","") -> New Sankey | CNK14: =_xlfn.SHEET( 'New Sankey'!$NTP$1000000) -> 5 | CNM14: ='New Sankey'!$NTP$1000000 -> 0 | CNN14: 12345678 | CNO14: ='New Sankey'!$H$20 -> Women | CNP14: ='New Sankey'!$I$20 -> 254 | CNQ14: =CNQ13+1 -> 4 | CNR14: =CONCATENATE(CNO14," ",CNP14) -> Women 254 | CNS14: =CNP14 -> 254 | CNT14: =CNS11/2-CNS14/2 -> 4873 | CNU14: =CNS11/2+CNS14/2 -> 5127 | CNV14: =CNQ13+1/2 -> 3.5 | CNW14: =CNW13 -> 4700 | CNX14: =CNX13 -> 5350 | CNY14: =CNS14/CNS11 -> 0.0254
CNI15: SF2_2 | CNJ15: =SUBSTITUTE(MID(_xlfn.FORMULATEXT(CNM15),2,FIND("!",_xlfn.FORMULATEXT(CNM15),1)-2), "'","") -> New Sankey | CNK15: =_xlfn.SHEET( 'New Sankey'!$NTP$1000000) -> 5 | CNM15: ='New Sankey'!$NTP$1000000 -> 0 | CNO15: BUBBLE | CNQ15: =CNQ14+31/100 -> 4.31 | CNR15: =CNS14 -> 254 | CNS15: =CNS11/2 -> 5000

Sheet For SanKey Base
A1: PROJECT NAME | B1: AWARDED | C1: BRAND | D1: PRODUCT | E1: AGENCY | F1: CAMPAIGN | G1: VENDOR | H1: PHASE | I1: SUBMISSION | J1: BID NAME | K1: BIDFILE TYPE | L1: BID TOTAL | M1: BID TYPE | N1: AVERAGE BID | O1: DIVERSITY:: WOMAN DIRECTOR | P1: DIVERSITY:: MIINORITY DIRECTOR | Q1: DIVERSITY:: WOMAN EDITOR | R1: DIVERSITY:: MIINORITY EDITOR | S1: DIVERSITY:: WOMAN OWNED | T1: DIVERSITY:: MINORITY OWNED | U1: Women Work Pitched | V1: Women Work Awarded | W1: AvgBidPrice LUT.Average Bid Price
A2: Summer Fun | B2: 1 | C2: Kelly Hard Cider | D2: Kelly Summer Spritzer | E2: Korea SMB | F2: Q2 Summer Blitz | G2: Petulant Pictures | H2: Film & Video Production | I2: Summer Fun | J2: Petulant_SummerFun_LiveAction | K2: Original | L2: 960207.05 | M2: firm-bid | N2: 745866.47 | O2: 1 | U2: 960207.05 | V2: 960207.05 | W2: 745866.47
A3: Summer Fun | B3: 0 | C3: Kelly Hard Cider | D3: Kelly Summer Spritzer | E3: Korea SMB | F3: Q2 Summer Blitz | H3: Film & Video Production | I3: Summer Fun | J3: OpenFrameworks_SummerFun_LiveAction | K3: Original | L3: 662457.18 | M3: firm-bid | O3: 1 | P3: 1 | U3: 662457.18 | V3: 0 | W3: 745866.47
A4: Summer Fun | B4: 0 | C4: Kelly Hard Cider | D4: Kelly Summer Spritzer | E4: Korea SMB | F4: Q2 Summer Blitz | H4: Film & Video Production | I4: Summer Fun | J4: Club101_SummerFun_LiveAction | K4: Original | L4: 614935.17 | M4: firm-bid | U4: 0 | V4: 0 | W4: 745866.47
A5: Summer Fun | B5: 0 | C5: Kelly Hard Cider | D5: Kelly Summer Spritzer | E5: Korea SMB | F5: Q2 Summer Blitz | H5: Editorial | I5: Summer Fun | J5: ToTo_SummerFun_Edit | K5: Original | L5: 107610.42 | M5: firm-bid | U5: 0 | V5: 0 | W5: 109194.19
A6: Summer Fun | B6: 0 | C6: Kelly Hard Cider | D6: Kelly Summer Spritzer | E6: Korea SMB | F6: Q2 Summer Blitz | H6: Editorial | I6: Summer Fun | J6: MyrtleRow_SummerFun_Edit | K6: Original | L6: 133998.96 | M6: firm-bid | Q6: 1 | T6: 1 | U6: 0 | V6: 0 | W6: 109194.19
A7: Summer Fun | B7: 1 | C7: Kelly Hard Cider | D7: Kelly Summer Spritzer | E7: Korea SMB | F7: Q2 Summer Blitz | G7: Saks Street Edit | H7: Editorial | I7: Summer Fun | J7: SaksStreetEdit_SummerFun_Edit | K7: Original | L7: 85973.183 | M7: firm-bid | N7: 109194.19 | T7: 1 | U7: 0 | V7: 0 | W7: 109194.19
A8: Summer Fun | B8: 0 | C8: Kelly Hard Cider | D8: Kelly Summer Spritzer | E8: Korea SMB | F8: Q2 Summer Blitz | H8: Audio Post | I8: Audio Bid | J8: Audio Bid | K8: Original | L8: 14510 | M8: firm-bid | U8: 0 | V8: 0 | W8: 21656.667
A9: Summer Fun | B9: 1 | C9: Kelly Hard Cider | D9: Kelly Summer Spritzer | E9: Korea SMB | F9: Q2 Summer Blitz | G9: My Audio Fantasy | H9: Audio Post | I9: My Audio Fantasy | J9: AudioFantasybBid | K9: Original | L9: 21040 | M9: firm-bid | N9: 21656.667 | O9: 1 | R9: 1 | U9: 21040 | V9: 21040 | W9: 21656.667
A10: Summer Fun | B10: 0 | C10: Kelly Hard Cider | D10: Kelly Summer Spritzer | E10: Korea SMB | F10: Q2 Summer Blitz | H10: Audio Post | I10: Love Language"Summer Fun" | J10: Love124 | K10: Original | L10: 29420 | M10: firm-bid | U10: 0 | V10: 0 | W10: 21656.667
A11: Summer Fun | B11: 0 | C11: Kelly Hard Cider | D11: Kelly Summer Spritzer | E11: Korea SMB | F11: Q2 Summer Blitz | H11: Finishing | I11: colorMaven for Summer Fun v1 | J11: ColorMaven_SummerFun_Finishing | K11: Original | L11: 52850 | M11: firm-bid | S11: 1 | U11: 0 | V11: 0 | W11: 37833.333
A12: Summer Fun | B12: 0 | C12: Kelly Hard Cider | D12: Kelly Summer Spritzer | E12: Korea SMB | F12: Q2 Summer Blitz | H12: Finishing | I12: Andiamo for "Summer Fun" | J12: AndiamoImages_SummerFun_Finishing | K12: Original | L12: 20700 | M12: firm-bid | Q12: 1 | S12: 1 | U12: 0 | V12: 0 | W12: 37833.333
A13: Summer Fun | B13: 1 | C13: Kelly Hard Cider | D13: Kelly Summer Spritzer | E13: Korea SMB | F13: Q2 Summer Blitz | G13: Evan Bander LLC | H13: Finishing | I13: EB "Summer Fun" | J13: EvanBanderLLC_SummerFun_Finishing | K13: Original | L13: 39950 | M13: firm-bid | N13: 37833.333 | R13: 1 | T13: 1 | U13: 0 | V13: 0 | W13: 37833.333
A14: Summer Fun | B14: 1 | C14: Kelly Hard Cider | D14: Kelly Summer Spritzer | E14: Korea SMB | F14: Q2 Summer Blitz | G14: Petulant Pictures | H14: Sanitary Production Costs | I14: Summer Fun | J14: Petulant_SummerFun_Covid | K14: Original | L14: 4805.275 | M14: firm-bid | N14: 7050.3625 | O14: 1 | U14: 4805.275 | V14: 4805.275 | W14: 7050.3625
A15: Summer Fun | B15: 0 | C15: Kelly Hard Cider | D15: Kelly Summer Spritzer | E15: Korea SMB | F15: Q2 Summer Blitz | H15: Sanitary Production Costs | I15: Summer Fun | J15: OpenFrameworks_SummerFun_Covid | K15: Original | L15: 10043.812 | M15: firm-bid | O15: 1 | P15: 1 | U15: 10043.812 | V15: 0 | W15: 7050.3625
A16: Summer Fun | B16: 0 | C16: Kelly Hard Cider | D16: Kelly Summer Spritzer | E16: Korea SMB | F16: Q2 Summer Blitz | H16: Sanitary Production Costs | I16: Summer Fun | J16: Club101_SummerFun_Covid | K16: Original | L16: 6302 | M16: firm-bid | U16: 0 | V16: 0 | W16: 7050.3625
A17: Summer Fun | B17: 1 | C17: Kelly Hard Cider | D17: Kelly Summer Spritzer | E17: Korea SMB | F17: Q2 Summer Blitz | G17: Petulant Pictures | H17: Green Production Costs | I17: Summer Fun | J17: Petulant_SummerFun_Green | K17: Original | L17: 18176 | M17: firm-bid | N17: 14980 | O17: 1 | U17: 18176 | V17: 18176 | W17: 14980
A18: Summer Fun | B18: 0 | C18: Kelly Hard Cider | D18: Kelly Summer Spritzer | E18: Korea SMB | F18: Q2 Summer Blitz | H18: Green Production Costs | I18: Summer Fun | J18: OpenFrameworks_SummerFun_Green | K18: Original | L18: 14364 | M18: firm-bid | O18: 1 | P18: 1 | U18: 14364 | V18: 0 | W18: 14980
A19: Summer Fun | B19: 0 | C19: Kelly Hard Cider | D19: Kelly Summer Spritzer | E19: Korea SMB | F19: Q2 Summer Blitz | H19: Green Production Costs | I19: Summer Fun | J19: Club101_SummerFun_Green | K19: Original | L19: 12400 | M19: firm-bid | U19: 0 | V19: 0 | W19: 14980
A20: Summer Fun | B20: 0 | C20: Kelly Hard Cider | D20: Kelly Summer Spritzer | E20: Korea SMB | F20: Q2 Summer Blitz | H20: Photo Retouching & Post | I20: Kent Wilson Studio Estimate for "Summer Fun" #1 | J20: KentWilsonStudio_SummerFun_Retouching | K20: Original | L20: 39250 | M20: firm-bid | P20: 1 | U20: 0 | V20: 0 | W20: 37483.333
A21: Summer Fun | B21: 0 | C21: Kelly Hard Cider | D21: Kelly Summer Spritzer | E21: Korea SMB | F21: Q2 Summer Blitz | H21: Photo Retouching & Post | I21: Summer Fun | J21: Interstate_SummerFun_Retouching | K21: Original | L21: 36200 | M21: firm-bid | S21: 1 | U21: 0 | V21: 0 | W21: 37483.333
A22: Summer Fun | B22: 1 | C22: Kelly Hard Cider | D22: Kelly Summer Spritzer | E22: Korea SMB | F22: Q2 Summer Blitz | G22: Buck & Archie | H22: Photo Retouching & Post | I22: Buck & Archie "Kelly Hard Cider:Summer Fun" v2 | J22: BuckandArchie_SummerFun_Retouching | K22: Original | L22: 37000 | M22: firm-bid | N22: 37483.333 | U22: 0 | V22: 0 | W22: 37483.333
A23: Summer Fun | B23: 0 | C23: Kelly Hard Cider | D23: Kelly Summer Spritzer | E23: Korea SMB | F23: Q2 Summer Blitz | H23: Still Photography Production | I23: Kent Wilson Studio Estimate for "Summer Fun" #1 | J23: KentWilsonStudio_SummerFun_Stills | K23: Original | L23: 161541.3 | M23: firm-bid | P23: 1 | U23: 0 | V23: 0 | W23: 145472.98
A24: Summer Fun | B24: 0 | C24: Kelly Hard Cider | D24: Kelly Summer Spritzer | E24: Korea SMB | F24: Q2 Summer Blitz | H24: Still Photography Production | I24: Summer Fun | J24: Interstate_SummerFun_Stills | K24: Original | L24: 138331.55 | M24: firm-bid | S24: 1 | U24: 0 | V24: 0 | W24: 145472.98
A25: Summer Fun | B25: 1 | C25: Kelly Hard Cider | D25: Kelly Summer Spritzer | E25: Korea SMB | F25: Q2 Summer Blitz | G25: Buck & Archie | H25: Still Photography Production | I25: Buck & Archie "Kelly Hard Cider:Summer Fun" v2 | J25: BuckandArchie_SummerFun_Stills | K25: Original | L25: 136546.09 | M25: firm-bid | N25: 145472.98 | U25: 0 | V25: 0 | W25: 145472.98
A26: Summer Fun | B26: 0 | C26: Kelly Hard Cider | D26: Kelly Summer Spritzer | E26: Korea SMB | F26: Q2 Summer Blitz | H26: Music | I26: AEM "Kelly Summer Spritzer || Q2 Summer Blitz" | J26: ArnoldEstherMusic_SummerFun_Music | K26: Original | L26: 8700 | M26: firm-bid | U26: 0 | V26: 0 | W26: 38916.667
A27: Summer Fun | B27: 0 | C27: Kelly Hard Cider | D27: Kelly Summer Spritzer | E27: Korea SMB | F27: Q2 Summer Blitz | H27: Music | I27: "Summer Fun" - Special Oaks Music | J27: SpecialOaks_SummerFun_Music | K27: Original | L27: 69900 | M27: firm-bid | U27: 0 | V27: 0 | W27: 38916.667
A28: Summer Fun | B28: 1 | C28: Kelly Hard Cider | D28: Kelly Summer Spritzer | E28: Korea SMB | F28: Q2 Summer Blitz | G28: Tone & Logic | H28: Music | I28: T+L for "Kelly's Summer Fun" | J28: ToneandLogic_SummerFun_Music | K28: Original | L28: 38150 | M28: firm-bid | N28: 38916.667 | T28: 1 | U28: 0 | V28: 0 | W28: 38916.667
A29: The Traveller UK | B29: 0 | C29: Dewey North | D29: Dewey North 107º | E29: Last Station Group | F29: The Sophisticated Traveller | H29: Audio Post | I29: Special Oaks"The Traveller UK" | J29: Special Oaks | K29: Original | L29: 24800 | M29: firm-bid | O29: 1 | T29: 1 | U29: 24800 | V29: 0 | W29: 33935
A30: The Traveller UK | B30: 1 | C30: Dewey North | D30: Dewey North 107º | E30: Last Station Group | F30: The Sophisticated Traveller | G30: Love Language | H30: Audio Post | I30: Love Language "The Traveller UK" | J30: Love126 | K30: Original | L30: 43070 | M30: firm-bid | N30: 33935 | U30: 0 | V30: 0 | W30: 33935
A31: The Traveller UK | B31: 1 | C31: Dewey North | D31: Dewey North 107º | E31: Last Station Group | F31: The Sophisticated Traveller | G31: Love Language | H31: Music | I31: Love Language "The Traveller UK" - MUSIC ONLY | J31: LoveLanguage_TheTravellerUK_Music | K31: Original | L31: 20800 | M31: firm-bid | N31: 40150 | U31: 0 | V31: 0 | W31: 40150
A32: The Traveller UK | B32: 0 | C32: Dewey North | D32: Dewey North 107º | E32: Last Station Group | F32: The Sophisticated Traveller | H32: Music | I32: Frequency Presentation for "The Traveller UK" | J32: Frequency_TheTravellerUK_Music | K32: Original | L32: 49050 | M32: firm-bid | U32: 0 | V32: 0 | W32: 40150
A33: The Traveller UK | B33: 0 | C33: Dewey North | D33: Dewey North 107º | E33: Last Station Group | F33: The Sophisticated Traveller | H33: Music | I33: AEM "Dewey North || The Sophisticated Traveller (UK)" | J33: ArnoldEstherMusic_TheTravellerUK_Music | K33: Original | L33: 50600 | M33: firm-bid | U33: 0 | V33: 0 | W33: 40150
A34: The Traveller UK | B34: 1 | C34: Dewey North | D34: Dewey North 107º | E34: Last Station Group | F34: The Sophisticated Traveller | G34: EFX VFX | H34: VFX | I34: EFXvfx \\ "The Traveller UK" \\ v3 | J34: EFXVFX_TheTravellerUK_VFX | K34: Original | L34: 116454 | M34: firm-bid | N34: 104828.75 | U34: 0 | V34: 0 | W34: 104828.75
A35: The Traveller UK | B35: 0 | C35: Dewey North | D35: Dewey North 107º | E35: Last Station Group | F35: The Sophisticated Traveller | H35: VFX | I35: v2 - "The Traveller UK" //SORCERY | J35: Sorcery_TheTravellerUK_VFX | K35: Original | L35: 93203.5 | M35: firm-bid | U35: 0 | V35: 0 | W35: 104828.75
A36: The Traveller UK | B36: 0 | C36: Dewey North | D36: Dewey North 107º | E36: Last Station Group | F36: The Sophisticated Traveller | H36: Finishing | I36: colorMaven for "The Traveller UK" v3 | J36: ColorMaven_TheTravellerUK_Finishing | K36: Original | L36: 17500 | M36: firm-bid | S36: 1 | U36: 0 | V36: 0 | W36: 32250
A37: The Traveller UK | B37: 1 | C37: Dewey North | D37: Dewey North 107º | E37: Last Station Group | F37: The Sophisticated Traveller | G37: Andiamo Images | H37: Finishing | I37: Andiamo for "The Traveller" (UK Version) | J37: AndiamoImages_TheTravellerUK_Finishing | K37: Original | L37: 49250 | M37: firm-bid | N37: 32250 | O37: 1 | S37: 1 | U37: 49250 | V37: 49250 | W37: 32250
A38: The Traveller UK | B38: 0 | C38: Dewey North | D38: Dewey North 107º | E38: Last Station Group | F38: The Sophisticated Traveller | H38: Finishing | I38: ‚ÄúThe Traveller UK‚Äù - POI | J38: PersonsofInterest_TheTravellerUK_Finishing | K38: Original | L38: 30000 | M38: firm-bid | R38: 1 | U38: 0 | V38: 0 | W38: 32250
A39: The Traveller UK | B39: 1 | C39: Dewey North | D39: Dewey North 107º | E39: Last Station Group | F39: The Sophisticated Traveller | G39: Myrtle Row Editorial | H39: Editorial | I39: The Traveller UK | J39: MyrtleRow_TheTravellerUK_Edit | K39: Original | L39: 95889.792 | M39: firm-bid | N39: 93203.872 | T39: 1 | U39: 0 | V39: 0 | W39: 93203.872
A40: The Traveller UK | B40: 0 | C40: Dewey North | D40: Dewey North 107º | E40: Last Station Group | F40: The Sophisticated Traveller | H40: Editorial | I40: The Traveller UK | J40: TotalCuts_TheTravellerUK_Edit | K40: Original | L40: 67406.617 | M40: firm-bid | Q40: 1 | U40: 0 | V40: 0 | W40: 93203.872
A41: The Traveller UK | B41: 0 | C41: Dewey North | D41: Dewey North 107º | E41: Last Station Group | F41: The Sophisticated Traveller | H41: Editorial | I41: The Traveller UK | J41: Fightclub_TheTravellerUK_Edit | K41: Original | L41: 116315.21 | M41: firm-bid | U41: 0 | V41: 0 | W41: 93203.872
A42: The Traveller UK | B42: 1 | C42: Dewey North | D42: Dewey North 107º | E42: Last Station Group | F42: The Sophisticated Traveller | G42: Harmony & Light | H42: Green Production Costs | I42: The Traveller UK | J42: harmony_and_Light_TheTravellerUK_Green | K42: Original | L42: 10250 | M42: firm-bid | N42: 9606 | U42: 0 | V42: 0 | W42: 9606
A43: The Traveller UK | B43: 0 | C43: Dewey North | D43: Dewey North 107º | E43: Last Station Group | F43: The Sophisticated Traveller | H43: Green Production Costs | I43: The Traveller UK | J43: Level12_TheTravellerUK_Green | K43: Original | L43: 8568 | M43: firm-bid | O43: 1 | U43: 8568 | V43: 0 | W43: 9606
A44: The Traveller UK | B44: 0 | C44: Dewey North | D44: Dewey North 107º | E44: Last Station Group | F44: The Sophisticated Traveller | H44: Green Production Costs | I44: The Traveller UK | J44: OpenFrameworks_TheTravellerUK_Green | K44: Original | L44: 10000 | M44: firm-bid | O44: 1 | P44: 1 | U44: 10000 | V44: 0 | W44: 9606
A45: The Traveller UK | B45: 1 | C45: Dewey North | D45: Dewey North 107º | E45: Last Station Group | F45: The Sophisticated Traveller | G45: Harmony & Light | H45: Sanitary Production Costs | I45: The Traveller UK | J45: harmony_and_Light_TheTravellerUK_Covid | K45: Original | L45: 7200.035 | M45: firm-bid | N45: 9810.1133 | U45: 0 | V45: 0 | W45: 9810.1133
A46: The Traveller UK | B46: 0 | C46: Dewey North | D46: Dewey North 107º | E46: Last Station Group | F46: The Sophisticated Traveller | H46: Sanitary Production Costs | I46: The Traveller UK | J46: Level12_TheTravellerUK_Covid | K46: Original | L46: 12958.487 | M46: firm-bid | O46: 1 | U46: 12958.487 | V46: 0 | W46: 9810.1133
A47: The Traveller UK | B47: 0 | C47: Dewey North | D47: Dewey North 107º | E47: Last Station Group | F47: The Sophisticated Traveller | H47: Sanitary Production Costs | I47: The Traveller UK | J47: OpenFrameworks_TheTravellerUK_Covid | K47: Original | L47: 9271.8175 | M47: firm-bid | O47: 1 | P47: 1 | U47: 9271.8175 | V47: 0 | W47: 9810.1133
A48: The Traveller UK | B48: 1 | C48: Dewey North | D48: Dewey North 107º | E48: Last Station Group | F48: The Sophisticated Traveller | G48: Harmony & Light | H48: Film & Video Production | I48: The Traveller UK | J48: harmony_and_Light_TheTravellerUK_LiveAction | K48: Original | L48: 685626.9 | M48: firm-bid | N48: 649602.48 | U48: 0 | V48: 0 | W48: 649602.48
A49: The Traveller UK | B49: 0 | C49: Dewey North | D49: Dewey North 107º | E49: Last Station Group | F49: The Sophisticated Traveller | H49: Film & Video Production | I49: The Traveller UK | J49: Level12_TheTravellerUK_LiveAction | K49: Original | L49: 673878.44 | M49: firm-bid | O49: 1 | U49: 673878.44 | V49: 0 | W49: 649602.48
A50: The Traveller UK | B50: 0 | C50: Dewey North | D50: Dewey North 107º | E50: Last Station Group | F50: The Sophisticated Traveller | H50: Film & Video Production | I50: The Traveller UK | J50: OpenFrameworks_TheTravellerUK_LiveAction | K50: Original | L50: 589302.09 | M50: firm-bid | O50: 1 | P50: 1 | U50: 589302.09 | V50: 0 | W50: 649602.48
A51: The Traveller US | B51: 0 | C51: Dewey North | D51: Dewey North 107º | E51: Top Notch Creative | F51: The Sophisticated Traveller | H51: Audio Post | I51: Earwax "The Traveller US" | J51: Earwax | K51: Original | L51: 29320 | M51: firm-bid | U51: 0 | V51: 0 | W51: 48990
A52: The Traveller US | B52: 1 | C52: Dewey North | D52: Dewey North 107º | E52: Top Notch Creative | F52: The Sophisticated Traveller | G52: Audio Lab Technologies | H52: Audio Post | I52: Audio Lab"The Traveller US" | J52: Audio_85 | K52: Original | L52: 68660 | M52: firm-bid | N52: 48990 | Q52: 1 | S52: 1 | U52: 0 | V52: 0 | W52: 48990
A53: The Traveller US | B53: 0 | C53: Dewey North | D53: Dewey North 107º | E53: Top Notch Creative | F53: The Sophisticated Traveller | H53: Behind The Scenes (BTS) | I53: The Traveller (US Version) | J53: Club101_SummerFun_BTS | K53: Original | L53: 22844.75 | M53: firm-bid | U53: 0 | V53: 0 | W53: 18774.708
A54: The Traveller US | B54: 1 | C54: Dewey North | D54: Dewey North 107º | E54: Top Notch Creative | F54: The Sophisticated Traveller | G54: Test Flight Productions | H54: Behind The Scenes (BTS) | I54: The Traveller (for US) | J54: TestFlight_TheTravellerUS_BTS | K54: Original | L54: 19457.425 | M54: firm-bid | N54: 18774.708 | T54: 1 | U54: 0 | V54: 0 | W54: 18774.708
A55: The Traveller US | B55: 0 | C55: Dewey North | D55: Dewey North 107º | E55: Top Notch Creative | F55: The Sophisticated Traveller | H55: Behind The Scenes (BTS) | I55: The Traveller US V2 | J55: CHAW_TheTravellerUS_BTSv2 | K55: Original | L55: 14021.95 | M55: firm-bid | P55: 1 | T55: 1 | U55: 0 | V55: 0 | W55: 18774.708
A56: The Traveller US | B56: 1 | C56: Dewey North | D56: Dewey North 107º | E56: Top Notch Creative | F56: The Sophisticated Traveller | G56: Tone & Logic | H56: Music | I56: T+L for "Dewey North - The Traveller (US)" | J56: ToneandLogic_TheTravellerUS_Music | K56: Original | L56: 15950 | M56: firm-bid | N56: 30350 | T56: 1 | U56: 0 | V56: 0 | W56: 30350
A57: The Traveller US | B57: 0 | C57: Dewey North | D57: Dewey North 107º | E57: Top Notch Creative | F57: The Sophisticated Traveller | H57: Music | I57: Love Language "The Traveller US" v2 | J57: LoveLanguage_TheTravellerUS_Music | K57: Original | L57: 34650 | M57: firm-bid | U57: 0 | V57: 0 | W57: 30350
A58: The Traveller US | B58: 0 | C58: Dewey North | D58: Dewey North 107º | E58: Top Notch Creative | F58: The Sophisticated Traveller | H58: Music | I58: Frequency Presentation for "The Traveller US " | J58: Frequency_TheTravellerUS_Music | K58: Original | L58: 40450 | M58: firm-bid | U58: 0 | V58: 0 | W58: 30350
A59: The Traveller US | B59: 0 | C59: Dewey North | D59: Dewey North 107º | E59: Top Notch Creative | F59: The Sophisticated Traveller | H59: Finishing | I59: ‚ÄúThe Traveller US ‚Äù - POI | J59: PersonsofInterest_TheTravellerUS_Finishing | K59: Original | L59: 14900 | M59: firm-bid | R59: 1 | U59: 0 | V59: 0 | W59: 27083.333
A60: The Traveller US | B60: 0 | C60: Dewey North | D60: Dewey North 107º | E60: Top Notch Creative | F60: The Sophisticated Traveller | H60: Finishing | I60: EB "The Traveller US" | J60: EvanBanderLLC_TheTravellerUS_Finishing | K60: Original | L60: 47450 | M60: firm-bid | R60: 1 | T60: 1 | U60: 0 | V60: 0 | W60: 27083.333
A61: The Traveller US | B61: 1 | C61: Dewey North | D61: Dewey North 107º | E61: Top Notch Creative | F61: The Sophisticated Traveller | G61: The Dub House | H61: Finishing | I61: ‚ÄúThe Traveller US‚Äù | Dub House | J61: TheDubHouse_TheTravellerUS_Finishing | K61: Original | L61: 18900 | M61: firm-bid | N61: 27083.333 | U61: 0 | V61: 0 | W61: 27083.333
A62: The Traveller US | B62: 0 | C62: Dewey North | D62: Dewey North 107º | E62: Top Notch Creative | F62: The Sophisticated Traveller | H62: Editorial | I62: The Traveller US | J62: TotalCuts_TheTravellerUS_Edit | K62: Original | L62: 56933.45 | M62: firm-bid | Q62: 1 | U62: 0 | V62: 0 | W62: 93441.483
A63: The Traveller US | B63: 1 | C63: Dewey North | D63: Dewey North 107º | E63: Top Notch Creative | F63: The Sophisticated Traveller | G63: The Closet | H63: Editorial | I63: The Traveller US | J63: TheCloset_TheTravellerUS_Edit | K63: Original | L63: 100975.58 | M63: firm-bid | N63: 93441.483 | S63: 1 | T63: 1 | U63: 0 | V63: 0 | W63: 93441.483
A64: The Traveller US | B64: 0 | C64: Dewey North | D64: Dewey North 107º | E64: Top Notch Creative | F64: The Sophisticated Traveller | H64: Editorial | I64: The Traveller US | J64: SaksStreetEdit_TheTravellerUS_Edit | K64: Original | L64: 122415.42 | M64: firm-bid | T64: 1 | U64: 0 | V64: 0 | W64: 93441.483
A65: The Traveller US | B65: 0 | C65: Dewey North | D65: Dewey North 107º | E65: Top Notch Creative | F65: The Sophisticated Traveller | H65: Green Production Costs | I65: The Traveller (US Version) | J65: Club101_SummerFun_Green | K65: Original | L65: 12400 | M65: firm-bid | U65: 0 | V65: 0 | W65: 11703.333
A66: The Traveller US | B66: 1 | C66: Dewey North | D66: Dewey North 107º | E66: Top Notch Creative | F66: The Sophisticated Traveller | G66: Test Flight Productions | H66: Green Production Costs | I66: The Traveller (for US) | J66: TestFlight_TheTravellerUS_Green | K66: Original | L66: 13750 | M66: firm-bid | N66: 11703.333 | T66: 1 | U66: 0 | V66: 0 | W66: 11703.333
A67: The Traveller US | B67: 0 | C67: Dewey North | D67: Dewey North 107º | E67: Top Notch Creative | F67: The Sophisticated Traveller | H67: Green Production Costs | I67: The Traveller US V2 | J67: CHAW_TheTravellersFriend_Green | K67: Original | L67: 8960 | M67: firm-bid | P67: 1 | T67: 1 | U67: 0 | V67: 0 | W67: 11703.333
A68: The Traveller US | B68: 0 | C68: Dewey North | D68: Dewey North 107º | E68: Top Notch Creative | F68: The Sophisticated Traveller | H68: Sanitary Production Costs | I68: The Traveller (US Version) | J68: Club101_TheTravellerUS_Covid | K68: Original | L68: 7010.975 | M68: firm-bid | U68: 0 | V68: 0 | W68: 7058.24
A69: The Traveller US | B69: 1 | C69: Dewey North | D69: Dewey North 107º | E69: Top Notch Creative | F69: The Sophisticated Traveller | G69: Test Flight Productions | H69: Sanitary Production Costs | I69: The Traveller (for US) | J69: TestFlight_TheTravellerUS_Covid | K69: Original | L69: 5317.3125 | M69: firm-bid | N69: 7058.24 | T69: 1 | U69: 0 | V69: 0 | W69: 7058.24
A70: The Traveller US | B70: 0 | C70: Dewey North | D70: Dewey North 107º | E70: Top Notch Creative | F70: The Sophisticated Traveller | H70: Sanitary Production Costs | I70: The Traveller US V2 | J70: CHAW_TheTravellerUS_Covid | K70: Original | L70: 8846.4325 | M70: firm-bid | P70: 1 | T70: 1 | U70: 0 | V70: 0 | W70: 7058.24
A71: The Traveller US | B71: 0 | C71: Dewey North | D71: Dewey North 107º | E71: Top Notch Creative | F71: The Sophisticated Traveller | H71: Film & Video Production | I71: The Traveller (US Version) | J71: Club101_TheTravellerUS_LiveAction | K71: Original | L71: 748472.66 | M71: firm-bid | U71: 0 | V71: 0 | W71: 835635.38
A72: The Traveller US | B72: 1 | C72: Dewey North | D72: Dewey North 107º | E72: Top Notch Creative | F72: The Sophisticated Traveller | G72: Test Flight Productions | H72: Film & Video Production | I72: The Traveller (for US) | J72: TestFlight_TheTravellerUS_LiveAction | K72: Original | L72: 856318.5 | M72: firm-bid | N72: 835635.38 | T72: 1 | U72: 0 | V72: 0 | W72: 835635.38
A73: The Traveller US | B73: 0 | C73: Dewey North | D73: Dewey North 107º | E73: Top Notch Creative | F73: The Sophisticated Traveller | H73: Film & Video Production | I73: The Traveller US V2 | J73: CHAW_TheTravellerUS_LiveAction | K73: Original | L73: 902114.97 | M73: firm-bid | P73: 1 | T73: 1 | U73: 0 | V73: 0 | W73: 835635.38
A74: The Traveller Settles Down | B74: 0 | C74: Dewey North | D74: Dewey North 80¬∫ | E74: Top Notch Creative | F74: The Sophisticated Traveller | H74: Audio Post | I74: Earwax "The Traveller Settles Down" | J74: Earwax | K74: Original | L74: 35540 | M74: firm-bid | U74: 0 | V74: 0 | W74: 52025
A75: The Traveller Settles Down | B75: 1 | C75: Dewey North | D75: Dewey North 80¬∫ | E75: Top Notch Creative | F75: The Sophisticated Traveller | G75: Sound Monster | H75: Audio Post | I75: Sound Monster"The Traveller Settles Down" | J75: Sound Monster | K75: Original | L75: 68510 | M75: firm-bid | N75: 52025 | R75: 1 | U75: 0 | V75: 0 | W75: 52025
A76: The Traveller Settles Down | B76: 0 | C76: Dewey North | D76: Dewey North 80¬∫ | E76: Top Notch Creative | F76: The Sophisticated Traveller | H76: Music | I76: "The Traveller Settles Down" v2 | J76: M52_TheTravellerSettlesDown_Music | K76: Original | L76: 8600 | M76: firm-bid | O76: 1 | S76: 1 | U76: 8600 | V76: 0 | W76: 40166.667
A77: The Traveller Settles Down | B77: 1 | C77: Dewey North | D77: Dewey North 80¬∫ | E77: Top Notch Creative | F77: The Sophisticated Traveller | G77: Love Language | H77: Music | I77: Love Language "The Traveller Settles Down" v2 | J77: LoveLanguage_TheTravellerSettlesDown_Music | K77: Original | L77: 52150 | M77: firm-bid | N77: 40166.667 | U77: 0 | V77: 0 | W77: 40166.667
A78: The Traveller Settles Down | B78: 0 | C78: Dewey North | D78: Dewey North 80¬∫ | E78: Top Notch Creative | F78: The Sophisticated Traveller | H78: Music | I78: T+L for "Dewey North - The Traveller Settles Down" | J78: ToneandLogic_TheTravellerSettlesDown_Music | K78: Original | L78: 59750 | M78: firm-bid | T78: 1 | U78: 0 | V78: 0 | W78: 40166.667
A79: The Traveller Settles Down | B79: 1 | C79: Dewey North | D79: Dewey North 80¬∫ | E79: Top Notch Creative | F79: The Sophisticated Traveller | G79: Sorcery | H79: VFX | I79: v5 - "The Traveller Settles Down" //SORCERY | J79: Sorcery_TheTravellerSettlesDown_VFX | K79: Original | L79: 80541.5 | M79: firm-bid | N79: 79204.667 | U79: 0 | V79: 0 | W79: 79204.667
A80: The Traveller Settles Down | B80: 0 | C80: Dewey North | D80: Dewey North 80¬∫ | E80: Top Notch Creative | F80: The Sophisticated Traveller | H80: VFX | I80: "The Traveller Settles Down" JOB #4001 | J80: TerminalOutput_TheTravellerSettlesDown_VFX | K80: Original | L80: 92170 | M80: firm-bid | U80: 0 | V80: 0 | W80: 79204.667
A81: The Traveller Settles Down | B81: 0 | C81: Dewey North | D81: Dewey North 80¬∫ | E81: Top Notch Creative | F81: The Sophisticated Traveller | H81: VFX | I81: "The Traveller Settles Down" by CJ #4 | J81: CalamityJane_TheTravellerSettlesDown_VFX | K81: Original | L81: 64902.5 | M81: firm-bid | S81: 1 | U81: 0 | V81: 0 | W81: 79204.667
A82: The Traveller Settles Down | B82: 0 | C82: Dewey North | D82: Dewey North 80¬∫ | E82: Top Notch Creative | F82: The Sophisticated Traveller | H82: Finishing | I82: The Traveller Settles Down Burnish | J82: Burnish_TheTravellerSettlesDown_Finishing | K82: Original | L82: 8850 | M82: firm-bid | S82: 1 | U82: 0 | V82: 0 | W82: 18050
A83: The Traveller Settles Down | B83: 1 | C83: Dewey North | D83: Dewey North 80¬∫ | E83: Top Notch Creative | F83: The Sophisticated Traveller | G83: Witness | H83: Finishing | I83: WITNESS:: The Traveller Settles Down V2 | J83: Witness_TheTravellerSettlesDown_Finishing | K83: Original | L83: 28600 | M83: firm-bid | N83: 18050 | Q83: 1 | R83: 1 | U83: 0 | V83: 0 | W83: 18050
A84: The Traveller Settles Down | B84: 0 | C84: Dewey North | D84: Dewey North 80¬∫ | E84: Top Notch Creative | F84: The Sophisticated Traveller | H84: Finishing | I84: colorMaven "The Traveller Settles Down" | K84: Original | L84: 16700 | M84: firm-bid | S84: 1 | U84: 0 | V84: 0 | W84: 18050
A85: The Traveller Settles Down | B85: 0 | C85: Dewey North | D85: Dewey North 80¬∫ | E85: Top Notch Creative | F85: The Sophisticated Traveller | H85: Editorial | I85: The Traveller Settles Down | J85: ToTo_TheTravellerSettlesDown_Edit | K85: Original | L85: 112476.88 | M85: firm-bid | U85: 0 | V85: 0 | W85: 100943.6
A86: The Traveller Settles Down | B86: 1 | C86: Dewey North | D86: Dewey North 80¬∫ | E86: Top Notch Creative | F86: The Sophisticated Traveller | G86: Armistice Edit | H86: Editorial | I86: The Traveller Settles Down | J86: Armistace_TheTravellerSettlesDown_Edit | K86: Original | L86: 111615.99 | M86: firm-bid | N86: 100943.6 | U86: 0 | V86: 0 | W86: 100943.6
A87: The Traveller Settles Down | B87: 0 | C87: Dewey North | D87: Dewey North 80¬∫ | E87: Top Notch Creative | F87: The Sophisticated Traveller | H87: Editorial | I87: The Traveller Settles Down | J87: MyrtleRow_TheTravellerSettlesDown_Edit | K87: Original | L87: 78737.925 | M87: firm-bid | T87: 1 | U87: 0 | V87: 0 | W87: 100943.6
A88: The Traveller Settles Down | B88: 0 | C88: Dewey North | D88: Dewey North 80¬∫ | E88: Top Notch Creative | F88: The Sophisticated Traveller | H88: Green Production Costs | I88: TTSD | J88: Interstate_TheTravellerSettlesDown_Green | K88: Original | L88: 6875 | M88: firm-bid | S88: 1 | U88: 0 | V88: 0 | W88: 8766.3333
A89: The Traveller Settles Down | B89: 1 | C89: Dewey North | D89: Dewey North 80¬∫ | E89: Top Notch Creative | F89: The Sophisticated Traveller | G89: Open Frameworks Image Creation | H89: Green Production Costs | I89: The Traveller Settles Down | J89: OpenFrameworks_TheTravellerSettlesDown_Green | K89: Original | L89: 8928 | M89: firm-bid | N89: 8766.3333 | O89: 1 | P89: 1 | U89: 8928 | V89: 8928 | W89: 8766.3333
A90: The Traveller Settles Down | B90: 0 | C90: Dewey North | D90: Dewey North 80¬∫ | E90: Top Notch Creative | F90: The Sophisticated Traveller | H90: Green Production Costs | I90: TTSD | J90: Petulant_TheTravellerSettlesDown_Green | K90: Original | L90: 10496 | M90: firm-bid | O90: 1 | U90: 10496 | V90: 0 | W90: 8766.3333
A91: The Traveller Settles Down | B91: 0 | C91: Dewey North | D91: Dewey North 80¬∫ | E91: Top Notch Creative | F91: The Sophisticated Traveller | H91: Sanitary Production Costs | I91: TTSD | J91: Interstate_TheTravellerSettlesDown_Covid | K91: Original | L91: 10484.952 | M91: firm-bid | S91: 1 | U91: 0 | V91: 0 | W91: 7291.9392
A92: The Traveller Settles Down | B92: 1 | C92: Dewey North | D92: Dewey North 80¬∫ | E92: Top Notch Creative | F92: The Sophisticated Traveller | G92: Open Frameworks Image Creation | H92: Sanitary Production Costs | I92: The Traveller Settles Down | J92: OpenFrameworks_TheTravellerSettlesDown_Covid | K92: Original | L92: 6664.365 | M92: firm-bid | N92: 7291.9392 | O92: 1 | P92: 1 | U92: 6664.365 | V92: 6664.365 | W92: 7291.9392
A93: The Traveller Settles Down | B93: 0 | C93: Dewey North | D93: Dewey North 80¬∫ | E93: Top Notch Creative | F93: The Sophisticated Traveller | H93: Sanitary Production Costs | I93: TTSD | J93: Petulant_TheTravellerSettlesDown_Covid | K93: Original | L93: 4726.5 | M93: firm-bid | O93: 1 | U93: 4726.5 | V93: 0 | W93: 7291.9392
A94: The Traveller Settles Down | B94: 0 | C94: Dewey North | D94: Dewey North 80¬∫ | E94: Top Notch Creative | F94: The Sophisticated Traveller | H94: Film & Video Production | I94: TTSD | J94: Interstate_TheTravellerSettlesDown_LiveAction | K94: Original | L94: 702418.88 | M94: firm-bid | S94: 1 | U94: 0 | V94: 0 | W94: 656708.29
A95: The Traveller Settles Down | B95: 1 | C95: Dewey North | D95: Dewey North 80¬∫ | E95: Top Notch Creative | F95: The Sophisticated Traveller | G95: Open Frameworks Image Creation | H95: Film & Video Production | I95: The Traveller Settles Down | J95: OpenFrameworks_TheTravellerSettlesDown_LiveAction | K95: Original | L95: 621332.43 | M95: firm-bid | N95: 656708.29 | O95: 1 | P95: 1 | U95: 621332.43 | V95: 621332.43 | W95: 656708.29
A96: The Traveller Settles Down | B96: 0 | C96: Dewey North | D96: Dewey North 80¬∫ | E96: Top Notch Creative | F96: The Sophisticated Traveller | H96: Film & Video Production | I96: TTSD | J96: Petulant_TheTravellerSettlesDown_LiveAction | K96: Original | L96: 646373.56 | M96: firm-bid | O96: 1 | U96: 646373.56 | V96: 0 | W96: 656708.29
A97: Designated Dad | B97: 0 | C97: Walker's | D97: Walker's N/A | E97: Aster PPK | F97: Party Light | H97: Audio Post | I97: Sound Monster "Designated Dad" | J97: Sound Monster | K97: Original | L97: 50580 | M97: firm-bid | U97: 0 | V97: 0 | W97: 36220
A98: Designated Dad | B98: 0 | C98: Walker's | D98: Walker's N/A | E98: Aster PPK | F98: Party Light | H98: Audio Post | I98: Funny Rabbit "Designated Dad" | J98: Funny Rabbit | K98: Original | L98: 18410 | M98: firm-bid | O98: 1 | P98: 1 | R98: 1 | S98: 1 | U98: 18410 | V98: 0 | W98: 36220
A99: Designated Dad | B99: 1 | C99: Walker's | D99: Walker's N/A | E99: Aster PPK | F99: Party Light | G99: Earwax | H99: Audio Post | I99: Earwax | J99: Earwax | K99: Original | L99: 39670 | M99: firm-bid | N99: 36220 | U99: 0 | V99: 0 | W99: 36220
A100: Designated Dad | B100: 0 | C100: Walker's | D100: Walker's N/A | E100: Aster PPK | F100: Party Light | H100: Photo Retouching & Post | I100: DesDad | J100: Interstate_DesignatedDad_Retouching | K100: Original | L100: 21700 | M100: firm-bid | S100: 1 | U100: 0 | V100: 0 | W100: 25166.667
...

Sheet Wmoen Creatives
A1: PHASE | B1: Awarded to Women | C1: UnAwarded Women | D1: PhaseTOtal
A2: Film & Video Production | B2: 960207.05 | C2: 0 | D2: 960207.05
A3: Film & Video Production | B3: 0 | C3: 662457.18 | D3: 662457.18
A4: Film & Video Production | B4: 0 | C4: 0 | D4: 55315214
A5: Editorial | B5: 0 | C5: 0 | D5: 8233052.3
A6: Editorial | B6: 0 | C6: 133998.96 | D6: 133998.96
A7: Audio Post | B7: 0 | C7: 0 | D7: 1663370
A8: Audio Post | B8: 21040 | C8: 0 | D8: 21040
A9: Finishing | B9: 0 | C9: 0 | D9: 1988950
A10: Finishing | B10: 0 | C10: 20700 | D10: 20700
A11: Sanitary Production Costs | B11: 4805.275 | C11: 0 | D11: 4805.275
A12: Sanitary Production Costs | B12: 0 | C12: 10043.812 | D12: 10043.812
A13: Sanitary Production Costs | B13: 0 | C13: 0 | D13: 481039.54
... A115: Photo Retouching & Post | B115: 0 | C115: 31950 | D115: 31950

Sheet RevWomCreat
A1: PROJECT NAME | B1: AWARDED | C1: BRAND | D1: PRODUCT | E1: AGENCY | F1: CAMPAIGN | G1: VENDOR | H1: PHASE | I1: SUBMISSION | J1: BID NAME | K1: BIDFILE TYPE | L1: BID TOTAL | M1: BID TYPE | N1: AVERAGE BID | O1: DIVERSITY:: WOMAN DIRECTOR | P1: DIVERSITY:: MIINORITY DIRECTOR | Q1: DIVERSITY:: WOMAN EDITOR | R1: DIVERSITY:: MIINORITY EDITOR | S1: DIVERSITY:: WOMAN OWNED | T1: DIVERSITY:: MINORITY OWNED | U1: Women Work Pitched | V1: Women Work Awarded | W1: AvgBidPrice LUT.Average Bid Price | X1: Total Award | Y1: All Awarded
A2: Summer Fun | B2: 1 | C2: Kelly Hard Cider | D2: Kelly Summer Spritzer | E2: Korea SMB | F2: Q2 Summer Blitz | G2: Petulant Pictures | H2: Film & Video Production | I2: Summer Fun | J2: Petulant_SummerFun_LiveAction | K2: Original | L2: 960207.05 | M2: firm-bid | N2: 745866.47 | O2: 1 | U2: 960207.05 | V2: 960207.05 | W2: 745866.47 | X2: 960207.05 | Y2: 960207.05
A3: Summer Fun | B3: 0 | C3: Kelly Hard Cider | D3: Kelly Summer Spritzer | E3: Korea SMB | F3: Q2 Summer Blitz | H3: Film & Video Production | I3: Summer Fun | J3: OpenFrameworks_SummerFun_LiveAction | K3: Original | L3: 662457.18 | M3: firm-bid | O3: 1 | P3: 1 | U3: 662457.18 | V3: 0 | W3: 745866.47
A4: Summer Fun | B4: 0 | C4: Kelly Hard Cider | D4: Kelly Summer Spritzer | E4: Korea SMB | F4: Q2 Summer Blitz | H4: Film & Video Production | I4: Summer Fun | J4: Club101_SummerFun_LiveAction | K4: Original | L4: 614935.17 | M4: firm-bid | U4: 0 | V4: 0 | W4: 745866.47
A5: Summer Fun | B5: 0 | C5: Kelly Hard Cider | D5: Kelly Summer Spritzer | E5: Korea SMB | F5: Q2 Summer Blitz | H5: Editorial | I5: Summer Fun | J5: ToTo_SummerFun_Edit | K5: Original | L5: 107610.42 | M5: firm-bid | U5: 0 | V5: 0 | W5: 109194.19
A6: Summer Fun | B6: 0 | C6: Kelly Hard Cider | D6: Kelly Summer Spritzer | E6: Korea SMB | F6: Q2 Summer Blitz | H6: Editorial | I6: Summer Fun | J6: MyrtleRow_SummerFun_Edit | K6: Original | L6: 133998.96 | M6: firm-bid | Q6: 1 | T6: 1 | U6: 0 | V6: 0 | W6: 109194.19
A7: Summer Fun | B7: 1 | C7: Kelly Hard Cider | D7: Kelly Summer Spritzer | E7: Korea SMB | F7: Q2 Summer Blitz | G7: Saks Street Edit | H7: Editorial | I7: Summer Fun | J7: SaksStreetEdit_SummerFun_Edit | K7: Original | L7: 85973.183 | M7: firm-bid | N7: 109194.19 | T7: 1 | U7: 0 | V7: 0 | W7: 109194.19 | X7: 85973.183 | Y7: 85973.183
A8: Summer Fun | B8: 0 | C8: Kelly Hard Cider | D8: Kelly Summer Spritzer | E8: Korea SMB | F8: Q2 Summer Blitz | H8: Audio Post | I8: Audio Bid | J8: Audio Bid | K8: Original | L8: 14510 | M8: firm-bid | U8: 0 | V8: 0 | W8: 21656.667
A9: Summer Fun | B9: 1 | C9: Kelly Hard Cider | D9: Kelly Summer Spritzer | E9: Korea SMB | F9: Q2 Summer Blitz | G9: My Audio Fantasy | H9: Audio Post | I9: My Audio Fantasy | J9: AudioFantasybBid | K9: Original | L9: 21040 | M9: firm-bid | N9: 21656.667 | O9: 1 | R9: 1 | U9: 21040 | V9: 21040 | W9: 21656.667 | X9: 21040 | Y9: 21040
A10: Summer Fun | B10: 0 | C10: Kelly Hard Cider | D10: Kelly Summer Spritzer | E10: Korea SMB | F10: Q2 Summer Blitz | H10: Audio Post | I10: Love Language"Summer Fun" | J10: Love124 | K10: Original | L10: 29420 | M10: firm-bid | U10: 0 | V10: 0 | W10: 21656.667
A11: Summer Fun | B11: 0 | C11: Kelly Hard Cider | D11: Kelly Summer Spritzer | E11: Korea SMB | F11: Q2 Summer Blitz | H11: Finishing | I11: colorMaven for Summer Fun v1 | J11: ColorMaven_SummerFun_Finishing | K11: Original | L11: 52850 | M11: firm-bid | S11: 1 | U11: 0 | V11: 0 | W11: 37833.333
A12: Summer Fun | B12: 0 | C12: Kelly Hard Cider | D12: Kelly Summer Spritzer | E12: Korea SMB | F12: Q2 Summer Blitz | H12: Finishing | I12: Andiamo for "Summer Fun" | J12: AndiamoImages_SummerFun_Finishing | K12: Original | L12: 20700 | M12: firm-bid | Q12: 1 | S12: 1 | U12: 0 | V12: 0 | W12: 37833.333
A13: Summer Fun | B13: 1 | C13: Kelly Hard Cider | D13: Kelly Summer Spritzer | E13: Korea SMB | F13: Q2 Summer Blitz | G13: Evan Bander LLC | H13: Finishing | I13: EB "Summer Fun" | J13: EvanBanderLLC_SummerFun_Finishing | K13: Original | L13: 39950 | M13: firm-bid | N13: 37833.333 | R13: 1 | T13: 1 | U13: 0 | V13: 0 | W13: 37833.333 | X13: 39950 | Y13: 39950
A14: Summer Fun | B14: 1 | C14: Kelly Hard Cider | D14: Kelly Summer Spritzer | E14: Korea SMB | F14: Q2 Summer Blitz | G14: Petulant Pictures | H14: Sanitary Production Costs | I14: Summer Fun | J14: Petulant_SummerFun_Covid | K14: Original | L14: 4805.275 | M14: firm-bid | N14: 7050.3625 | O14: 1 | U14: 4805.275 | V14: 4805.275 | W14: 7050.3625 | X14: 4805.275 | Y14: 4805.275
A15: Summer Fun | B15: 0 | C15: Kelly Hard Cider | D15: Kelly Summer Spritzer | E15: Korea SMB | F15: Q2 Summer Blitz | H15: Sanitary Production Costs | I15: Summer Fun | J15: OpenFrameworks_SummerFun_Covid | K15: Original | L15: 10043.812 | M15: firm-bid | O15: 1 | P15: 1 | U15: 10043.812 | V15: 0 | W15: 7050.3625
A16: Summer Fun | B16: 0 | C16: Kelly Hard Cider | D16: Kelly Summer Spritzer | E16: Korea SMB | F16: Q2 Summer Blitz | H16: Sanitary Production Costs | I16: Summer Fun | J16: Club101_SummerFun_Covid | K16: Original | L16: 6302 | M16: firm-bid | U16: 0 | V16: 0 | W16: 7050.3625
A17: Summer Fun | B17: 1 | C17: Kelly Hard Cider | D17: Kelly Summer Spritzer | E17: Korea SMB | F17: Q2 Summer Blitz | G17: Petulant Pictures | H17: Green Production Costs | I17: Summer Fun | J17: Petulant_SummerFun_Green | K17: Original | L17: 18176 | M17: firm-bid | N17: 14980 | O17: 1 | U17: 18176 | V17: 18176 | W17: 14980 | X17: 18176 | Y17: 18176
A18: Summer Fun | B18: 0 | C18: Kelly Hard Cider | D18: Kelly Summer Spritzer | E18: Korea SMB | F18: Q2 Summer Blitz | H18: Green Production Costs | I18: Summer Fun | J18: OpenFrameworks_SummerFun_Green | K18: Original | L18: 14364 | M18: firm-bid | O18: 1 | P18: 1 | U18: 14364 | V18: 0 | W18: 14980
A19: Summer Fun | B19: 0 | C19: Kelly Hard Cider | D19: Kelly Summer Spritzer | E19: Korea SMB | F19: Q2 Summer Blitz | H19: Green Production Costs | I19: Summer Fun | J19: Club101_SummerFun_Green | K19: Original | L19: 12400 | M19: firm-bid | U19: 0 | V19: 0 | W19: 14980
A20: Summer Fun | B20: 0 | C20: Kelly Hard Cider | D20: Kelly Summer Spritzer | E20: Korea SMB | F20: Q2 Summer Blitz | H20: Photo Retouching & Post | I20: Kent Wilson Studio Estimate for "Summer Fun" #1 | J20: KentWilsonStudio_SummerFun_Retouching | K20: Original | L20: 39250 | M20: firm-bid | P20: 1 | U20: 0 | V20: 0 | W20: 37483.333
A21: Summer Fun | B21: 0 | C21: Kelly Hard Cider | D21: Kelly Summer Spritzer | E21: Korea SMB | F21: Q2 Summer Blitz | H21: Photo Retouching & Post | I21: Summer Fun | J21: Interstate_SummerFun_Retouching | K21: Original | L21: 36200 | M21: firm-bid | S21: 1 | U21: 0 | V21: 0 | W21: 37483.333
A22: Summer Fun | B22: 1 | C22: Kelly Hard Cider | D22: Kelly Summer Spritzer | E22: Korea SMB | F22: Q2 Summer Blitz | G22: Buck & Archie | H22: Photo Retouching & Post | I22: Buck & Archie "Kelly Hard Cider:Summer Fun" v2 | J22: BuckandArchie_SummerFun_Retouching | K22: Original | L22: 37000 | M22: firm-bid | N22: 37483.333 | U22: 0 | V22: 0 | W22: 37483.333 | X22: 37000 | Y22: 37000
A23: Summer Fun | B23: 0 | C23: Kelly Hard Cider | D23: Kelly Summer Spritzer | E23: Korea SMB | F23: Q2 Summer Blitz | H23: Still Photography Production | I23: Kent Wilson Studio Estimate for "Summer Fun" #1 | J23: KentWilsonStudio_SummerFun_Stills | K23: Original | L23: 161541.3 | M23: firm-bid | P23: 1 | U23: 0 | V23: 0 | W23: 145472.98
A24: Summer Fun | B24: 0 | C24: Kelly Hard Cider | D24: Kelly Summer Spritzer | E24: Korea SMB | F24: Q2 Summer Blitz | H24: Still Photography Production | I24: Summer Fun | J24: Interstate_SummerFun_Stills | K24: Original | L24: 138331.55 | M24: firm-bid | S24: 1 | U24: 0 | V24: 0 | W24: 145472.98
A25: Summer Fun | B25: 1 | C25: Kelly Hard Cider | D25: Kelly Summer Spritzer | E25: Korea SMB | F25: Q2 Summer Blitz | G25: Buck & Archie | H25: Still Photography Production | I25: Buck & Archie "Kelly Hard Cider:Summer Fun" v2 | J25: BuckandArchie_SummerFun_Stills | K25: Original | L25: 136546.09 | M25: firm-bid | N25: 145472.98 | U25: 0 | V25: 0 | W25: 145472.98 | X25: 136546.09 | Y25: 136546.09
A26: Summer Fun | B26: 0 | C26: Kelly Hard Cider | D26: Kelly Summer Spritzer | E26: Korea SMB | F26: Q2 Summer Blitz | H26: Music | I26: AEM "Kelly Summer Spritzer || Q2 Summer Blitz" | J26: ArnoldEstherMusic_SummerFun_Music | K26: Original | L26: 8700 | M26: firm-bid | U26: 0 | V26: 0 | W26: 38916.667
A27: Summer Fun | B27: 0 | C27: Kelly Hard Cider | D27: Kelly Summer Spritzer | E27: Korea SMB | F27: Q2 Summer Blitz | H27: Music | I27: "Summer Fun" - Special Oaks Music | J27: SpecialOaks_SummerFun_Music | K27: Original | L27: 69900 | M27: firm-bid | U27: 0 | V27: 0 | W27: 38916.667
A28: Summer Fun | B28: 1 | C28: Kelly Hard Cider | D28: Kelly Summer Spritzer | E28: Korea SMB | F28: Q2 Summer Blitz | G28: Tone & Logic | H28: Music | I28: T+L for "Kelly's Summer Fun" | J28: ToneandLogic_SummerFun_Music | K28: Original | L28: 38150 | M28: firm-bid | N28: 38916.667 | T28: 1 | U28: 0 | V28: 0 | W28: 38916.667 | X28: 38150 | Y28: 38150
A29: The Traveller UK | B29: 0 | C29: Dewey North | D29: Dewey North 107º | E29: Last Station Group | F29: The Sophisticated Traveller | H29: Audio Post | I29: Special Oaks"The Traveller UK" | J29: Special Oaks | K29: Original | L29: 24800 | M29: firm-bid | O29: 1 | T29: 1 | U29: 24800 | V29: 0 | W29: 33935
A30: The Traveller UK | B30: 1 | C30: Dewey North | D30: Dewey North 107º | E30: Last Station Group | F30: The Sophisticated Traveller | G30: Love Language | H30: Audio Post | I30: Love Language "The Traveller UK" | J30: Love126 | K30: Original | L30: 43070 | M30: firm-bid | N30: 33935 | U30: 0 | V30: 0 | W30: 33935 | X30: 43070 | Y30: 43070
A31: The Traveller UK | B31: 1 | C31: Dewey North | D31: Dewey North 107º | E31: Last Station Group | F31: The Sophisticated Traveller | G31: Love Language | H31: Music | I31: Love Language "The Traveller UK" - MUSIC ONLY | J31: LoveLanguage_TheTravellerUK_Music | K31: Original | L31: 20800 | M31: firm-bid | N31: 40150 | U31: 0 | V31: 0 | W31: 40150 | X31: 20800 | Y31: 20800
A32: The Traveller UK | B32: 0 | C32: Dewey North | D32: Dewey North 107º | E32: Last Station Group | F32: The Sophisticated Traveller | H32: Music | I32: Frequency Presentation for "The Traveller UK" | J32: Frequency_TheTravellerUK_Music | K32: Original | L32: 49050 | M32: firm-bid | U32: 0 | V32: 0 | W32: 40150
A33: The Traveller UK | B33: 0 | C33: Dewey North | D33: Dewey North 107º | E33: Last Station Group | F33: The Sophisticated Traveller | H33: Music | I33: AEM "Dewey North || The Sophisticated Traveller (UK)" | J33: ArnoldEstherMusic_TheTravellerUK_Music | K33: Original | L33: 50600 | M33: firm-bid | U33: 0 | V33: 0 | W33: 40150
A34: The Traveller UK | B34: 1 | C34: Dewey North | D34: Dewey North 107º | E34: Last Station Group | F34: The Sophisticated Traveller | G34: EFX VFX | H34: VFX | I34: EFXvfx \\ "The Traveller UK" \\ v3 | J34: EFXVFX_TheTravellerUK_VFX | K34: Original | L34: 116454 | M34: firm-bid | N34: 104828.75 | U34: 0 | V34: 0 | W34: 104828.75 | X34: 116454 | Y34: 116454
A35: The Traveller UK | B35: 0 | C35: Dewey North | D35: Dewey North 107º | E35: Last Station Group | F35: The Sophisticated Traveller | H35: VFX | I35: v2 - "The Traveller UK" //SORCERY | J35: Sorcery_TheTravellerUK_VFX | K35: Original | L35: 93203.5 | M35: firm-bid | U35: 0 | V35: 0 | W35: 104828.75
A36: The Traveller UK | B36: 0 | C36: Dewey North | D36: Dewey North 107º | E36: Last Station Group | F36: The Sophisticated Traveller | H36: Finishing | I36: colorMaven for "The Traveller UK" v3 | J36: ColorMaven_TheTravellerUK_Finishing | K36: Original | L36: 17500 | M36: firm-bid | S36: 1 | U36: 0 | V36: 0 | W36: 32250
A37: The Traveller UK | B37: 1 | C37: Dewey North | D37: Dewey North 107º | E37: Last Station Group | F37: The Sophisticated Traveller | G37: Andiamo Images | H37: Finishing | I37: Andiamo for "The Traveller" (UK Version) | J37: AndiamoImages_TheTravellerUK_Finishing | K37: Original | L37: 49250 | M37: firm-bid | N37: 32250 | O37: 1 | S37: 1 | U37: 49250 | V37: 49250 | W37: 32250 | X37: 49250 | Y37: 49250
A38: The Traveller UK | B38: 0 | C38: Dewey North | D38: Dewey North 107º | E38: Last Station Group | F38: The Sophisticated Traveller | H38: Finishing | I38: ‚ÄúThe Traveller UK‚Äù - POI | J38: PersonsofInterest_TheTravellerUK_Finishing | K38: Original | L38: 30000 | M38: firm-bid | R38: 1 | U38: 0 | V38: 0 | W38: 32250
A39: The Traveller UK | B39: 1 | C39: Dewey North | D39: Dewey North 107º | E39: Last Station Group | F39: The Sophisticated Traveller | G39: Myrtle Row Editorial | H39: Editorial | I39: The Traveller UK | J39: MyrtleRow_TheTravellerUK_Edit | K39: Original | L39: 95889.792 | M39: firm-bid | N39: 93203.872 | T39: 1 | U39: 0 | V39: 0 | W39: 93203.872 | X39: 95889.792 | Y39: 95889.792
A40: The Traveller UK | B40: 0 | C40: Dewey North | D40: Dewey North 107º | E40: Last Station Group | F40: The Sophisticated Traveller | H40: Editorial | I40: The Traveller UK | J40: TotalCuts_TheTravellerUK_Edit | K40: Original | L40: 67406.617 | M40: firm-bid | Q40: 1 | U40: 0 | V40: 0 | W40: 93203.872
A41: The Traveller UK | B41: 0 | C41: Dewey North | D41: Dewey North 107º | E41: Last Station Group | F41: The Sophisticated Traveller | H41: Editorial | I41: The Traveller UK | J41: Fightclub_TheTravellerUK_Edit | K41: Original | L41: 116315.21 | M41: firm-bid | U41: 0 | V41: 0 | W41: 93203.872
A42: The Traveller UK | B42: 1 | C42: Dewey North | D42: Dewey North 107º | E42: Last Station Group | F42: The Sophisticated Traveller | G42: Harmony & Light | H42: Green Production Costs | I42: The Traveller UK | J42: harmony_and_Light_TheTravellerUK_Green | K42: Original | L42: 10250 | M42: firm-bid | N42: 9606 | U42: 0 | V42: 0 | W42: 9606 | X42: 10250 | Y42: 10250
A43: The Traveller UK | B43: 0 | C43: Dewey North | D43: Dewey North 107º | E43: Last Station Group | F43: The Sophisticated Traveller | H43: Green Production Costs | I43: The Traveller UK | J43: Level12_TheTravellerUK_Green | K43: Original | L43: 8568 | M43: firm-bid | O43: 1 | U43: 8568 | V43: 0 | W43: 9606
A44: The Traveller UK | B44: 0 | C44: Dewey North | D44: Dewey North 107º | E44: Last Station Group | F44: The Sophisticated Traveller | H44: Green Production Costs | I44: The Traveller UK | J44: OpenFrameworks_TheTravellerUK_Green | K44: Original | L44: 10000 | M44: firm-bid | O44: 1 | P44: 1 | U44: 10000 | V44: 0 | W44: 9606
A45: The Traveller UK | B45: 1 | C45: Dewey North | D45: Dewey North 107º | E45: Last Station Group | F45: The Sophisticated Traveller | G45: Harmony & Light | H45: Sanitary Production Costs | I45: The Traveller UK | J45: harmony_and_Light_TheTravellerUK_Covid | K45: Original | L45: 7200.035 | M45: firm-bid | N45: 9810.1133 | U45: 0 | V45: 0 | W45: 9810.1133 | X45: 7200.035 | Y45: 7200.035
A46: The Traveller UK | B46: 0 | C46: Dewey North | D46: Dewey North 107º | E46: Last Station Group | F46: The Sophisticated Traveller | H46: Sanitary Production Costs | I46: The Traveller UK | J46: Level12_TheTravellerUK_Covid | K46: Original | L46: 12958.487 | M46: firm-bid | O46: 1 | U46: 12958.487 | V46: 0 | W46: 9810.1133
A47: The Traveller UK | B47: 0 | C47: Dewey North | D47: Dewey North 107º | E47: Last Station Group | F47: The Sophisticated Traveller | H47: Sanitary Production Costs | I47: The Traveller UK | J47: OpenFrameworks_TheTravellerUK_Covid | K47: Original | L47: 9271.8175 | M47: firm-bid | O47: 1 | P47: 1 | U47: 9271.8175 | V47: 0 | W47: 9810.1133
A48: The Traveller UK | B48: 1 | C48: Dewey North | D48: Dewey North 107º | E48: Last Station Group | F48: The Sophisticated Traveller | G48: Harmony & Light | H48: Film & Video Production | I48: The Traveller UK | J48: harmony_and_Light_TheTravellerUK_LiveAction | K48: Original | L48: 685626.9 | M48: firm-bid | N48: 649602.48 | U48: 0 | V48: 0 | W48: 649602.48 | X48: 685626.9 | Y48: 685626.9
A49: The Traveller UK | B49: 0 | C49: Dewey North | D49: Dewey North 107º | E49: Last Station Group | F49: The Sophisticated Traveller | H49: Film & Video Production | I49: The Traveller UK | J49: Level12_TheTravellerUK_LiveAction | K49: Original | L49: 673878.44 | M49: firm-bid | O49: 1 | U49: 673878.44 | V49: 0 | W49: 649602.48
A50: The Traveller UK | B50: 0 | C50: Dewey North | D50: Dewey North 107º | E50: Last Station Group | F50: The Sophisticated Traveller | H50: Film & Video Production | I50: The Traveller UK | J50: OpenFrameworks_TheTravellerUK_LiveAction | K50: Original | L50: 589302.09 | M50: firm-bid | O50: 1 | P50: 1 | U50: 589302.09 | V50: 0 | W50: 649602.48
A51: The Traveller US | B51: 0 | C51: Dewey North | D51: Dewey North 107º | E51: Top Notch Creative | F51: The Sophisticated Traveller | H51: Audio Post | I51: Earwax "The Traveller US" | J51: Earwax | K51: Original | L51: 29320 | M51: firm-bid | U51: 0 | V51: 0 | W51: 48990
A52: The Traveller US | B52: 1 | C52: Dewey North | D52: Dewey North 107º | E52: Top Notch Creative | F52: The Sophisticated Traveller | G52: Audio Lab Technologies | H52: Audio Post | I52: Audio Lab"The Traveller US" | J52: Audio_85 | K52: Original | L52: 68660 | M52: firm-bid | N52: 48990 | Q52: 1 | S52: 1 | U52: 0 | V52: 0 | W52: 48990 | X52: 68660 | Y52: 68660
A53: The Traveller US | B53: 0 | C53: Dewey North | D53: Dewey North 107º | E53: Top Notch Creative | F53: The Sophisticated Traveller | H53: Behind The Scenes (BTS) | I53: The Traveller (US Version) | J53: Club101_SummerFun_BTS | K53: Original | L53: 22844.75 | M53: firm-bid | U53: 0 | V53: 0 | W53: 18774.708
A54: The Traveller US | B54: 1 | C54: Dewey North | D54: Dewey North 107º | E54: Top Notch Creative | F54: The Sophisticated Traveller | G54: Test Flight Productions | H54: Behind The Scenes (BTS) | I54: The Traveller (for US) | J54: TestFlight_TheTravellerUS_BTS | K54: Original | L54: 19457.425 | M54: firm-bid | N54: 18774.708 | T54: 1 | U54: 0 | V54: 0 | W54: 18774.708 | X54: 19457.425 | Y54: 19457.425
A55: The Traveller US | B55: 0 | C55: Dewey North | D55: Dewey North 107º | E55: Top Notch Creative | F55: The Sophisticated Traveller | H55: Behind The Scenes (BTS) | I55: The Traveller US V2 | J55: CHAW_TheTravellerUS_BTSv2 | K55: Original | L55: 14021.95 | M55: firm-bid | P55: 1 | T55: 1 | U55: 0 | V55: 0 | W55: 18774.708
A56: The Traveller US | B56: 1 | C56: Dewey North | D56: Dewey North 107º | E56: Top Notch Creative | F56: The Sophisticated Traveller | G56: Tone & Logic | H56: Music | I56: T+L for "Dewey North - The Traveller (US)" | J56: ToneandLogic_TheTravellerUS_Music | K56: Original | L56: 15950 | M56: firm-bid | N56: 30350 | T56: 1 | U56: 0 | V56: 0 | W56: 30350 | X56: 15950 | Y56: 15950
A57: The Traveller US | B57: 0 | C57: Dewey North | D57: Dewey North 107º | E57: Top Notch Creative | F57: The Sophisticated Traveller | H57: Music | I57: Love Language "The Traveller US" v2 | J57: LoveLanguage_TheTravellerUS_Music | K57: Original | L57: 34650 | M57: firm-bid | U57: 0 | V57: 0 | W57: 30350
A58: The Traveller US | B58: 0 | C58: Dewey North | D58: Dewey North 107º | E58: Top Notch Creative | F58: The Sophisticated Traveller | H58: Music | I58: Frequency Presentation for "The Traveller US " | J58: Frequency_TheTravellerUS_Music | K58: Original | L58: 40450 | M58: firm-bid | U58: 0 | V58: 0 | W58: 30350
A59: The Traveller US | B59: 0 | C59: Dewey North | D59: Dewey North 107º | E59: Top Notch Creative | F59: The Sophisticated Traveller | H59: Finishing | I59: ‚ÄúThe Traveller US ‚Äù - POI | J59: PersonsofInterest_TheTravellerUS_Finishing | K59: Original | L59: 14900 | M59: firm-bid | R59: 1 | U59: 0 | V59: 0 | W59: 27083.333
A60: The Traveller US | B60: 0 | C60: Dewey North | D60: Dewey North 107º | E60: Top Notch Creative | F60: The Sophisticated Traveller | H60: Finishing | I60: EB "The Traveller US" | J60: EvanBanderLLC_TheTravellerUS_Finishing | K60: Original | L60: 47450 | M60: firm-bid | R60: 1 | T60: 1 | U60: 0 | V60: 0 | W60: 27083.333
A61: The Traveller US | B61: 1 | C61: Dewey North | D61: Dewey North 107º | E61: Top Notch Creative | F61: The Sophisticated Traveller | G61: The Dub House | H61: Finishing | I61: ‚ÄúThe Traveller US‚Äù | Dub House | J61: TheDubHouse_TheTravellerUS_Finishing | K61: Original | L61: 18900 | M61: firm-bid | N61: 27083.333 | U61: 0 | V61: 0 | W61: 27083.333 | X61: 18900 | Y61: 18900
A62: The Traveller US | B62: 0 | C62: Dewey North | D62: Dewey North 107º | E62: Top Notch Creative | F62: The Sophisticated Traveller | H62: Editorial | I62: The Traveller US | J62: TotalCuts_TheTravellerUS_Edit | K62: Original | L62: 56933.45 | M62: firm-bid | Q62: 1 | U62: 0 | V62: 0 | W62: 93441.483
A63: The Traveller US | B63: 1 | C63: Dewey North | D63: Dewey North 107º | E63: Top Notch Creative | F63: The Sophisticated Traveller | G63: The Closet | H63: Editorial | I63: The Traveller US | J63: TheCloset_TheTravellerUS_Edit | K63: Original | L63: 100975.58 | M63: firm-bid | N63: 93441.483 | S63: 1 | T63: 1 | U63: 0 | V63: 0 | W63: 93441.483 | X63: 100975.58 | Y63: 100975.58
A64: The Traveller US | B64: 0 | C64: Dewey North | D64: Dewey North 107º | E64: Top Notch Creative | F64: The Sophisticated Traveller | H64: Editorial | I64: The Traveller US | J64: SaksStreetEdit_TheTravellerUS_Edit | K64: Original | L64: 122415.42 | M64: firm-bid | T64: 1 | U64: 0 | V64: 0 | W64: 93441.483
A65: The Traveller US | B65: 0 | C65: Dewey North | D65: Dewey North 107º | E65: Top Notch Creative | F65: The Sophisticated Traveller | H65: Green Production Costs | I65: The Traveller (US Version) | J65: Club101_SummerFun_Green | K65: Original | L65: 12400 | M65: firm-bid | U65: 0 | V65: 0 | W65: 11703.333
A66: The Traveller US | B66: 1 | C66: Dewey North | D66: Dewey North 107º | E66: Top Notch Creative | F66: The Sophisticated Traveller | G66: Test Flight Productions | H66: Green Production Costs | I66: The Traveller (for US) | J66: TestFlight_TheTravellerUS_Green | K66: Original | L66: 13750 | M66: firm-bid | N66: 11703.333 | T66: 1 | U66: 0 | V66: 0 | W66: 11703.333 | X66: 13750 | Y66: 13750
A67: The Traveller US | B67: 0 | C67: Dewey North | D67: Dewey North 107º | E67: Top Notch Creative | F67: The Sophisticated Traveller | H67: Green Production Costs | I67: The Traveller US V2 | J67: CHAW_TheTravellersFriend_Green | K67: Original | L67: 8960 | M67: firm-bid | P67: 1 | T67: 1 | U67: 0 | V67: 0 | W67: 11703.333
A68: The Traveller US | B68: 0 | C68: Dewey North | D68: Dewey North 107º | E68: Top Notch Creative | F68: The Sophisticated Traveller | H68: Sanitary Production Costs | I68: The Traveller (US Version) | J68: Club101_TheTravellerUS_Covid | K68: Original | L68: 7010.975 | M68: firm-bid | U68: 0 | V68: 0 | W68: 7058.24
A69: The Traveller US | B69: 1 | C69: Dewey North | D69: Dewey North 107º | E69: Top Notch Creative | F69: The Sophisticated Traveller | G69: Test Flight Productions | H69: Sanitary Production Costs | I69: The Traveller (for US) | J69: TestFlight_TheTravellerUS_Covid | K69: Original | L69: 5317.3125 | M69: firm-bid | N69: 7058.24 | T69: 1 | U69: 0 | V69: 0 | W69: 7058.24 | X69: 5317.3125 | Y69: 5317.3125
A70: The Traveller US | B70: 0 | C70: Dewey North | D70: Dewey North 107º | E70: Top Notch Creative | F70: The Sophisticated Traveller | H70: Sanitary Production Costs | I70: The Traveller US V2 | J70: CHAW_TheTravellerUS_Covid | K70: Original | L70: 8846.4325 | M70: firm-bid | P70: 1 | T70: 1 | U70: 0 | V70: 0 | W70: 7058.24
A71: The Traveller US | B71: 0 | C71: Dewey North | D71: Dewey North 107º | E71: Top Notch Creative | F71: The Sophisticated Traveller | H71: Film & Video Production | I71: The Traveller (US Version) | J71: Club101_TheTravellerUS_LiveAction | K71: Original | L71: 748472.66 | M71: firm-bid | U71: 0 | V71: 0 | W71: 835635.38
A72: The Traveller US | B72: 1 | C72: Dewey North | D72: Dewey North 107º | E72: Top Notch Creative | F72: The Sophisticated Traveller | G72: Test Flight Productions | H72: Film & Video Production | I72: The Traveller (for US) | J72: TestFlight_TheTravellerUS_LiveAction | K72: Original | L72: 856318.5 | M72: firm-bid | N72: 835635.38 | T72: 1 | U72: 0 | V72: 0 | W72: 835635.38 | X72: 856318.5 | Y72: 856318.5
A73: The Traveller US | B73: 0 | C73: Dewey North | D73: Dewey North 107º | E73: Top Notch Creative | F73: The Sophisticated Traveller | H73: Film & Video Production | I73: The Traveller US V2 | J73: CHAW_TheTravellerUS_LiveAction | K73: Original | L73: 902114.97 | M73: firm-bid | P73: 1 | T73: 1 | U73: 0 | V73: 0 | W73: 835635.38
A74: The Traveller Settles Down | B74: 0 | C74: Dewey North | D74: Dewey North 80¬∫ | E74: Top Notch Creative | F74: The Sophisticated Traveller | H74: Audio Post | I74: Earwax "The Traveller Settles Down" | J74: Earwax | K74: Original | L74: 35540 | M74: firm-bid | U74: 0 | V74: 0 | W74: 52025
A75: The Traveller Settles Down | B75: 1 | C75: Dewey North | D75: Dewey North 80¬∫ | E75: Top Notch Creative | F75: The Sophisticated Traveller | G75: Sound Monster | H75: Audio Post | I75: Sound Monster"The Traveller Settles Down" | J75: Sound Monster | K75: Original | L75: 68510 | M75: firm-bid | N75: 52025 | R75: 1 | U75: 0 | V75: 0 | W75: 52025 | X75: 68510 | Y75: 68510
A76: The Traveller Settles Down | B76: 0 | C76: Dewey North | D76: Dewey North 80¬∫ | E76: Top Notch Creative | F76: The Sophisticated Traveller | H76: Music | I76: "The Traveller Settles Down" v2 | J76: M52_TheTravellerSettlesDown_Music | K76: Original | L76: 8600 | M76: firm-bid | O76: 1 | S76: 1 | U76: 8600 | V76: 0 | W76: 40166.667
A77: The Traveller Settles Down | B77: 1 | C77: Dewey North | D77: Dewey North 80¬∫ | E77: Top Notch Creative | F77: The Sophisticated Traveller | G77: Love Language | H77: Music | I77: Love Language "The Traveller Settles Down" v2 | J77: LoveLanguage_TheTravellerSettlesDown_Music | K77: Original | L77: 52150 | M77: firm-bid | N77: 40166.667 | U77: 0 | V77: 0 | W77: 40166.667 | X77: 52150 | Y77: 52150
A78: The Traveller Settles Down | B78: 0 | C78: Dewey North | D78: Dewey North 80¬∫ | E78: Top Notch Creative | F78: The Sophisticated Traveller | H78: Music | I78: T+L for "Dewey North - The Traveller Settles Down" | J78: ToneandLogic_TheTravellerSettlesDown_Music | K78: Original | L78: 59750 | M78: firm-bid | T78: 1 | U78: 0 | V78: 0 | W78: 40166.667
A79: The Traveller Settles Down | B79: 1 | C79: Dewey North | D79: Dewey North 80¬∫ | E79: Top Notch Creative | F79: The Sophisticated Traveller | G79: Sorcery | H79: VFX | I79: v5 - "The Traveller Settles Down" //SORCERY | J79: Sorcery_TheTravellerSettlesDown_VFX | K79: Original | L79: 80541.5 | M79: firm-bid | N79: 79204.667 | U79: 0 | V79: 0 | W79: 79204.667 | X79: 80541.5 | Y79: 80541.5
A80: The Traveller Settles Down | B80: 0 | C80: Dewey North | D80: Dewey North 80¬∫ | E80: Top Notch Creative | F80: The Sophisticated Traveller | H80: VFX | I80: "The Traveller Settles Down" JOB #4001 | J80: TerminalOutput_TheTravellerSettlesDown_VFX | K80: Original | L80: 92170 | M80: firm-bid | U80: 0 | V80: 0 | W80: 79204.667
A81: The Traveller Settles Down | B81: 0 | C81: Dewey North | D81: Dewey North 80¬∫ | E81: Top Notch Creative | F81: The Sophisticated Traveller | H81: VFX | I81: "The Traveller Settles Down" by CJ #4 | J81: CalamityJane_TheTravellerSettlesDown_VFX | K81: Original | L81: 64902.5 | M81: firm-bid | S81: 1 | U81: 0 | V81: 0 | W81: 79204.667
A82: The Traveller Settles Down | B82: 0 | C82: Dewey North | D82: Dewey North 80¬∫ | E82: Top Notch Creative | F82: The Sophisticated Traveller | H82: Finishing | I82: The Traveller Settles Down Burnish | J82: Burnish_TheTravellerSettlesDown_Finishing | K82: Original | L82: 8850 | M82: firm-bid | S82: 1 | U82: 0 | V82: 0 | W82: 18050
A83: The Traveller Settles Down | B83: 1 | C83: Dewey North | D83: Dewey North 80¬∫ | E83: Top Notch Creative | F83: The Sophisticated Traveller | G83: Witness | H83: Finishing | I83: WITNESS:: The Traveller Settles Down V2 | J83: Witness_TheTravellerSettlesDown_Finishing | K83: Original | L83: 28600 | M83: firm-bid | N83: 18050 | Q83: 1 | R83: 1 | U83: 0 | V83: 0 | W83: 18050 | X83: 28600 | Y83: 28600
A84: The Traveller Settles Down | B84: 0 | C84: Dewey North | D84: Dewey North 80¬∫ | E84: Top Notch Creative | F84: The Sophisticated Traveller | H84: Finishing | I84: colorMaven "The Traveller Settles Down" | K84: Original | L84: 16700 | M84: firm-bid | S84: 1 | U84: 0 | V84: 0 | W84: 18050
A85: The Traveller Settles Down | B85: 0 | C85: Dewey North | D85: Dewey North 80¬∫ | E85: Top Notch Creative | F85: The Sophisticated Traveller | H85: Editorial | I85: The Traveller Settles Down | J85: ToTo_TheTravellerSettlesDown_Edit | K85: Original | L85: 112476.88 | M85: firm-bid | U85: 0 | V85: 0 | W85: 100943.6
A86: The Traveller Settles Down | B86: 1 | C86: Dewey North | D86: Dewey North 80¬∫ | E86: Top Notch Creative | F86: The Sophisticated Traveller | G86: Armistice Edit | H86: Editorial | I86: The Traveller Settles Down | J86: Armistace_TheTravellerSettlesDown_Edit | K86: Original | L86: 111615.99 | M86: firm-bid | N86: 100943.6 | U86: 0 | V86: 0 | W86: 100943.6 | X86: 111615.99 | Y86: 111615.99
A87: The Traveller Settles Down | B87: 0 | C87: Dewey North | D87: Dewey North 80¬∫ | E87: Top Notch Creative | F87: The Sophisticated Traveller | H87: Editorial | I87: The Traveller Settles Down | J87: MyrtleRow_TheTravellerSettlesDown_Edit | K87: Original | L87: 78737.925 | M87: firm-bid | T87: 1 | U87: 0 | V87: 0 | W87: 100943.6
A88: The Traveller Settles Down | B88: 0 | C88: Dewey North | D88: Dewey North 80¬∫ | E88: Top Notch Creative | F88: The Sophisticated Traveller | H88: Green Production Costs | I88: TTSD | J88: Interstate_TheTravellerSettlesDown_Green | K88: Original | L88: 6875 | M88: firm-bid | S88: 1 | U88: 0 | V88: 0 | W88: 8766.3333
A89: The Traveller Settles Down | B89: 1 | C89: Dewey North | D89: Dewey North 80¬∫ | E89: Top Notch Creative | F89: The Sophisticated Traveller | G89: Open Frameworks Image Creation | H89: Green Production Costs | I89: The Traveller Settles Down | J89: OpenFrameworks_TheTravellerSettlesDown_Green | K89: Original | L89: 8928 | M89: firm-bid | N89: 8766.3333 | O89: 1 | P89: 1 | U89: 8928 | V89: 8928 | W89: 8766.3333 | X89: 8928 | Y89: 8928
A90: The Traveller Settles Down | B90: 0 | C90: Dewey North | D90: Dewey North 80¬∫ | E90: Top Notch Creative | F90: The Sophisticated Traveller | H90: Green Production Costs | I90: TTSD | J90: Petulant_TheTravellerSettlesDown_Green | K90: Original | L90: 10496 | M90: firm-bid | O90: 1 | U90: 10496 | V90: 0 | W90: 8766.3333
A91: The Traveller Settles Down | B91: 0 | C91: Dewey North | D91: Dewey North 80¬∫ | E91: Top Notch Creative | F91: The Sophisticated Traveller | H91: Sanitary Production Costs | I91: TTSD | J91: Interstate_TheTravellerSettlesDown_Covid | K91: Original | L91: 10484.952 | M91: firm-bid | S91: 1 | U91: 0 | V91: 0 | W91: 7291.9392
A92: The Traveller Settles Down | B92: 1 | C92: Dewey North | D92: Dewey North 80¬∫ | E92: Top Notch Creative | F92: The Sophisticated Traveller | G92: Open Frameworks Image Creation | H92: Sanitary Production Costs | I92: The Traveller Settles Down | J92: OpenFrameworks_TheTravellerSettlesDown_Covid | K92: Original | L92: 6664.365 | M92: firm-bid | N92: 7291.9392 | O92: 1 | P92: 1 | U92: 6664.365 | V92: 6664.365 | W92: 7291.9392 | X92: 6664.365 | Y92: 6664.365
A93: The Traveller Settles Down | B93: 0 | C93: Dewey North | D93: Dewey North 80¬∫ | E93: Top Notch Creative | F93: The Sophisticated Traveller | H93: Sanitary Production Costs | I93: TTSD | J93: Petulant_TheTravellerSettlesDown_Covid | K93: Original | L93: 4726.5 | M93: firm-bid | O93: 1 | U93: 4726.5 | V93: 0 | W93: 7291.9392
A94: The Traveller Settles Down | B94: 0 | C94: Dewey North | D94: Dewey North 80¬∫ | E94: Top Notch Creative | F94: The Sophisticated Traveller | H94: Film & Video Production | I94: TTSD | J94: Interstate_TheTravellerSettlesDown_LiveAction | K94: Original | L94: 702418.88 | M94: firm-bid | S94: 1 | U94: 0 | V94: 0 | W94: 656708.29
A95: The Traveller Settles Down | B95: 1 | C95: Dewey North | D95: Dewey North 80¬∫ | E95: Top Notch Creative | F95: The Sophisticated Traveller | G95: Open Frameworks Image Creation | H95: Film & Video Production | I95: The Traveller Settles Down | J95: OpenFrameworks_TheTravellerSettlesDown_LiveAction | K95: Original | L95: 621332.43 | M95: firm-bid | N95: 656708.29 | O95: 1 | P95: 1 | U95: 621332.43 | V95: 621332.43 | W95: 656708.29 | X95: 621332.43 | Y95: 621332.43
A96: The Traveller Settles Down | B96: 0 | C96: Dewey North | D96: Dewey North 80¬∫ | E96: Top Notch Creative | F96: The Sophisticated Traveller | H96: Film & Video Production | I96: TTSD | J96: Petulant_TheTravellerSettlesDown_LiveAction | K96: Original | L96: 646373.56 | M96: firm-bid | O96: 1 | U96: 646373.56 | V96: 0 | W96: 656708.29
A97: Designated Dad | B97: 0 | C97: Walker's | D97: Walker's N/A | E97: Aster PPK | F97: Party Light | H97: Audio Post | I97: Sound Monster "Designated Dad" | J97: Sound Monster | K97: Original | L97: 50580 | M97: firm-bid | U97: 0 | V97: 0 | W97: 36220
A98: Designated Dad | B98: 0 | C98: Walker's | D98: Walker's N/A | E98: Aster PPK | F98: Party Light | H98: Audio Post | I98: Funny Rabbit "Designated Dad" | J98: Funny Rabbit | K98: Original | L98: 18410 | M98: firm-bid | O98: 1 | P98: 1 | R98: 1 | S98: 1 | U98: 18410 | V98: 0 | W98: 36220
A99: Designated Dad | B99: 1 | C99: Walker's | D99: Walker's N/A | E99: Aster PPK | F99: Party Light | G99: Earwax | H99: Audio Post | I99: Earwax | J99: Earwax | K99: Original | L99: 39670 | M99: firm-bid | N99: 36220 | U99: 0 | V99: 0 | W99: 36220 | X99: 39670 | Y99: 39670
A100: Designated Dad | B100: 0 | C100: Walker's | D100: Walker's N/A | E100: Aster PPK | F100: Party Light | H100: Photo Retouching & Post | I100: DesDad | J100: Interstate_DesignatedDad_Retouching | K100: Original | L100: 21700 | M100: firm-bid | S100: 1 | U100: 0 | V100: 0 | W100: 25166.667
...

Sheet New Sankey
A1: Row Labels | B1: Sum of BID TOTAL | C1: Sum of Women Work Pitched | D1: Sum of Women Work Awarded | E1: Sum of Total Award | G1: Row Labels | H1: Sum of Women Work Pitched | I1: Sum of Women Work Awarded | K1: Agency | L1: Pitched | M1: Awarded
A2: Audio Post | B2: 2663120 | C2: 434880 | D2: 225190 | E2: 1127400 | G2: Aster PPK | H2: 2723028.5 | I2: 1002751 | K2: =G2 -> Aster PPK | L2: =H2 -> 2723028.5 | M2: =I2 -> 1002751
A3: Behind The Scenes (BTS) | B3: 335817.83 | C3: 74757.475 | D3: 36236.5 | E3: 124070.62 | G3: Cantor Asia Media | H3: 1746051.4 | I3: 833932.81 | K3: =G3 -> Cantor Asia Media | L3: =H3 -> 1746051.4 | M3: =I3 -> 833932.81
A4: Editorial | B4: 9593788.1 | C4: 0 | D4: 0 | E4: 3528420.8 | G4: Geoffrey Monty Allen | H4: 920570.16 | I4: 183460 | K4: =G4 -> Geoffrey Monty Allen | L4: =H4 -> 920570.16 | M4: =I4 -> 183460
A5: Film & Video Production | B5: 64143459 | C5: 8828244.8 | D5: 3126995.8 | E5: 23213713 | G5: Idea Manufacturing | H5: 0 | I5: 0 | K5: =G5 -> Idea Manufacturing | L5: =H5 -> 0 | M5: =I5 -> 0
A6: Finishing | B6: 2500550 | C6: 49250 | D6: 49250 | E6: 1107850 | G6: Korea SMB | H6: 1691093.3 | I6: 1004228.3 | K6: =G6 -> Korea SMB | L6: =H6 -> 1691093.3 | M6: =I6 -> 1004228.3
A7: Green Production Costs | B7: 825054 | C7: 140452 | D7: 51526 | E7: 295508 | G7: Last Station Group | H7: 1378028.8 | I7: 49250 | K7: =G7 -> Last Station Group | L7: =H7 -> 1378028.8 | M7: =I7 -> 49250
A8: Music | B8: 697000 | C8: 8600 | D8: 0 | E8: 231750 | G8: Top Notch Creative | H8: 1943021.8 | I8: 636924.79 | K8: =G8 -> Top Notch Creative | L8: =H8 -> 1943021.8 | M8: =I8 -> 636924.79
A9: Photo Retouching & Post | B9: 830150 | C9: 114250 | D9: 12500 | E9: 311500 | G9: Grand Total | H9: 10401794 | I9: 3710547
A10: Sanitary Production Costs | B10: 571764.71 | C10: 90725.167 | D10: 21025.048 | E10: 192053.45
A11: Still Photography Production | B11: 3693749.9 | C11: 660634.55 | D11: 187823.63 | E11: 1420184.1
A12: VFX | B12: 1429070.5 | C12: 0 | D12: 0 | E12: 575991
A13: Grand Total | B13: 87283524 | C13: 10401794 | D13: 3710547 | E13: 32128441
H18: All Work | I18: 10000
H19: Awarded | I19: 3000
H20: Women | I20: 254

Sheet Sheet8
A1: Source | B1: Target | C1: Value | D1: Type | F1: Source | G1: Target | H1: Value | I1: Type
A2: Edit | B2: Edit pitch men | C2: =GETPIVOTDATA("Sum of BID TOTAL",'New Sankey'!$A$1,"PHASE","Editorial")-GETPIVOTDATA("Sum of Women Work Pitched",'New Sankey'!$A$1,"PHASE","Editorial") -> 9593788.1 | D2: input | F2: Production Pitch men | G2: Total Pitched | H2: =GETPIVOTDATA("Sum of BID TOTAL",'New Sankey'!$A$1,"PHASE","Film & Video Production")-GETPIVOTDATA("Sum of Women Work Pitched",'New Sankey'!$A$1,"PHASE","Film & Video Production") -> 55315214 | I2: input
A3: Edit | B3: Edit pitch women | C3: =GETPIVOTDATA("Sum of Women Work Pitched",'New Sankey'!$A$1,"PHASE","Editorial") -> 0 | D3: input | F3: Production Pitch Women | G3: Total Pitched | H3: =GETPIVOTDATA("Sum of Women Work Pitched",'New Sankey'!$A$1,"PHASE","Film & Video Production") -> 8828244.8 | I3: input
A4: Production | B4: Production Pitch men | C4: =GETPIVOTDATA("Sum of BID TOTAL",'New Sankey'!$A$1,"PHASE","Film & Video Production")-GETPIVOTDATA("Sum of Women Work Pitched",'New Sankey'!$A$1,"PHASE","Film & Video Production") -> 55315214 | D4: profit | F4: Post Pitch Men | G4: Total Pitched | H4: =C2+C6+C8+C16+C10 -> 16390799 | I4: profit
A5: Production | B5: Production Pitch Women | C5: =GETPIVOTDATA("Sum of Women Work Pitched",'New Sankey'!$A$1,"PHASE","Film & Video Production") -> 8828244.8 | D5: profit | F5: Post Pitch Women | G5: Total Pitched | H5: =C3+C7+C9+C11+C17 -> 492730 | I5: profit
A6: Audio | B6: Audio Pitch Men | C6: =GETPIVOTDATA("Sum of BID TOTAL",'New Sankey'!$A$1,"PHASE","Audio Post")-GETPIVOTDATA("Sum of Women Work Pitched",'New Sankey'!$A$1,"PHASE","Audio Post") -> 2228240 | D6: equity | F6: Stills Pitch Men | G6: Total Pitched | H6: =C12 -> 3749015.4 | I6: equity
A7: Audio | B7: Audio Pitch Women | C7: =GETPIVOTDATA("Sum of Women Work Pitched",'New Sankey'!$A$1,"PHASE","Audio Post") -> 434880 | D7: equity | F7: Stills Pitch Women | G7: Total Pitched | H7: =C13 -> 774884.55 | I7: equity
A8: Finishing | B8: Finishing Pitch Men | C8: =GETPIVOTDATA("Sum of BID TOTAL",'New Sankey'!$A$1,"PHASE","Finishing")-GETPIVOTDATA("Sum of Women Work Pitched",'New Sankey'!$A$1,"PHASE","Finishing") -> 2451300 | D8: input | F8: BTS Pitch Men | G8: Total Pitched | H8: =C14 -> 261060.35 | I8: input | L8: Edit pitch men | M8: Pitched | N8: 200 | O8: input
A9: Finishing | B9: Finishing Pitch Women | C9: =GETPIVOTDATA("Sum of Women Work Pitched",'New Sankey'!$A$1,"PHASE","Finishing") -> 49250 | D9: input | F9: BTS Pitch Women | G9: Total Pitched | H9: =C15 -> 74757.475 | I9: input | L9: Edit pitch women | M9: Pitched | N9: 1000 | O9: input
A10: Music | B10: Music Pitch Men | C10: =GETPIVOTDATA("Sum of BID TOTAL",'New Sankey'!$A$1,"PHASE","Music")-GETPIVOTDATA("Sum of Women Work Pitched",'New Sankey'!$A$1,"PHASE","Music") -> 688400 | D10: profit | F10: Total Pitched | G10: Production award men | H10: =GETPIVOTDATA("Sum of Total Award",'New Sankey'!$A$1,"PHASE","Film & Video Production")-GETPIVOTDATA("Sum of Women Work Awarded",'New Sankey'!$A$1,"PHASE","Film & Video Production") -> 20086717 | I10: profit | L10: Production Pitch men | M10: Pitched | N10: 8000 | O10: profit
A11: Music | B11: Music Pitch Women | C11: =GETPIVOTDATA("Sum of Women Work Pitched",'New Sankey'!$A$1,"PHASE","Music") -> 8600 | D11: profit | F11: Total Pitched | G11: Production award Women | H11: =GETPIVOTDATA("Sum of Women Work Awarded",'New Sankey'!$A$1,"PHASE","Film & Video Production") -> 3126995.8 | I11: equity | L11: Production Pitch Women | M11: Pitched | N11: 2000 | O11: profit
A12: Stills | B12: Stills Pitch Men | C12: =GETPIVOTDATA("Sum of BID TOTAL",'New Sankey'!$A$1,"PHASE","Still Photography Production")+GETPIVOTDATA("Sum of BID TOTAL",'New Sankey'!$A$1,"PHASE","Photo Retouching & Post")-GETPIVOTDATA("Sum of Women Work Pitched",'New Sankey'!$A$1,"PHASE","Photo Retouching & Post")-GETPIVOTDATA("Sum of Women Work Pitched",'New Sankey'!$A$1,"PHASE","Still Photography Production") -> 3749015.4 | D12: equity | F12: Total Pitched | G12: Post award Men | H12: =C35+C39+C41+C43+C49 -> 6296971.8 | I12: profit | L12: Audio Pitch Men | M12: Pitched | N12: 1500 | O12: equity
A13: Stills | B13: Stills Pitch Women | C13: =GETPIVOTDATA("Sum of Women Work Pitched",'New Sankey'!$A$1,"PHASE","Photo Retouching & Post")+GETPIVOTDATA("Sum of Women Work Pitched",'New Sankey'!$A$1,"PHASE","Still Photography Production") -> 774884.55 | D13: equity | F13: Total Pitched | G13: Post award Women | H13: =C36+C40+C42+C44+C50 -> 274440 | I13: equity | L13: Audio Pitch Women | M13: Pitched | N13: 500 | O13: equity
A14: BTS | B14: BTS Pitch Men | C14: =GETPIVOTDATA("Sum of BID TOTAL",'New Sankey'!$A$1,"PHASE","Behind The Scenes (BTS)")-GETPIVOTDATA("Sum of Women Work Pitched",'New Sankey'!$A$1,"PHASE","Behind The Scenes (BTS)") -> 261060.35 | D14: input | F14: Total Pitched | G14: stills Award Men | H14: =C45 -> 1531360.4 | I14: profit | L14: Pitched | M14: Edit Award men | N14: 1500 | O14: input
A15: BTS | B15: BTS Pitch Women | C15: =GETPIVOTDATA("Sum of Women Work Pitched",'New Sankey'!$A$1,"PHASE","Behind The Scenes (BTS)") -> 74757.475 | D15: input | F15: Total Pitched | G15: Stills AwardWomen | H15: =C46 -> 200323.63 | I15: equity | L15: Pitched | M15: Edit Award women | N15: 500 | O15: input
A16: VFX | B16: VFX Pitch Men | C16: =GETPIVOTDATA("Sum of BID TOTAL",'New Sankey'!$A$1,"PHASE","VFX")-GETPIVOTDATA("Sum of Women Work Pitched",'New Sankey'!$A$1,"PHASE","VFX") -> 1429070.5 | D16: profit | F16: Total Pitched | G16: BTS Award Men | H16: =C47 -> 87834.125 | I16: profit | L16: Pitched | M16: Production Award men | N16: 3000 | O16: profit
A17: VFX | B17: VFX Pitch Women | C17: =GETPIVOTDATA("Sum of Women Work Pitched",'New Sankey'!$A$1,"PHASE","VFX") -> 0 | D17: profit | F17: Total Pitched | G17: Bts Award Women | H17: =C48 -> 36236.5 | I17: equity | L17: Pitched | M17: Production Award Women | N17: 1000 | O17: profit
A18: Edit pitch men | B18: Pitched | C18: =GETPIVOTDATA("Sum of BID TOTAL",'New Sankey'!$A$1,"PHASE","Editorial")-GETPIVOTDATA("Sum of Women Work Pitched",'New Sankey'!$A$1,"PHASE","Editorial") -> 9593788.1 | D18: input | I18: equity | L18: Pitched | M18: Audio Award Men | N18: 800 | O18: equity
A19: Edit pitch women | B19: Pitched | C19: =GETPIVOTDATA("Sum of Women Work Pitched",'New Sankey'!$A$1,"PHASE","Editorial") -> 0 | D19: input | I19: equity | L19: Pitched | M19: Audio Award Women | N19: 200 | O19: equity | P19: Award
A20: Production Pitch men | B20: Pitched | C20: =GETPIVOTDATA("Sum of BID TOTAL",'New Sankey'!$A$1,"PHASE","Film & Video Production")-GETPIVOTDATA("Sum of Women Work Pitched",'New Sankey'!$A$1,"PHASE","Film & Video Production") -> 55315214 | D20: profit | I20: input | P20: Award
A21: Production Pitch Women | B21: Pitched | C21: =GETPIVOTDATA("Sum of Women Work Pitched",'New Sankey'!$A$1,"PHASE","Film & Video Production") -> 8828244.8 | D21: profit | I21: input | P21: Award
A22: Audio Pitch Men | B22: Pitched | C22: =GETPIVOTDATA("Sum of BID TOTAL",'New Sankey'!$A$1,"PHASE","Audio Post")-GETPIVOTDATA("Sum of Women Work Pitched",'New Sankey'!$A$1,"PHASE","Audio Post") -> 2228240 | D22: equity | I22: profit | P22: Award
A23: Audio Pitch Women | B23: Pitched | C23: =GETPIVOTDATA("Sum of Women Work Pitched",'New Sankey'!$A$1,"PHASE","Audio Post") -> 434880 | D23: equity | I23: profit | P23: Award
A24: Finishing Pitch Men | B24: Pitched | C24: =GETPIVOTDATA("Sum of BID TOTAL",'New Sankey'!$A$1,"PHASE","Finishing")-GETPIVOTDATA("Sum of Women Work Pitched",'New Sankey'!$A$1,"PHASE","Finishing") -> 2451300 | D24: input | I24: equity | P24: Award
A25: Finishing Pitch Women | B25: Pitched | C25: =GETPIVOTDATA("Sum of Women Work Pitched",'New Sankey'!$A$1,"PHASE","Finishing") -> 49250 | D25: input | I25: equity | P25: Award
A26: Music Pitch Men | B26: Pitched | C26: =GETPIVOTDATA("Sum of BID TOTAL",'New Sankey'!$A$1,"PHASE","Music")-GETPIVOTDATA("Sum of Women Work Pitched",'New Sankey'!$A$1,"PHASE","Music") -> 688400 | D26: profit | P26: Award
A27: Music Pitch Women | B27: Pitched | C27: =GETPIVOTDATA("Sum of Women Work Pitched",'New Sankey'!$A$1,"PHASE","Music") -> 8600 | D27: profit | G27: Pitched Work | H27: =SUM(H1:H8) -> 85811947 | I27: Input
A28: Stills Pitch Men | B28: Pitched | C28: =GETPIVOTDATA("Sum of BID TOTAL",'New Sankey'!$A$1,"PHASE","Still Photography Production")+GETPIVOTDATA("Sum of BID TOTAL",'New Sankey'!$A$1,"PHASE","Photo Retouching & Post")-GETPIVOTDATA("Sum of Women Work Pitched",'New Sankey'!$A$1,"PHASE","Photo Retouching & Post")-GETPIVOTDATA("Sum of Women Work Pitched",'New Sankey'!$A$1,"PHASE","Still Photography Production") -> 3749015.4 | D28: equity | F28: Pitched Work | G28: Awarded Work | H28: =N41+N42 -> 31640880 | I28: Input | L28: Production | M28: Production Pitch men | N28: =GETPIVOTDATA("Sum of BID TOTAL",'New Sankey'!$A$1,"PHASE","Film & Video Production")-GETPIVOTDATA("Sum of Women Work Pitched",'New Sankey'!$A$1,"PHASE","Film & Video Production") -> 55315214 | O28: profit
A29: Stills Pitch Women | B29: Pitched | C29: =GETPIVOTDATA("Sum of Women Work Pitched",'New Sankey'!$A$1,"PHASE","Photo Retouching & Post")+GETPIVOTDATA("Sum of Women Work Pitched",'New Sankey'!$A$1,"PHASE","Still Photography Production") -> 774884.55 | D29: equity | F29: Awarded Work | G29: Awarded Production | H29: =H33+H34 -> 23213713 | I29: Cost | L29: Production | M29: Production Pitch Women | N29: =GETPIVOTDATA("Sum of Women Work Pitched",'New Sankey'!$A$1,"PHASE","Film & Video Production") -> 8828244.8 | O29: profit
A30: BTS Pitch Men | B30: Pitched | C30: =GETPIVOTDATA("Sum of BID TOTAL",'New Sankey'!$A$1,"PHASE","Behind The Scenes (BTS)")-GETPIVOTDATA("Sum of Women Work Pitched",'New Sankey'!$A$1,"PHASE","Behind The Scenes (BTS)") -> 261060.35 | D30: input | F30: Awarded Work | G30: Awarded Post | H30: =H35+H36 -> 6571411.8 | I30: Investment | L30: Post | M30: Post Pitch Men | N30: =C2+C6+C8+C16+C10 -> 16390799 | O30: equity
A31: BTS Pitch Women | B31: Pitched | C31: =GETPIVOTDATA("Sum of Women Work Pitched",'New Sankey'!$A$1,"PHASE","Behind The Scenes (BTS)") -> 74757.475 | D31: input | F31: Awarded Work | G31: Awarded Stills | H31: =H37+H38 -> 1731684.1 | I31: Cost | L31: Post | M31: Post Pitch Women | N31: =C3+C7+C9+C11+C17 -> 492730 | O31: equity
A32: VFX Pitch Men | B32: Pitched | C32: =GETPIVOTDATA("Sum of BID TOTAL",'New Sankey'!$A$1,"PHASE","VFX")-GETPIVOTDATA("Sum of Women Work Pitched",'New Sankey'!$A$1,"PHASE","VFX") -> 1429070.5 | D32: profit | F32: Awarded Work | G32: Awarded BTS | H32: =H39+H40 -> 124070.62 | I32: Investment | L32: Stills | M32: Stills Pitch Men | N32: =C12 -> 3749015.4 | O32: input
A33: VFX Pitch Women | B33: Pitched | C33: =GETPIVOTDATA("Sum of Women Work Pitched",'New Sankey'!$A$1,"PHASE","VFX") -> 0 | D33: profit | F33: Awarded Production | G33: Production Awarded to Men | H33: =H10 -> 20086717 | I33: Profit | L33: Stills | M33: Stills Pitch Women | N33: =C13 -> 774884.55 | O33: input
A34: Pitched | B34: Award | C34: =GETPIVOTDATA("Sum of Total Award",'New Sankey'!$A$1) -> 32128441 | D34: Profit | F34: Awarded Production | G34: Production Awarded to Women | H34: =H11 -> 3126995.8 | I34: Equity | L34: BTS | M34: BTS Pitch Men | N34: =C14 -> 261060.35 | O34: profit
A35: Award | B35: Edit award men | C35: =GETPIVOTDATA("Sum of Total Award",'New Sankey'!$A$1,"PHASE","Editorial")-GETPIVOTDATA("Sum of Women Work Awarded",'New Sankey'!$A$1,"PHASE","Editorial") -> 3528420.8 | D35: input | F35: Awarded Post | G35: Post Awarded to Men | H35: =H12 -> 6296971.8 | I35: Profit | L35: BTS | M35: BTS Pitch Women | N35: =C15 -> 74757.475 | O35: profit
A36: Award | B36: Edit award women | C36: =GETPIVOTDATA("Sum of Women Work Awarded",'New Sankey'!$A$1,"PHASE","Editorial") -> 0 | D36: input | F36: Awarded Post | G36: Post Awrded to Women | H36: =H13 -> 274440 | I36: Equity
A37: Award | B37: Production award men | C37: =GETPIVOTDATA("Sum of Total Award",'New Sankey'!$A$1,"PHASE","Film & Video Production")-GETPIVOTDATA("Sum of Women Work Awarded",'New Sankey'!$A$1,"PHASE","Film & Video Production") -> 20086717 | D37: profit | F37: Awarded Stills | G37: Stills Awarded to Men | H37: =H14 -> 1531360.4 | I37: Profit
A38: Award | B38: Production award Women | C38: =GETPIVOTDATA("Sum of Women Work Awarded",'New Sankey'!$A$1,"PHASE","Film & Video Production") -> 3126995.8 | D38: profit | F38: Awarded Stills | G38: Stills Awarded to Women | H38: =H15 -> 200323.63 | I38: Equity
A39: Award | B39: Audio award Men | C39: =GETPIVOTDATA("Sum of Total Award",'New Sankey'!$A$1,"PHASE","Audio Post")-GETPIVOTDATA("Sum of Women Work Awarded",'New Sankey'!$A$1,"PHASE","Audio Post") -> 902210 | D39: Profit | F39: Awarded BTS | G39: BTS Awarded to Men | H39: =H16 -> 87834.125 | I39: Profit
A40: Award | B40: Audio award Women | C40: =GETPIVOTDATA("Sum of Women Work Awarded",'New Sankey'!$A$1,"PHASE","Audio Post") -> 225190 | F40: Awarded BTS | G40: BTS Awarded to Women | H40: =H17 -> 36236.5 | I40: Equity
A41: Award | B41: Finishing award Men | C41: =GETPIVOTDATA("Sum of Total Award",'New Sankey'!$A$1,"PHASE","Finishing")-GETPIVOTDATA("Sum of Women Work Awarded",'New Sankey'!$A$1,"PHASE","Finishing") -> 1058600 | L41: Awarded Work | M41: Awarded to Men | N41: =H10+H12+H14+H16 -> 28002884 | O41: Profit
A42: Award | B42: Finishing award Women | C42: =GETPIVOTDATA("Sum of Women Work Awarded",'New Sankey'!$A$1,"PHASE","Finishing") -> 49250 | F42: Awarded to Men | G42: Stills | L42: Awarded Work | M42: Awarded to Women | N42: =H11+H13+H15+H17 -> 3637995.9 | O42: Equity
A43: Award | B43: Music award Men | C43: =GETPIVOTDATA("Sum of Total Award",'New Sankey'!$A$1,"PHASE","Music")-GETPIVOTDATA("Sum of Women Work Awarded",'New Sankey'!$A$1,"PHASE","Music") -> 231750 | F43: Awarded to Women | G43: Stills
A44: Award | B44: Music award Women | C44: =GETPIVOTDATA("Sum of Women Work Awarded",'New Sankey'!$A$1,"PHASE","Music") -> 0 | F44: Awarded to Men | G44: BTS
A45: Award | B45: Stills award Men | C45: =GETPIVOTDATA("Sum of Total Award",'New Sankey'!$A$1,"PHASE","Still Photography Production")+GETPIVOTDATA("Sum of Total Award",'New Sankey'!$A$1,"PHASE","Photo Retouching & Post")-GETPIVOTDATA("Sum of Women Work Awarded",'New Sankey'!$A$1,"PHASE","Still Photography Production")-GETPIVOTDATA("Sum of Women Work Awarded",'New Sankey'!$A$1,"PHASE","Photo Retouching & Post") -> 1531360.4 | F45: Awarded to Women | G45: BTS
A46: Award | B46: Stills award Women | C46: =GETPIVOTDATA("Sum of Women Work Awarded",'New Sankey'!$A$1,"PHASE","Photo Retouching & Post")+GETPIVOTDATA("Sum of Women Work Awarded",'New Sankey'!$A$1,"PHASE","Still Photography Production") -> 200323.63
A47: Award | B47: BTS award Men | C47: =GETPIVOTDATA("Sum of Total Award",'New Sankey'!$A$1,"PHASE","Behind The Scenes (BTS)")-GETPIVOTDATA("Sum of Women Work Awarded",'New Sankey'!$A$1,"PHASE","Behind The Scenes (BTS)") -> 87834.125
A48: Award | B48: BTS award Women | C48: =GETPIVOTDATA("Sum of Women Work Awarded",'New Sankey'!$A$1,"PHASE","Behind The Scenes (BTS)") -> 36236.5
A49: Award | B49: VFX award Men | C49: =GETPIVOTDATA("Sum of Total Award",'New Sankey'!$A$1,"PHASE","VFX")-GETPIVOTDATA("Sum of Women Work Awarded",'New Sankey'!$A$1,"PHASE","VFX") -> 575991
A50: Award | B50: VFX award Women | C50: =GETPIVOTDATA("Sum of Women Work Awarded",'New Sankey'!$A$1,"PHASE","VFX") -> 0

Sheet Sheet10

Sheet RevWomCreat (2)
A1: PROJECT NAME | B1: AWARDED | C1: BRAND | D1: PRODUCT | E1: AGENCY | F1: CAMPAIGN | G1: VENDOR | H1: PHASE | I1: SUBMISSION | J1: BID NAME | K1: BIDFILE TYPE | L1: BID TOTAL | M1: BID TYPE | N1: AVERAGE BID | O1: DIVERSITY:: WOMAN DIRECTOR | P1: DIVERSITY:: MIINORITY DIRECTOR | Q1: DIVERSITY:: WOMAN EDITOR | R1: DIVERSITY:: MIINORITY EDITOR | S1: DIVERSITY:: WOMAN OWNED | T1: DIVERSITY:: MINORITY OWNED | U1: Women Work Pitched | V1: Women Work Awarded | W1: AvgBidPrice LUT.Average Bid Price | X1: Total Award | Y1: All Awarded
A2: Summer Fun | B2: 1 | C2: Kelly Hard Cider | D2: Kelly Summer Spritzer | E2: Korea SMB | F2: Q2 Summer Blitz | G2: Petulant Pictures | H2: Film & Video Production | I2: Summer Fun | J2: Petulant_SummerFun_LiveAction | K2: Original | L2: 960207.05 | M2: firm-bid | N2: 745866.47 | O2: 1 | U2: 960207.05 | V2: 960207.05 | W2: 745866.47 | X2: 960207.05 | Y2: 960207.05
A3: Summer Fun | B3: 0 | C3: Kelly Hard Cider | D3: Kelly Summer Spritzer | E3: Korea SMB | F3: Q2 Summer Blitz | H3: Film & Video Production | I3: Summer Fun | J3: OpenFrameworks_SummerFun_LiveAction | K3: Original | L3: 662457.18 | M3: firm-bid | O3: 1 | P3: 1 | U3: 662457.18 | V3: 0 | W3: 745866.47
A4: Summer Fun | B4: 0 | C4: Kelly Hard Cider | D4: Kelly Summer Spritzer | E4: Korea SMB | F4: Q2 Summer Blitz | H4: Film & Video Production | I4: Summer Fun | J4: Club101_SummerFun_LiveAction | K4: Original | L4: 614935.17 | M4: firm-bid | U4: 0 | V4: 0 | W4: 745866.47
A5: Summer Fun | B5: 0 | C5: Kelly Hard Cider | D5: Kelly Summer Spritzer | E5: Korea SMB | F5: Q2 Summer Blitz | H5: Editorial | I5: Summer Fun | J5: ToTo_SummerFun_Edit | K5: Original | L5: 107610.42 | M5: firm-bid | U5: 0 | V5: 0 | W5: 109194.19
A6: Summer Fun | B6: 0 | C6: Kelly Hard Cider | D6: Kelly Summer Spritzer | E6: Korea SMB | F6: Q2 Summer Blitz | H6: Editorial | I6: Summer Fun | J6: MyrtleRow_SummerFun_Edit | K6: Original | L6: 133998.96 | M6: firm-bid | Q6: 1 | T6: 1 | U6: 0 | V6: 0 | W6: 109194.19
A7: Summer Fun | B7: 1 | C7: Kelly Hard Cider | D7: Kelly Summer Spritzer | E7: Korea SMB | F7: Q2 Summer Blitz | G7: Saks Street Edit | H7: Editorial | I7: Summer Fun | J7: SaksStreetEdit_SummerFun_Edit | K7: Original | L7: 85973.183 | M7: firm-bid | N7: 109194.19 | T7: 1 | U7: 0 | V7: 0 | W7: 109194.19 | X7: 85973.183 | Y7: 85973.183
A8: Summer Fun | B8: 0 | C8: Kelly Hard Cider | D8: Kelly Summer Spritzer | E8: Korea SMB | F8: Q2 Summer Blitz | H8: Audio Post | I8: Audio Bid | J8: Audio Bid | K8: Original | L8: 14510 | M8: firm-bid | U8: 0 | V8: 0 | W8: 21656.667
A9: Summer Fun | B9: 1 | C9: Kelly Hard Cider | D9: Kelly Summer Spritzer | E9: Korea SMB | F9: Q2 Summer Blitz | G9: My Audio Fantasy | H9: Audio Post | I9: My Audio Fantasy | J9: AudioFantasybBid | K9: Original | L9: 21040 | M9: firm-bid | N9: 21656.667 | O9: 1 | R9: 1 | U9: 21040 | V9: 21040 | W9: 21656.667 | X9: 21040 | Y9: 21040
A10: Summer Fun | B10: 0 | C10: Kelly Hard Cider | D10: Kelly Summer Spritzer | E10: Korea SMB | F10: Q2 Summer Blitz | H10: Audio Post | I10: Love Language"Summer Fun" | J10: Love124 | K10: Original | L10: 29420 | M10: firm-bid | U10: 0 | V10: 0 | W10: 21656.667
A11: Summer Fun | B11: 0 | C11: Kelly Hard Cider | D11: Kelly Summer Spritzer | E11: Korea SMB | F11: Q2 Summer Blitz | H11: Finishing | I11: colorMaven for Summer Fun v1 | J11: ColorMaven_SummerFun_Finishing | K11: Original | L11: 52850 | M11: firm-bid | S11: 1 | U11: 0 | V11: 0 | W11: 37833.333
A12: Summer Fun | B12: 0 | C12: Kelly Hard Cider | D12: Kelly Summer Spritzer | E12: Korea SMB | F12: Q2 Summer Blitz | H12: Finishing | I12: Andiamo for "Summer Fun" | J12: AndiamoImages_SummerFun_Finishing | K12: Original | L12: 20700 | M12: firm-bid | Q12: 1 | S12: 1 | U12: 0 | V12: 0 | W12: 37833.333
A13: Summer Fun | B13: 1 | C13: Kelly Hard Cider | D13: Kelly Summer Spritzer | E13: Korea SMB | F13: Q2 Summer Blitz | G13: Evan Bander LLC | H13: Finishing | I13: EB "Summer Fun" | J13: EvanBanderLLC_SummerFun_Finishing | K13: Original | L13: 39950 | M13: firm-bid | N13: 37833.333 | R13: 1 | T13: 1 | U13: 0 | V13: 0 | W13: 37833.333 | X13: 39950 | Y13: 39950
A14: Summer Fun | B14: 1 | C14: Kelly Hard Cider | D14: Kelly Summer Spritzer | E14: Korea SMB | F14: Q2 Summer Blitz | G14: Petulant Pictures | H14: Sanitary Production Costs | I14: Summer Fun | J14: Petulant_SummerFun_Covid | K14: Original | L14: 4805.275 | M14: firm-bid | N14: 7050.3625 | O14: 1 | U14: 4805.275 | V14: 4805.275 | W14: 7050.3625 | X14: 4805.275 | Y14: 4805.275
A15: Summer Fun | B15: 0 | C15: Kelly Hard Cider | D15: Kelly Summer Spritzer | E15: Korea SMB | F15: Q2 Summer Blitz | H15: Sanitary Production Costs | I15: Summer Fun | J15: OpenFrameworks_SummerFun_Covid | K15: Original | L15: 10043.812 | M15: firm-bid | O15: 1 | P15: 1 | U15: 10043.812 | V15: 0 | W15: 7050.3625
A16: Summer Fun | B16: 0 | C16: Kelly Hard Cider | D16: Kelly Summer Spritzer | E16: Korea SMB | F16: Q2 Summer Blitz | H16: Sanitary Production Costs | I16: Summer Fun | J16: Club101_SummerFun_Covid | K16: Original | L16: 6302 | M16: firm-bid | U16: 0 | V16: 0 | W16: 7050.3625
A17: Summer Fun | B17: 1 | C17: Kelly Hard Cider | D17: Kelly Summer Spritzer | E17: Korea SMB | F17: Q2 Summer Blitz | G17: Petulant Pictures | H17: Green Production Costs | I17: Summer Fun | J17: Petulant_SummerFun_Green | K17: Original | L17: 18176 | M17: firm-bid | N17: 14980 | O17: 1 | U17: 18176 | V17: 18176 | W17: 14980 | X17: 18176 | Y17: 18176
A18: Summer Fun | B18: 0 | C18: Kelly Hard Cider | D18: Kelly Summer Spritzer | E18: Korea SMB | F18: Q2 Summer Blitz | H18: Green Production Costs | I18: Summer Fun | J18: OpenFrameworks_SummerFun_Green | K18: Original | L18: 14364 | M18: firm-bid | O18: 1 | P18: 1 | U18: 14364 | V18: 0 | W18: 14980
A19: Summer Fun | B19: 0 | C19: Kelly Hard Cider | D19: Kelly Summer Spritzer | E19: Korea SMB | F19: Q2 Summer Blitz | H19: Green Production Costs | I19: Summer Fun | J19: Club101_SummerFun_Green | K19: Original | L19: 12400 | M19: firm-bid | U19: 0 | V19: 0 | W19: 14980
A20: Summer Fun | B20: 0 | C20: Kelly Hard Cider | D20: Kelly Summer Spritzer | E20: Korea SMB | F20: Q2 Summer Blitz | H20: Photo Retouching & Post | I20: Kent Wilson Studio Estimate for "Summer Fun" #1 | J20: KentWilsonStudio_SummerFun_Retouching | K20: Original | L20: 39250 | M20: firm-bid | P20: 1 | U20: 0 | V20: 0 | W20: 37483.333
A21: Summer Fun | B21: 0 | C21: Kelly Hard Cider | D21: Kelly Summer Spritzer | E21: Korea SMB | F21: Q2 Summer Blitz | H21: Photo Retouching & Post | I21: Summer Fun | J21: Interstate_SummerFun_Retouching | K21: Original | L21: 36200 | M21: firm-bid | S21: 1 | U21: 0 | V21: 0 | W21: 37483.333
A22: Summer Fun | B22: 1 | C22: Kelly Hard Cider | D22: Kelly Summer Spritzer | E22: Korea SMB | F22: Q2 Summer Blitz | G22: Buck & Archie | H22: Photo Retouching & Post | I22: Buck & Archie "Kelly Hard Cider:Summer Fun" v2 | J22: BuckandArchie_SummerFun_Retouching | K22: Original | L22: 37000 | M22: firm-bid | N22: 37483.333 | U22: 0 | V22: 0 | W22: 37483.333 | X22: 37000 | Y22: 37000
A23: Summer Fun | B23: 0 | C23: Kelly Hard Cider | D23: Kelly Summer Spritzer | E23: Korea SMB | F23: Q2 Summer Blitz | H23: Still Photography Production | I23: Kent Wilson Studio Estimate for "Summer Fun" #1 | J23: KentWilsonStudio_SummerFun_Stills | K23: Original | L23: 161541.3 | M23: firm-bid | P23: 1 | U23: 0 | V23: 0 | W23: 145472.98
A24: Summer Fun | B24: 0 | C24: Kelly Hard Cider | D24: Kelly Summer Spritzer | E24: Korea SMB | F24: Q2 Summer Blitz | H24: Still Photography Production | I24: Summer Fun | J24: Interstate_SummerFun_Stills | K24: Original | L24: 138331.55 | M24: firm-bid | S24: 1 | U24: 0 | V24: 0 | W24: 145472.98
A25: Summer Fun | B25: 1 | C25: Kelly Hard Cider | D25: Kelly Summer Spritzer | E25: Korea SMB | F25: Q2 Summer Blitz | G25: Buck & Archie | H25: Still Photography Production | I25: Buck & Archie "Kelly Hard Cider:Summer Fun" v2 | J25: BuckandArchie_SummerFun_Stills | K25: Original | L25: 136546.09 | M25: firm-bid | N25: 145472.98 | U25: 0 | V25: 0 | W25: 145472.98 | X25: 136546.09 | Y25: 136546.09
A26: Summer Fun | B26: 0 | C26: Kelly Hard Cider | D26: Kelly Summer Spritzer | E26: Korea SMB | F26: Q2 Summer Blitz | H26: Music | I26: AEM "Kelly Summer Spritzer || Q2 Summer Blitz" | J26: ArnoldEstherMusic_SummerFun_Music | K26: Original | L26: 8700 | M26: firm-bid | U26: 0 | V26: 0 | W26: 38916.667
A27: Summer Fun | B27: 0 | C27: Kelly Hard Cider | D27: Kelly Summer Spritzer | E27: Korea SMB | F27: Q2 Summer Blitz | H27: Music | I27: "Summer Fun" - Special Oaks Music | J27: SpecialOaks_SummerFun_Music | K27: Original | L27: 69900 | M27: firm-bid | U27: 0 | V27: 0 | W27: 38916.667
A28: Summer Fun | B28: 1 | C28: Kelly Hard Cider | D28: Kelly Summer Spritzer | E28: Korea SMB | F28: Q2 Summer Blitz | G28: Tone & Logic | H28: Music | I28: T+L for "Kelly's Summer Fun" | J28: ToneandLogic_SummerFun_Music | K28: Original | L28: 38150 | M28: firm-bid | N28: 38916.667 | T28: 1 | U28: 0 | V28: 0 | W28: 38916.667 | X28: 38150 | Y28: 38150
A29: The Traveller UK | B29: 0 | C29: Dewey North | D29: Dewey North 107º | E29: Last Station Group | F29: The Sophisticated Traveller | H29: Audio Post | I29: Special Oaks"The Traveller UK" | J29: Special Oaks | K29: Original | L29: 24800 | M29: firm-bid | O29: 1 | T29: 1 | U29: 24800 | V29: 0 | W29: 33935
A30: The Traveller UK | B30: 1 | C30: Dewey North | D30: Dewey North 107º | E30: Last Station Group | F30: The Sophisticated Traveller | G30: Love Language | H30: Audio Post | I30: Love Language "The Traveller UK" | J30: Love126 | K30: Original | L30: 43070 | M30: firm-bid | N30: 33935 | U30: 0 | V30: 0 | W30: 33935 | X30: 43070 | Y30: 43070
A31: The Traveller UK | B31: 1 | C31: Dewey North | D31: Dewey North 107º | E31: Last Station Group | F31: The Sophisticated Traveller | G31: Love Language | H31: Music | I31: Love Language "The Traveller UK" - MUSIC ONLY | J31: LoveLanguage_TheTravellerUK_Music | K31: Original | L31: 20800 | M31: firm-bid | N31: 40150 | U31: 0 | V31: 0 | W31: 40150 | X31: 20800 | Y31: 20800
A32: The Traveller UK | B32: 0 | C32: Dewey North | D32: Dewey North 107º | E32: Last Station Group | F32: The Sophisticated Traveller | H32: Music | I32: Frequency Presentation for "The Traveller UK" | J32: Frequency_TheTravellerUK_Music | K32: Original | L32: 49050 | M32: firm-bid | U32: 0 | V32: 0 | W32: 40150
A33: The Traveller UK | B33: 0 | C33: Dewey North | D33: Dewey North 107º | E33: Last Station Group | F33: The Sophisticated Traveller | H33: Music | I33: AEM "Dewey North || The Sophisticated Traveller (UK)" | J33: ArnoldEstherMusic_TheTravellerUK_Music | K33: Original | L33: 50600 | M33: firm-bid | U33: 0 | V33: 0 | W33: 40150
A34: The Traveller UK | B34: 1 | C34: Dewey North | D34: Dewey North 107º | E34: Last Station Group | F34: The Sophisticated Traveller | G34: EFX VFX | H34: VFX | I34: EFXvfx \\ "The Traveller UK" \\ v3 | J34: EFXVFX_TheTravellerUK_VFX | K34: Original | L34: 116454 | M34: firm-bid | N34: 104828.75 | U34: 0 | V34: 0 | W34: 104828.75 | X34: 116454 | Y34: 116454
A35: The Traveller UK | B35: 0 | C35: Dewey North | D35: Dewey North 107º | E35: Last Station Group | F35: The Sophisticated Traveller | H35: VFX | I35: v2 - "The Traveller UK" //SORCERY | J35: Sorcery_TheTravellerUK_VFX | K35: Original | L35: 93203.5 | M35: firm-bid | U35: 0 | V35: 0 | W35: 104828.75
A36: The Traveller UK | B36: 0 | C36: Dewey North | D36: Dewey North 107º | E36: Last Station Group | F36: The Sophisticated Traveller | H36: Finishing | I36: colorMaven for "The Traveller UK" v3 | J36: ColorMaven_TheTravellerUK_Finishing | K36: Original | L36: 17500 | M36: firm-bid | S36: 1 | U36: 0 | V36: 0 | W36: 32250
A37: The Traveller UK | B37: 1 | C37: Dewey North | D37: Dewey North 107º | E37: Last Station Group | F37: The Sophisticated Traveller | G37: Andiamo Images | H37: Finishing | I37: Andiamo for "The Traveller" (UK Version) | J37: AndiamoImages_TheTravellerUK_Finishing | K37: Original | L37: 49250 | M37: firm-bid | N37: 32250 | O37: 1 | S37: 1 | U37: 49250 | V37: 49250 | W37: 32250 | X37: 49250 | Y37: 49250
A38: The Traveller UK | B38: 0 | C38: Dewey North | D38: Dewey North 107º | E38: Last Station Group | F38: The Sophisticated Traveller | H38: Finishing | I38: ‚ÄúThe Traveller UK‚Äù - POI | J38: PersonsofInterest_TheTravellerUK_Finishing | K38: Original | L38: 30000 | M38: firm-bid | R38: 1 | U38: 0 | V38: 0 | W38: 32250
A39: The Traveller UK | B39: 1 | C39: Dewey North | D39: Dewey North 107º | E39: Last Station Group | F39: The Sophisticated Traveller | G39: Myrtle Row Editorial | H39: Editorial | I39: The Traveller UK | J39: MyrtleRow_TheTravellerUK_Edit | K39: Original | L39: 95889.792 | M39: firm-bid | N39: 93203.872 | T39: 1 | U39: 0 | V39: 0 | W39: 93203.872 | X39: 95889.792 | Y39: 95889.792
A40: The Traveller UK | B40: 0 | C40: Dewey North | D40: Dewey North 107º | E40: Last Station Group | F40: The Sophisticated Traveller | H40: Editorial | I40: The Traveller UK | J40: TotalCuts_TheTravellerUK_Edit | K40: Original | L40: 67406.617 | M40: firm-bid | Q40: 1 | U40: 0 | V40: 0 | W40: 93203.872
A41: The Traveller UK | B41: 0 | C41: Dewey North | D41: Dewey North 107º | E41: Last Station Group | F41: The Sophisticated Traveller | H41: Editorial | I41: The Traveller UK | J41: Fightclub_TheTravellerUK_Edit | K41: Original | L41: 116315.21 | M41: firm-bid | U41: 0 | V41: 0 | W41: 93203.872
A42: The Traveller UK | B42: 1 | C42: Dewey North | D42: Dewey North 107º | E42: Last Station Group | F42: The Sophisticated Traveller | G42: Harmony & Light | H42: Green Production Costs | I42: The Traveller UK | J42: harmony_and_Light_TheTravellerUK_Green | K42: Original | L42: 10250 | M42: firm-bid | N42: 9606 | U42: 0 | V42: 0 | W42: 9606 | X42: 10250 | Y42: 10250
A43: The Traveller UK | B43: 0 | C43: Dewey North | D43: Dewey North 107º | E43: Last Station Group | F43: The Sophisticated Traveller | H43: Green Production Costs | I43: The Traveller UK | J43: Level12_TheTravellerUK_Green | K43: Original | L43: 8568 | M43: firm-bid | O43: 1 | U43: 8568 | V43: 0 | W43: 9606
A44: The Traveller UK | B44: 0 | C44: Dewey North | D44: Dewey North 107º | E44: Last Station Group | F44: The Sophisticated Traveller | H44: Green Production Costs | I44: The Traveller UK | J44: OpenFrameworks_TheTravellerUK_Green | K44: Original | L44: 10000 | M44: firm-bid | O44: 1 | P44: 1 | U44: 10000 | V44: 0 | W44: 9606
A45: The Traveller UK | B45: 1 | C45: Dewey North | D45: Dewey North 107º | E45: Last Station Group | F45: The Sophisticated Traveller | G45: Harmony & Light | H45: Sanitary Production Costs | I45: The Traveller UK | J45: harmony_and_Light_TheTravellerUK_Covid | K45: Original | L45: 7200.035 | M45: firm-bid | N45: 9810.1133 | U45: 0 | V45: 0 | W45: 9810.1133 | X45: 7200.035 | Y45: 7200.035
A46: The Traveller UK | B46: 0 | C46: Dewey North | D46: Dewey North 107º | E46: Last Station Group | F46: The Sophisticated Traveller | H46: Sanitary Production Costs | I46: The Traveller UK | J46: Level12_TheTravellerUK_Covid | K46: Original | L46: 12958.487 | M46: firm-bid | O46: 1 | U46: 12958.487 | V46: 0 | W46: 9810.1133
A47: The Traveller UK | B47: 0 | C47: Dewey North | D47: Dewey North 107º | E47: Last Station Group | F47: The Sophisticated Traveller | H47: Sanitary Production Costs | I47: The Traveller UK | J47: OpenFrameworks_TheTravellerUK_Covid | K47: Original | L47: 9271.8175 | M47: firm-bid | O47: 1 | P47: 1 | U47: 9271.8175 | V47: 0 | W47: 9810.1133
A48: The Traveller UK | B48: 1 | C48: Dewey North | D48: Dewey North 107º | E48: Last Station Group | F48: The Sophisticated Traveller | G48: Harmony & Light | H48: Film & Video Production | I48: The Traveller UK | J48: harmony_and_Light_TheTravellerUK_LiveAction | K48: Original | L48: 685626.9 | M48: firm-bid | N48: 649602.48 | U48: 0 | V48: 0 | W48: 649602.48 | X48: 685626.9 | Y48: 685626.9
A49: The Traveller UK | B49: 0 | C49: Dewey North | D49: Dewey North 107º | E49: Last Station Group | F49: The Sophisticated Traveller | H49: Film & Video Production | I49: The Traveller UK | J49: Level12_TheTravellerUK_LiveAction | K49: Original | L49: 673878.44 | M49: firm-bid | O49: 1 | U49: 673878.44 | V49: 0 | W49: 649602.48
A50: The Traveller UK | B50: 0 | C50: Dewey North | D50: Dewey North 107º | E50: Last Station Group | F50: The Sophisticated Traveller | H50: Film & Video Production | I50: The Traveller UK | J50: OpenFrameworks_TheTravellerUK_LiveAction | K50: Original | L50: 589302.09 | M50: firm-bid | O50: 1 | P50: 1 | U50: 589302.09 | V50: 0 | W50: 649602.48
A51: The Traveller US | B51: 0 | C51: Dewey North | D51: Dewey North 107º | E51: Top Notch Creative | F51: The Sophisticated Traveller | H51: Audio Post | I51: Earwax "The Traveller US" | J51: Earwax | K51: Original | L51: 29320 | M51: firm-bid | U51: 0 | V51: 0 | W51: 48990
A52: The Traveller US | B52: 1 | C52: Dewey North | D52: Dewey North 107º | E52: Top Notch Creative | F52: The Sophisticated Traveller | G52: Audio Lab Technologies | H52: Audio Post | I52: Audio Lab"The Traveller US" | J52: Audio_85 | K52: Original | L52: 68660 | M52: firm-bid | N52: 48990 | Q52: 1 | S52: 1 | U52: 0 | V52: 0 | W52: 48990 | X52: 68660 | Y52: 68660
A53: The Traveller US | B53: 0 | C53: Dewey North | D53: Dewey North 107º | E53: Top Notch Creative | F53: The Sophisticated Traveller | H53: Behind The Scenes (BTS) | I53: The Traveller (US Version) | J53: Club101_SummerFun_BTS | K53: Original | L53: 22844.75 | M53: firm-bid | U53: 0 | V53: 0 | W53: 18774.708
A54: The Traveller US | B54: 1 | C54: Dewey North | D54: Dewey North 107º | E54: Top Notch Creative | F54: The Sophisticated Traveller | G54: Test Flight Productions | H54: Behind The Scenes (BTS) | I54: The Traveller (for US) | J54: TestFlight_TheTravellerUS_BTS | K54: Original | L54: 19457.425 | M54: firm-bid | N54: 18774.708 | T54: 1 | U54: 0 | V54: 0 | W54: 18774.708 | X54: 19457.425 | Y54: 19457.425
A55: The Traveller US | B55: 0 | C55: Dewey North | D55: Dewey North 107º | E55: Top Notch Creative | F55: The Sophisticated Traveller | H55: Behind The Scenes (BTS) | I55: The Traveller US V2 | J55: CHAW_TheTravellerUS_BTSv2 | K55: Original | L55: 14021.95 | M55: firm-bid | P55: 1 | T55: 1 | U55: 0 | V55: 0 | W55: 18774.708
A56: The Traveller US | B56: 1 | C56: Dewey North | D56: Dewey North 107º | E56: Top Notch Creative | F56: The Sophisticated Traveller | G56: Tone & Logic | H56: Music | I56: T+L for "Dewey North - The Traveller (US)" | J56: ToneandLogic_TheTravellerUS_Music | K56: Original | L56: 15950 | M56: firm-bid | N56: 30350 | T56: 1 | U56: 0 | V56: 0 | W56: 30350 | X56: 15950 | Y56: 15950
A57: The Traveller US | B57: 0 | C57: Dewey North | D57: Dewey North 107º | E57: Top Notch Creative | F57: The Sophisticated Traveller | H57: Music | I57: Love Language "The Traveller US" v2 | J57: LoveLanguage_TheTravellerUS_Music | K57: Original | L57: 34650 | M57: firm-bid | U57: 0 | V57: 0 | W57: 30350
A58: The Traveller US | B58: 0 | C58: Dewey North | D58: Dewey North 107º | E58: Top Notch Creative | F58: The Sophisticated Traveller | H58: Music | I58: Frequency Presentation for "The Traveller US " | J58: Frequency_TheTravellerUS_Music | K58: Original | L58: 40450 | M58: firm-bid | U58: 0 | V58: 0 | W58: 30350
A59: The Traveller US | B59: 0 | C59: Dewey North | D59: Dewey North 107º | E59: Top Notch Creative | F59: The Sophisticated Traveller | H59: Finishing | I59: ‚ÄúThe Traveller US ‚Äù - POI | J59: PersonsofInterest_TheTravellerUS_Finishing | K59: Original | L59: 14900 | M59: firm-bid | R59: 1 | U59: 0 | V59: 0 | W59: 27083.333
A60: The Traveller US | B60: 0 | C60: Dewey North | D60: Dewey North 107º | E60: Top Notch Creative | F60: The Sophisticated Traveller | H60: Finishing | I60: EB "The Traveller US" | J60: EvanBanderLLC_TheTravellerUS_Finishing | K60: Original | L60: 47450 | M60: firm-bid | R60: 1 | T60: 1 | U60: 0 | V60: 0 | W60: 27083.333
A61: The Traveller US | B61: 1 | C61: Dewey North | D61: Dewey North 107º | E61: Top Notch Creative | F61: The Sophisticated Traveller | G61: The Dub House | H61: Finishing | I61: ‚ÄúThe Traveller US‚Äù | Dub House | J61: TheDubHouse_TheTravellerUS_Finishing | K61: Original | L61: 18900 | M61: firm-bid | N61: 27083.333 | U61: 0 | V61: 0 | W61: 27083.333 | X61: 18900 | Y61: 18900
A62: The Traveller US | B62: 0 | C62: Dewey North | D62: Dewey North 107º | E62: Top Notch Creative | F62: The Sophisticated Traveller | H62: Editorial | I62: The Traveller US | J62: TotalCuts_TheTravellerUS_Edit | K62: Original | L62: 56933.45 | M62: firm-bid | Q62: 1 | U62: 0 | V62: 0 | W62: 93441.483
A63: The Traveller US | B63: 1 | C63: Dewey North | D63: Dewey North 107º | E63: Top Notch Creative | F63: The Sophisticated Traveller | G63: The Closet | H63: Editorial | I63: The Traveller US | J63: TheCloset_TheTravellerUS_Edit | K63: Original | L63: 100975.58 | M63: firm-bid | N63: 93441.483 | S63: 1 | T63: 1 | U63: 0 | V63: 0 | W63: 93441.483 | X63: 100975.58 | Y63: 100975.58
A64: The Traveller US | B64: 0 | C64: Dewey North | D64: Dewey North 107º | E64: Top Notch Creative | F64: The Sophisticated Traveller | H64: Editorial | I64: The Traveller US | J64: SaksStreetEdit_TheTravellerUS_Edit | K64: Original | L64: 122415.42 | M64: firm-bid | T64: 1 | U64: 0 | V64: 0 | W64: 93441.483
A65: The Traveller US | B65: 0 | C65: Dewey North | D65: Dewey North 107º | E65: Top Notch Creative | F65: The Sophisticated Traveller | H65: Green Production Costs | I65: The Traveller (US Version) | J65: Club101_SummerFun_Green | K65: Original | L65: 12400 | M65: firm-bid | U65: 0 | V65: 0 | W65: 11703.333
A66: The Traveller US | B66: 1 | C66: Dewey North | D66: Dewey North 107º | E66: Top Notch Creative | F66: The Sophisticated Traveller | G66: Test Flight Productions | H66: Green Production Costs | I66: The Traveller (for US) | J66: TestFlight_TheTravellerUS_Green | K66: Original | L66: 13750 | M66: firm-bid | N66: 11703.333 | T66: 1 | U66: 0 | V66: 0 | W66: 11703.333 | X66: 13750 | Y66: 13750
A67: The Traveller US | B67: 0 | C67: Dewey North | D67: Dewey North 107º | E67: Top Notch Creative | F67: The Sophisticated Traveller | H67: Green Production Costs | I67: The Traveller US V2 | J67: CHAW_TheTravellersFriend_Green | K67: Original | L67: 8960 | M67: firm-bid | P67: 1 | T67: 1 | U67: 0 | V67: 0 | W67: 11703.333
A68: The Traveller US | B68: 0 | C68: Dewey North | D68: Dewey North 107º | E68: Top Notch Creative | F68: The Sophisticated Traveller | H68: Sanitary Production Costs | I68: The Traveller (US Version) | J68: Club101_TheTravellerUS_Covid | K68: Original | L68: 7010.975 | M68: firm-bid | U68: 0 | V68: 0 | W68: 7058.24
A69: The Traveller US | B69: 1 | C69: Dewey North | D69: Dewey North 107º | E69: Top Notch Creative | F69: The Sophisticated Traveller | G69: Test Flight Productions | H69: Sanitary Production Costs | I69: The Traveller (for US) | J69: TestFlight_TheTravellerUS_Covid | K69: Original | L69: 5317.3125 | M69: firm-bid | N69: 7058.24 | T69: 1 | U69: 0 | V69: 0 | W69: 7058.24 | X69: 5317.3125 | Y69: 5317.3125
A70: The Traveller US | B70: 0 | C70: Dewey North | D70: Dewey North 107º | E70: Top Notch Creative | F70: The Sophisticated Traveller | H70: Sanitary Production Costs | I70: The Traveller US V2 | J70: CHAW_TheTravellerUS_Covid | K70: Original | L70: 8846.4325 | M70: firm-bid | P70: 1 | T70: 1 | U70: 0 | V70: 0 | W70: 7058.24
A71: The Traveller US | B71: 0 | C71: Dewey North | D71: Dewey North 107º | E71: Top Notch Creative | F71: The Sophisticated Traveller | H71: Film & Video Production | I71: The Traveller (US Version) | J71: Club101_TheTravellerUS_LiveAction | K71: Original | L71: 748472.66 | M71: firm-bid | U71: 0 | V71: 0 | W71: 835635.38
A72: The Traveller US | B72: 1 | C72: Dewey North | D72: Dewey North 107º | E72: Top Notch Creative | F72: The Sophisticated Traveller | G72: Test Flight Productions | H72: Film & Video Production | I72: The Traveller (for US) | J72: TestFlight_TheTravellerUS_LiveAction | K72: Original | L72: 856318.5 | M72: firm-bid | N72: 835635.38 | T72: 1 | U72: 0 | V72: 0 | W72: 835635.38 | X72: 856318.5 | Y72: 856318.5
A73: The Traveller US | B73: 0 | C73: Dewey North | D73: Dewey North 107º | E73: Top Notch Creative | F73: The Sophisticated Traveller | H73: Film & Video Production | I73: The Traveller US V2 | J73: CHAW_TheTravellerUS_LiveAction | K73: Original | L73: 902114.97 | M73: firm-bid | P73: 1 | T73: 1 | U73: 0 | V73: 0 | W73: 835635.38
A74: The Traveller Settles Down | B74: 0 | C74: Dewey North | D74: Dewey North 80¬∫ | E74: Top Notch Creative | F74: The Sophisticated Traveller | H74: Audio Post | I74: Earwax "The Traveller Settles Down" | J74: Earwax | K74: Original | L74: 35540 | M74: firm-bid | U74: 0 | V74: 0 | W74: 52025
A75: The Traveller Settles Down | B75: 1 | C75: Dewey North | D75: Dewey North 80¬∫ | E75: Top Notch Creative | F75: The Sophisticated Traveller | G75: Sound Monster | H75: Audio Post | I75: Sound Monster"The Traveller Settles Down" | J75: Sound Monster | K75: Original | L75: 68510 | M75: firm-bid | N75: 52025 | R75: 1 | U75: 0 | V75: 0 | W75: 52025 | X75: 68510 | Y75: 68510
A76: The Traveller Settles Down | B76: 0 | C76: Dewey North | D76: Dewey North 80¬∫ | E76: Top Notch Creative | F76: The Sophisticated Traveller | H76: Music | I76: "The Traveller Settles Down" v2 | J76: M52_TheTravellerSettlesDown_Music | K76: Original | L76: 8600 | M76: firm-bid | O76: 1 | S76: 1 | U76: 8600 | V76: 0 | W76: 40166.667
A77: The Traveller Settles Down | B77: 1 | C77: Dewey North | D77: Dewey North 80¬∫ | E77: Top Notch Creative | F77: The Sophisticated Traveller | G77: Love Language | H77: Music | I77: Love Language "The Traveller Settles Down" v2 | J77: LoveLanguage_TheTravellerSettlesDown_Music | K77: Original | L77: 52150 | M77: firm-bid | N77: 40166.667 | U77: 0 | V77: 0 | W77: 40166.667 | X77: 52150 | Y77: 52150
A78: The Traveller Settles Down | B78: 0 | C78: Dewey North | D78: Dewey North 80¬∫ | E78: Top Notch Creative | F78: The Sophisticated Traveller | H78: Music | I78: T+L for "Dewey North - The Traveller Settles Down" | J78: ToneandLogic_TheTravellerSettlesDown_Music | K78: Original | L78: 59750 | M78: firm-bid | T78: 1 | U78: 0 | V78: 0 | W78: 40166.667
A79: The Traveller Settles Down | B79: 1 | C79: Dewey North | D79: Dewey North 80¬∫ | E79: Top Notch Creative | F79: The Sophisticated Traveller | G79: Sorcery | H79: VFX | I79: v5 - "The Traveller Settles Down" //SORCERY | J79: Sorcery_TheTravellerSettlesDown_VFX | K79: Original | L79: 80541.5 | M79: firm-bid | N79: 79204.667 | U79: 0 | V79: 0 | W79: 79204.667 | X79: 80541.5 | Y79: 80541.5
A80: The Traveller Settles Down | B80: 0 | C80: Dewey North | D80: Dewey North 80¬∫ | E80: Top Notch Creative | F80: The Sophisticated Traveller | H80: VFX | I80: "The Traveller Settles Down" JOB #4001 | J80: TerminalOutput_TheTravellerSettlesDown_VFX | K80: Original | L80: 92170 | M80: firm-bid | U80: 0 | V80: 0 | W80: 79204.667
A81: The Traveller Settles Down | B81: 0 | C81: Dewey North | D81: Dewey North 80¬∫ | E81: Top Notch Creative | F81: The Sophisticated Traveller | H81: VFX | I81: "The Traveller Settles Down" by CJ #4 | J81: CalamityJane_TheTravellerSettlesDown_VFX | K81: Original | L81: 64902.5 | M81: firm-bid | S81: 1 | U81: 0 | V81: 0 | W81: 79204.667
A82: The Traveller Settles Down | B82: 0 | C82: Dewey North | D82: Dewey North 80¬∫ | E82: Top Notch Creative | F82: The Sophisticated Traveller | H82: Finishing | I82: The Traveller Settles Down Burnish | J82: Burnish_TheTravellerSettlesDown_Finishing | K82: Original | L82: 8850 | M82: firm-bid | S82: 1 | U82: 0 | V82: 0 | W82: 18050
A83: The Traveller Settles Down | B83: 1 | C83: Dewey North | D83: Dewey North 80¬∫ | E83: Top Notch Creative | F83: The Sophisticated Traveller | G83: Witness | H83: Finishing | I83: WITNESS:: The Traveller Settles Down V2 | J83: Witness_TheTravellerSettlesDown_Finishing | K83: Original | L83: 28600 | M83: firm-bid | N83: 18050 | Q83: 1 | R83: 1 | U83: 0 | V83: 0 | W83: 18050 | X83: 28600 | Y83: 28600
A84: The Traveller Settles Down | B84: 0 | C84: Dewey North | D84: Dewey North 80¬∫ | E84: Top Notch Creative | F84: The Sophisticated Traveller | H84: Finishing | I84: colorMaven "The Traveller Settles Down" | K84: Original | L84: 16700 | M84: firm-bid | S84: 1 | U84: 0 | V84: 0 | W84: 18050
A85: The Traveller Settles Down | B85: 0 | C85: Dewey North | D85: Dewey North 80¬∫ | E85: Top Notch Creative | F85: The Sophisticated Traveller | H85: Editorial | I85: The Traveller Settles Down | J85: ToTo_TheTravellerSettlesDown_Edit | K85: Original | L85: 112476.88 | M85: firm-bid | U85: 0 | V85: 0 | W85: 100943.6
A86: The Traveller Settles Down | B86: 1 | C86: Dewey North | D86: Dewey North 80¬∫ | E86: Top Notch Creative | F86: The Sophisticated Traveller | G86: Armistice Edit | H86: Editorial | I86: The Traveller Settles Down | J86: Armistace_TheTravellerSettlesDown_Edit | K86: Original | L86: 111615.99 | M86: firm-bid | N86: 100943.6 | U86: 0 | V86: 0 | W86: 100943.6 | X86: 111615.99 | Y86: 111615.99
A87: The Traveller Settles Down | B87: 0 | C87: Dewey North | D87: Dewey North 80¬∫ | E87: Top Notch Creative | F87: The Sophisticated Traveller | H87: Editorial | I87: The Traveller Settles Down | J87: MyrtleRow_TheTravellerSettlesDown_Edit | K87: Original | L87: 78737.925 | M87: firm-bid | T87: 1 | U87: 0 | V87: 0 | W87: 100943.6
A88: The Traveller Settles Down | B88: 0 | C88: Dewey North | D88: Dewey North 80¬∫ | E88: Top Notch Creative | F88: The Sophisticated Traveller | H88: Green Production Costs | I88: TTSD | J88: Interstate_TheTravellerSettlesDown_Green | K88: Original | L88: 6875 | M88: firm-bid | S88: 1 | U88: 0 | V88: 0 | W88: 8766.3333
A89: The Traveller Settles Down | B89: 1 | C89: Dewey North | D89: Dewey North 80¬∫ | E89: Top Notch Creative | F89: The Sophisticated Traveller | G89: Open Frameworks Image Creation | H89: Green Production Costs | I89: The Traveller Settles Down | J89: OpenFrameworks_TheTravellerSettlesDown_Green | K89: Original | L89: 8928 | M89: firm-bid | N89: 8766.3333 | O89: 1 | P89: 1 | U89: 8928 | V89: 8928 | W89: 8766.3333 | X89: 8928 | Y89: 8928
A90: The Traveller Settles Down | B90: 0 | C90: Dewey North | D90: Dewey North 80¬∫ | E90: Top Notch Creative | F90: The Sophisticated Traveller | H90: Green Production Costs | I90: TTSD | J90: Petulant_TheTravellerSettlesDown_Green | K90: Original | L90: 10496 | M90: firm-bid | O90: 1 | U90: 10496 | V90: 0 | W90: 8766.3333
A91: The Traveller Settles Down | B91: 0 | C91: Dewey North | D91: Dewey North 80¬∫ | E91: Top Notch Creative | F91: The Sophisticated Traveller | H91: Sanitary Production Costs | I91: TTSD | J91: Interstate_TheTravellerSettlesDown_Covid | K91: Original | L91: 10484.952 | M91: firm-bid | S91: 1 | U91: 0 | V91: 0 | W91: 7291.9392
A92: The Traveller Settles Down | B92: 1 | C92: Dewey North | D92: Dewey North 80¬∫ | E92: Top Notch Creative | F92: The Sophisticated Traveller | G92: Open Frameworks Image Creation | H92: Sanitary Production Costs | I92: The Traveller Settles Down | J92: OpenFrameworks_TheTravellerSettlesDown_Covid | K92: Original | L92: 6664.365 | M92: firm-bid | N92: 7291.9392 | O92: 1 | P92: 1 | U92: 6664.365 | V92: 6664.365 | W92: 7291.9392 | X92: 6664.365 | Y92: 6664.365
A93: The Traveller Settles Down | B93: 0 | C93: Dewey North | D93: Dewey North 80¬∫ | E93: Top Notch Creative | F93: The Sophisticated Traveller | H93: Sanitary Production Costs | I93: TTSD | J93: Petulant_TheTravellerSettlesDown_Covid | K93: Original | L93: 4726.5 | M93: firm-bid | O93: 1 | U93: 4726.5 | V93: 0 | W93: 7291.9392
A94: The Traveller Settles Down | B94: 0 | C94: Dewey North | D94: Dewey North 80¬∫ | E94: Top Notch Creative | F94: The Sophisticated Traveller | H94: Film & Video Production | I94: TTSD | J94: Interstate_TheTravellerSettlesDown_LiveAction | K94: Original | L94: 702418.88 | M94: firm-bid | S94: 1 | U94: 0 | V94: 0 | W94: 656708.29
A95: The Traveller Settles Down | B95: 1 | C95: Dewey North | D95: Dewey North 80¬∫ | E95: Top Notch Creative | F95: The Sophisticated Traveller | G95: Open Frameworks Image Creation | H95: Film & Video Production | I95: The Traveller Settles Down | J95: OpenFrameworks_TheTravellerSettlesDown_LiveAction | K95: Original | L95: 621332.43 | M95: firm-bid | N95: 656708.29 | O95: 1 | P95: 1 | U95: 621332.43 | V95: 621332.43 | W95: 656708.29 | X95: 621332.43 | Y95: 621332.43
A96: The Traveller Settles Down | B96: 0 | C96: Dewey North | D96: Dewey North 80¬∫ | E96: Top Notch Creative | F96: The Sophisticated Traveller | H96: Film & Video Production | I96: TTSD | J96: Petulant_TheTravellerSettlesDown_LiveAction | K96: Original | L96: 646373.56 | M96: firm-bid | O96: 1 | U96: 646373.56 | V96: 0 | W96: 656708.29
A97: Designated Dad | B97: 0 | C97: Walker's | D97: Walker's N/A | E97: Aster PPK | F97: Party Light | H97: Audio Post | I97: Sound Monster "Designated Dad" | J97: Sound Monster | K97: Original | L97: 50580 | M97: firm-bid | U97: 0 | V97: 0 | W97: 36220
A98: Designated Dad | B98: 0 | C98: Walker's | D98: Walker's N/A | E98: Aster PPK | F98: Party Light | H98: Audio Post | I98: Funny Rabbit "Designated Dad" | J98: Funny Rabbit | K98: Original | L98: 18410 | M98: firm-bid | O98: 1 | P98: 1 | R98: 1 | S98: 1 | U98: 18410 | V98: 0 | W98: 36220
A99: Designated Dad | B99: 1 | C99: Walker's | D99: Walker's N/A | E99: Aster PPK | F99: Party Light | G99: Earwax | H99: Audio Post | I99: Earwax | J99: Earwax | K99: Original | L99: 39670 | M99: firm-bid | N99: 36220 | U99: 0 | V99: 0 | W99: 36220 | X99: 39670 | Y99: 39670
A100: Designated Dad | B100: 0 | C100: Walker's | D100: Walker's N/A | E100: Aster PPK | F100: Party Light | H100: Photo Retouching & Post | I100: DesDad | J100: Interstate_DesignatedDad_Retouching | K100: Original | L100: 21700 | M100: firm-bid | S100: 1 | U100: 0 | V100: 0 | W100: 25166.667
...

Sheet Sheet9

Sheet BeverageData
A1: PROJECT ID | B1: ORIGINAL SUBMISSION DATE | C1: PROJECT NAME | D1: WORKSPACE | E1: PROJECT GROUP | F1: AWARDED | G1: BRAND | H1: PRODUCT | I1: AGENCY | J1: CAMPAIGN | K1: VENDOR | L1: PHASE | M1: SUBMISSION | N1: BID NAME | O1: BIDFILE TYPE | P1: BID TOTAL | Q1: BID TYPE | R1: AVERAGE BID | S1: DIVERSITY:: WOMAN DIRECTOR | T1: DIVERSITY:: MIINORITY DIRECTOR | U1: DIVERSITY:: WOMAN EDITOR | V1: DIVERSITY:: MIINORITY EDITOR | W1: DIVERSITY:: WOMAN OWNED | X1: DIVERSITY:: MINORITY OWNED | Y1: SPEND:: ANIMATION | Z1: SPEND:: ART DEPARTMENT LABOR | AA1: SPEND:: ART DEPARTMENT MATERIALS | AB1: SPEND:: AUDIO POST | AC1: SPEND:: BEHIND THE SCENES | AD1: SPEND:: CATERING / CRAFT SERVICE | AE1: SPEND:: COLOR GRADING | AF1: SPEND:: COVID LABOR | AG1: SPEND:: CUSTOM | AH1: SPEND:: DESIGN | AI1: SPEND:: DIRECTOR/ CREATIVE FEES | AJ1: SPEND:: DO NOT USE | AK1: SPEND:: EDITORIAL GRAPHICS | AL1: SPEND:: EDITORIAL LABOR | AM1: SPEND:: EDITORIAL MISC | AN1: SPEND:: EDITORIAL OFFLINE | AO1: SPEND:: EDITORIAL PREP | AP1: SPEND:: EQUIPMENT COSTS | AQ1: SPEND:: EXPENDABLES | AR1: SPEND:: FILM STOCK & DIGITAL MEDIA | AS1: SPEND:: FINISHING | AT1: SPEND:: FOREIGN PRODUCTION SERVICES | AU1: SPEND:: HAIR & MAKEUP | AV1: SPEND:: INTERACTIVE | AW1: SPEND:: LOCATION & TRAVEL EXPENSES | AX1: SPEND:: MEALS | AY1: SPEND:: MISCELLANEOUS | AZ1: SPEND:: MUSIC | BA1: SPEND:: OTHER LABOR | BB1: SPEND:: PHOTO RETOUCHING | BC1: SPEND:: PRE-PRODUCTION EXPENSES | BD1: SPEND:: PRE-PRODUCTION LABOR | BE1: SPEND:: PRODUCTION COVID 19 COSTS | BF1: SPEND:: PRODUCTION STAFF | BG1: SPEND:: PRODUCTION SUSTAINABILITY | BH1: SPEND:: PROPS, WARDROBE, ANIMALS | BI1: SPEND:: SHOOTING CREW LABOR | BJ1: SPEND:: SOCIAL MEDIA | BK1: SPEND:: SPECIAL INSURANCE | BL1: SPEND:: STILL PHOTOGRAPHER FEES | BM1: SPEND:: STILL PHOTOGRAPHY PRODUCTION | BN1: SPEND:: STILLS POST PRODUCTION | BO1: SPEND:: STUDIO & LOCATIONS COMBINED | BP1: SPEND:: STUDIO RENTAL & STAGE EXPENSES | BQ1: SPEND:: TALENT | BR1: SPEND:: TALENT EXPENSES | BS1: SPEND:: VFX | BT1: SPEND:: WARDROBE | BU1: Women Work Pitched | BV1: Women Work Awarded | BW1: AvgBidPrice LUT.Average Bid Price
A2: 318 | B2: 45126.801 | C2: Summer Fun | D2: Alcoholic Beverages | E2: APAC | F2: 1 | G2: Kelly Hard Cider | H2: Kelly Summer Spritzer | I2: Korea SMB | J2: Q2 Summer Blitz | K2: Petulant Pictures | L2: Film & Video Production | M2: Summer Fun | N2: Petulant_SummerFun_LiveAction | O2: Original | P2: 960207.05 | Q2: firm-bid | R2: 745866.47 | S2: 1 | Z2: 36250.5 | AA2: 4200 | AI2: 240000 | AL2: 0 | AN2: 0 | AP2: 16550 | AR2: 3000 | AW2: 37115 | AY2: 5000 | BC2: 25950 | BD2: 141212.5 | BH2: 48000 | BI2: 163923.76 | BP2: 28960 | BQ2: 0 | BR2: 0 | BU2: 960207.05 | BV2: 960207.05 | BW2: 745866.47
A3: 318 | B3: 45126.801 | C3: Summer Fun | D3: Alcoholic Beverages | E3: APAC | F3: 0 | G3: Kelly Hard Cider | H3: Kelly Summer Spritzer | I3: Korea SMB | J3: Q2 Summer Blitz | L3: Film & Video Production | M3: Summer Fun | N3: OpenFrameworks_SummerFun_LiveAction | O3: Original | P3: 662457.18 | Q3: firm-bid | S3: 1 | T3: 1 | BU3: 662457.18 | BV3: 0 | BW3: 745866.47
A4: 318 | B4: 45126.801 | C4: Summer Fun | D4: Alcoholic Beverages | E4: APAC | F4: 0 | G4: Kelly Hard Cider | H4: Kelly Summer Spritzer | I4: Korea SMB | J4: Q2 Summer Blitz | L4: Film & Video Production | M4: Summer Fun | N4: Club101_SummerFun_LiveAction | O4: Original | P4: 614935.17 | Q4: firm-bid | BU4: 0 | BV4: 0 | BW4: 745866.47
A5: 318 | B5: 45126.801 | C5: Summer Fun | D5: Alcoholic Beverages | E5: APAC | F5: 0 | G5: Kelly Hard Cider | H5: Kelly Summer Spritzer | I5: Korea SMB | J5: Q2 Summer Blitz | L5: Editorial | M5: Summer Fun | N5: ToTo_SummerFun_Edit | O5: Original | P5: 107610.42 | Q5: firm-bid | BU5: 0 | BV5: 0 | BW5: 109194.19
A6: 318 | B6: 45126.801 | C6: Summer Fun | D6: Alcoholic Beverages | E6: APAC | F6: 0 | G6: Kelly Hard Cider | H6: Kelly Summer Spritzer | I6: Korea SMB | J6: Q2 Summer Blitz | L6: Editorial | M6: Summer Fun | N6: MyrtleRow_SummerFun_Edit | O6: Original | P6: 133998.96 | Q6: firm-bid | U6: 1 | X6: 1 | BU6: 0 | BV6: 0 | BW6: 109194.19
A7: 318 | B7: 45126.801 | C7: Summer Fun | D7: Alcoholic Beverages | E7: APAC | F7: 1 | G7: Kelly Hard Cider | H7: Kelly Summer Spritzer | I7: Korea SMB | J7: Q2 Summer Blitz | K7: Saks Street Edit | L7: Editorial | M7: Summer Fun | N7: SaksStreetEdit_SummerFun_Edit | O7: Original | P7: 85973.183 | Q7: firm-bid | R7: 109194.19 | X7: 1 | AL7: 13200 | AM7: 28800 | AN7: 10550 | AO7: 10166 | BU7: 0 | BV7: 0 | BW7: 109194.19
A8: 318 | B8: 45126.801 | C8: Summer Fun | D8: Alcoholic Beverages | E8: APAC | F8: 0 | G8: Kelly Hard Cider | H8: Kelly Summer Spritzer | I8: Korea SMB | J8: Q2 Summer Blitz | L8: Audio Post | M8: Audio Bid | N8: Audio Bid | O8: Original | P8: 14510 | Q8: firm-bid | BU8: 0 | BV8: 0 | BW8: 21656.667
A9: 318 | B9: 45126.801 | C9: Summer Fun | D9: Alcoholic Beverages | E9: APAC | F9: 1 | G9: Kelly Hard Cider | H9: Kelly Summer Spritzer | I9: Korea SMB | J9: Q2 Summer Blitz | K9: My Audio Fantasy | L9: Audio Post | M9: My Audio Fantasy | N9: AudioFantasybBid | O9: Original | P9: 21040 | Q9: firm-bid | R9: 21656.667 | S9: 1 | V9: 1 | AB9: 21040 | BU9: 21040 | BV9: 21040 | BW9: 21656.667
A10: 318 | B10: 45126.801 | C10: Summer Fun | D10: Alcoholic Beverages | E10: APAC | F10: 0 | G10: Kelly Hard Cider | H10: Kelly Summer Spritzer | I10: Korea SMB | J10: Q2 Summer Blitz | L10: Audio Post | M10: Love Language"Summer Fun" | N10: Love124 | O10: Original | P10: 29420 | Q10: firm-bid | BU10: 0 | BV10: 0 | BW10: 21656.667
A11: 318 | B11: 45126.801 | C11: Summer Fun | D11: Alcoholic Beverages | E11: APAC | F11: 0 | G11: Kelly Hard Cider | H11: Kelly Summer Spritzer | I11: Korea SMB | J11: Q2 Summer Blitz | L11: Finishing | M11: colorMaven for Summer Fun v1 | N11: ColorMaven_SummerFun_Finishing | O11: Original | P11: 52850 | Q11: firm-bid | W11: 1 | BU11: 0 | BV11: 0 | BW11: 37833.333
A12: 318 | B12: 45126.801 | C12: Summer Fun | D12: Alcoholic Beverages | E12: APAC | F12: 0 | G12: Kelly Hard Cider | H12: Kelly Summer Spritzer | I12: Korea SMB | J12: Q2 Summer Blitz | L12: Finishing | M12: Andiamo for "Summer Fun" | N12: AndiamoImages_SummerFun_Finishing | O12: Original | P12: 20700 | Q12: firm-bid | U12: 1 | W12: 1 | BU12: 0 | BV12: 0 | BW12: 37833.333
A13: 318 | B13: 45126.801 | C13: Summer Fun | D13: Alcoholic Beverages | E13: APAC | F13: 1 | G13: Kelly Hard Cider | H13: Kelly Summer Spritzer | I13: Korea SMB | J13: Q2 Summer Blitz | K13: Evan Bander LLC | L13: Finishing | M13: EB "Summer Fun" | N13: EvanBanderLLC_SummerFun_Finishing | O13: Original | P13: 39950 | Q13: firm-bid | R13: 37833.333 | V13: 1 | X13: 1 | AS13: 39950 | BU13: 0 | BV13: 0 | BW13: 37833.333
A14: 318 | B14: 45126.801 | C14: Summer Fun | D14: Alcoholic Beverages | E14: APAC | F14: 1 | G14: Kelly Hard Cider | H14: Kelly Summer Spritzer | I14: Korea SMB | J14: Q2 Summer Blitz | K14: Petulant Pictures | L14: Sanitary Production Costs | M14: Summer Fun | N14: Petulant_SummerFun_Covid | O14: Original | P14: 4805.275 | Q14: firm-bid | R14: 7050.3625 | S14: 1 | AF14: 2000 | BE14: 1050 | BU14: 4805.275 | BV14: 4805.275 | BW14: 7050.3625
A15: 318 | B15: 45126.801 | C15: Summer Fun | D15: Alcoholic Beverages | E15: APAC | F15: 0 | G15: Kelly Hard Cider | H15: Kelly Summer Spritzer | I15: Korea SMB | J15: Q2 Summer Blitz | L15: Sanitary Production Costs | M15: Summer Fun | N15: OpenFrameworks_SummerFun_Covid | O15: Original | P15: 10043.812 | Q15: firm-bid | S15: 1 | T15: 1 | BU15: 10043.812 | BV15: 0 | BW15: 7050.3625
A16: 318 | B16: 45126.801 | C16: Summer Fun | D16: Alcoholic Beverages | E16: APAC | F16: 0 | G16: Kelly Hard Cider | H16: Kelly Summer Spritzer | I16: Korea SMB | J16: Q2 Summer Blitz | L16: Sanitary Production Costs | M16: Summer Fun | N16: Club101_SummerFun_Covid | O16: Original | P16: 6302 | Q16: firm-bid | BU16: 0 | BV16: 0 | BW16: 7050.3625
A17: 318 | B17: 45126.801 | C17: Summer Fun | D17: Alcoholic Beverages | E17: APAC | F17: 1 | G17: Kelly Hard Cider | H17: Kelly Summer Spritzer | I17: Korea SMB | J17: Q2 Summer Blitz | K17: Petulant Pictures | L17: Green Production Costs | M17: Summer Fun | N17: Petulant_SummerFun_Green | O17: Original | P17: 18176 | Q17: firm-bid | R17: 14980 | S17: 1 | Z17: 0 | AA17: 0 | AI17: 0 | AL17: 0 | AN17: 0 | AP17: 0 | AR17: 0 | AW17: 0 | AY17: 14200 | BC17: 0 | BD17: 0 | BH17: 0 | BI17: 0 | BP17: 0 | BQ17: 0 | BR17: 0 | BU17: 18176 | BV17: 18176 | BW17: 14980
A18: 318 | B18: 45126.801 | C18: Summer Fun | D18: Alcoholic Beverages | E18: APAC | F18: 0 | G18: Kelly Hard Cider | H18: Kelly Summer Spritzer | I18: Korea SMB | J18: Q2 Summer Blitz | L18: Green Production Costs | M18: Summer Fun | N18: OpenFrameworks_SummerFun_Green | O18: Original | P18: 14364 | Q18: firm-bid | S18: 1 | T18: 1 | BU18: 14364 | BV18: 0 | BW18: 14980
A19: 318 | B19: 45126.801 | C19: Summer Fun | D19: Alcoholic Beverages | E19: APAC | F19: 0 | G19: Kelly Hard Cider | H19: Kelly Summer Spritzer | I19: Korea SMB | J19: Q2 Summer Blitz | L19: Green Production Costs | M19: Summer Fun | N19: Club101_SummerFun_Green | O19: Original | P19: 12400 | Q19: firm-bid | BU19: 0 | BV19: 0 | BW19: 14980
A20: 318 | B20: 45126.801 | C20: Summer Fun | D20: Alcoholic Beverages | E20: APAC | F20: 0 | G20: Kelly Hard Cider | H20: Kelly Summer Spritzer | I20: Korea SMB | J20: Q2 Summer Blitz | L20: Photo Retouching & Post | M20: Kent Wilson Studio Estimate for "Summer Fun" #1 | N20: KentWilsonStudio_SummerFun_Retouching | O20: Original | P20: 39250 | Q20: firm-bid | T20: 1 | BU20: 0 | BV20: 0 | BW20: 37483.333
A21: 318 | B21: 45126.801 | C21: Summer Fun | D21: Alcoholic Beverages | E21: APAC | F21: 0 | G21: Kelly Hard Cider | H21: Kelly Summer Spritzer | I21: Korea SMB | J21: Q2 Summer Blitz | L21: Photo Retouching & Post | M21: Summer Fun | N21: Interstate_SummerFun_Retouching | O21: Original | P21: 36200 | Q21: firm-bid | W21: 1 | BU21: 0 | BV21: 0 | BW21: 37483.333
A22: 318 | B22: 45126.801 | C22: Summer Fun | D22: Alcoholic Beverages | E22: APAC | F22: 1 | G22: Kelly Hard Cider | H22: Kelly Summer Spritzer | I22: Korea SMB | J22: Q2 Summer Blitz | K22: Buck & Archie | L22: Photo Retouching & Post | M22: Buck & Archie "Kelly Hard Cider:Summer Fun" v2 | N22: BuckandArchie_SummerFun_Retouching | O22: Original | P22: 37000 | Q22: firm-bid | R22: 37483.333 | BN22: 37000 | BU22: 0 | BV22: 0 | BW22: 37483.333
A23: 318 | B23: 45126.801 | C23: Summer Fun | D23: Alcoholic Beverages | E23: APAC | F23: 0 | G23: Kelly Hard Cider | H23: Kelly Summer Spritzer | I23: Korea SMB | J23: Q2 Summer Blitz | L23: Still Photography Production | M23: Kent Wilson Studio Estimate for "Summer Fun" #1 | N23: KentWilsonStudio_SummerFun_Stills | O23: Original | P23: 161541.3 | Q23: firm-bid | T23: 1 | BU23: 0 | BV23: 0 | BW23: 145472.98
A24: 318 | B24: 45126.801 | C24: Summer Fun | D24: Alcoholic Beverages | E24: APAC | F24: 0 | G24: Kelly Hard Cider | H24: Kelly Summer Spritzer | I24: Korea SMB | J24: Q2 Summer Blitz | L24: Still Photography Production | M24: Summer Fun | N24: Interstate_SummerFun_Stills | O24: Original | P24: 138331.55 | Q24: firm-bid | W24: 1 | BU24: 0 | BV24: 0 | BW24: 145472.98
A25: 318 | B25: 45126.801 | C25: Summer Fun | D25: Alcoholic Beverages | E25: APAC | F25: 1 | G25: Kelly Hard Cider | H25: Kelly Summer Spritzer | I25: Korea SMB | J25: Q2 Summer Blitz | K25: Buck & Archie | L25: Still Photography Production | M25: Buck & Archie "Kelly Hard Cider:Summer Fun" v2 | N25: BuckandArchie_SummerFun_Stills | O25: Original | P25: 136546.09 | Q25: firm-bid | R25: 145472.98 | AA25: 0 | AD25: 8053 | AP25: 2816 | AR25: 7357 | AY25: 0 | BC25: 15030 | BF25: 7639 | BH25: 3398 | BI25: 33713 | BL25: 11876 | BO25: 3905 | BQ25: 4610 | BR25: 1189 | BU25: 0 | BV25: 0 | BW25: 145472.98
A26: 318 | B26: 45126.801 | C26: Summer Fun | D26: Alcoholic Beverages | E26: APAC | F26: 0 | G26: Kelly Hard Cider | H26: Kelly Summer Spritzer | I26: Korea SMB | J26: Q2 Summer Blitz | L26: Music | M26: AEM "Kelly Summer Spritzer || Q2 Summer Blitz" | N26: ArnoldEstherMusic_SummerFun_Music | O26: Original | P26: 8700 | Q26: firm-bid | BU26: 0 | BV26: 0 | BW26: 38916.667
A27: 318 | B27: 45126.801 | C27: Summer Fun | D27: Alcoholic Beverages | E27: APAC | F27: 0 | G27: Kelly Hard Cider | H27: Kelly Summer Spritzer | I27: Korea SMB | J27: Q2 Summer Blitz | L27: Music | M27: "Summer Fun" - Special Oaks Music | N27: SpecialOaks_SummerFun_Music | O27: Original | P27: 69900 | Q27: firm-bid | BU27: 0 | BV27: 0 | BW27: 38916.667
A28: 318 | B28: 45126.801 | C28: Summer Fun | D28: Alcoholic Beverages | E28: APAC | F28: 1 | G28: Kelly Hard Cider | H28: Kelly Summer Spritzer | I28: Korea SMB | J28: Q2 Summer Blitz | K28: Tone & Logic | L28: Music | M28: T+L for "Kelly's Summer Fun" | N28: ToneandLogic_SummerFun_Music | O28: Original | P28: 38150 | Q28: firm-bid | R28: 38916.667 | X28: 1 | AZ28: 38150 | BU28: 0 | BV28: 0 | BW28: 38916.667
A29: 323 | B29: 45128.784 | C29: The Traveller UK | D29: Alcoholic Beverages | E29: Europe | F29: 0 | G29: Dewey North | H29: Dewey North 107º | I29: Last Station Group | J29: The Sophisticated Traveller | L29: Audio Post | M29: Special Oaks"The Traveller UK" | N29: Special Oaks | O29: Original | P29: 24800 | Q29: firm-bid | S29: 1 | X29: 1 | BU29: 24800 | BV29: 0 | BW29: 33935
A30: 323 | B30: 45128.784 | C30: The Traveller UK | D30: Alcoholic Beverages | E30: Europe | F30: 1 | G30: Dewey North | H30: Dewey North 107º | I30: Last Station Group | J30: The Sophisticated Traveller | K30: Love Language | L30: Audio Post | M30: Love Language "The Traveller UK" | N30: Love126 | O30: Original | P30: 43070 | Q30: firm-bid | R30: 33935 | AB30: 43070 | BU30: 0 | BV30: 0 | BW30: 33935
A31: 323 | B31: 45128.784 | C31: The Traveller UK | D31: Alcoholic Beverages | E31: Europe | F31: 1 | G31: Dewey North | H31: Dewey North 107º | I31: Last Station Group | J31: The Sophisticated Traveller | K31: Love Language | L31: Music | M31: Love Language "The Traveller UK" - MUSIC ONLY | N31: LoveLanguage_TheTravellerUK_Music | O31: Original | P31: 20800 | Q31: firm-bid | R31: 40150 | AZ31: 20800 | BU31: 0 | BV31: 0 | BW31: 40150
A32: 323 | B32: 45128.784 | C32: The Traveller UK | D32: Alcoholic Beverages | E32: Europe | F32: 0 | G32: Dewey North | H32: Dewey North 107º | I32: Last Station Group | J32: The Sophisticated Traveller | L32: Music | M32: Frequency Presentation for "The Traveller UK" | N32: Frequency_TheTravellerUK_Music | O32: Original | P32: 49050 | Q32: firm-bid | BU32: 0 | BV32: 0 | BW32: 40150
A33: 323 | B33: 45128.784 | C33: The Traveller UK | D33: Alcoholic Beverages | E33: Europe | F33: 0 | G33: Dewey North | H33: Dewey North 107º | I33: Last Station Group | J33: The Sophisticated Traveller | L33: Music | M33: AEM "Dewey North || The Sophisticated Traveller (UK)" | N33: ArnoldEstherMusic_TheTravellerUK_Music | O33: Original | P33: 50600 | Q33: firm-bid | BU33: 0 | BV33: 0 | BW33: 40150
A34: 323 | B34: 45128.784 | C34: The Traveller UK | D34: Alcoholic Beverages | E34: Europe | F34: 1 | G34: Dewey North | H34: Dewey North 107º | I34: Last Station Group | J34: The Sophisticated Traveller | K34: EFX VFX | L34: VFX | M34: EFXvfx \\ "The Traveller UK" \\ v3 | N34: EFXVFX_TheTravellerUK_VFX | O34: Original | P34: 116454 | Q34: firm-bid | R34: 104828.75 | Y34: 56750 | AR34: 750 | AS34: 7500 | AY34: 7900 | BF34: 16680 | BU34: 0 | BV34: 0 | BW34: 104828.75
A35: 323 | B35: 45128.784 | C35: The Traveller UK | D35: Alcoholic Beverages | E35: Europe | F35: 0 | G35: Dewey North | H35: Dewey North 107º | I35: Last Station Group | J35: The Sophisticated Traveller | L35: VFX | M35: v2 - "The Traveller UK" //SORCERY | N35: Sorcery_TheTravellerUK_VFX | O35: Original | P35: 93203.5 | Q35: firm-bid | BU35: 0 | BV35: 0 | BW35: 104828.75
A36: 323 | B36: 45128.784 | C36: The Traveller UK | D36: Alcoholic Beverages | E36: Europe | F36: 0 | G36: Dewey North | H36: Dewey North 107º | I36: Last Station Group | J36: The Sophisticated Traveller | L36: Finishing | M36: colorMaven for "The Traveller UK" v3 | N36: ColorMaven_TheTravellerUK_Finishing | O36: Original | P36: 17500 | Q36: firm-bid | W36: 1 | BU36: 0 | BV36: 0 | BW36: 32250
A37: 323 | B37: 45128.784 | C37: The Traveller UK | D37: Alcoholic Beverages | E37: Europe | F37: 1 | G37: Dewey North | H37: Dewey North 107º | I37: Last Station Group | J37: The Sophisticated Traveller | K37: Andiamo Images | L37: Finishing | M37: Andiamo for "The Traveller" (UK Version) | N37: AndiamoImages_TheTravellerUK_Finishing | O37: Original | P37: 49250 | Q37: firm-bid | R37: 32250 | S37: 1 | W37: 1 | AS37: 49250 | BU37: 49250 | BV37: 49250 | BW37: 32250
A38: 323 | B38: 45128.784 | C38: The Traveller UK | D38: Alcoholic Beverages | E38: Europe | F38: 0 | G38: Dewey North | H38: Dewey North 107º | I38: Last Station Group | J38: The Sophisticated Traveller | L38: Finishing | M38: ‚ÄúThe Traveller UK‚Äù - POI | N38: PersonsofInterest_TheTravellerUK_Finishing | O38: Original | P38: 30000 | Q38: firm-bid | V38: 1 | BU38: 0 | BV38: 0 | BW38: 32250
A39: 323 | B39: 45128.784 | C39: The Traveller UK | D39: Alcoholic Beverages | E39: Europe | F39: 1 | G39: Dewey North | H39: Dewey North 107º | I39: Last Station Group | J39: The Sophisticated Traveller | K39: Myrtle Row Editorial | L39: Editorial | M39: The Traveller UK | N39: MyrtleRow_TheTravellerUK_Edit | O39: Original | P39: 95889.792 | Q39: firm-bid | R39: 93203.872 | X39: 1 | AL39: 16650 | AM39: 13100 | AN39: 32950 | AO39: 7250 | BU39: 0 | BV39: 0 | BW39: 93203.872
A40: 323 | B40: 45128.784 | C40: The Traveller UK | D40: Alcoholic Beverages | E40: Europe | F40: 0 | G40: Dewey North | H40: Dewey North 107º | I40: Last Station Group | J40: The Sophisticated Traveller | L40: Editorial | M40: The Traveller UK | N40: TotalCuts_TheTravellerUK_Edit | O40: Original | P40: 67406.617 | Q40: firm-bid | U40: 1 | BU40: 0 | BV40: 0 | BW40: 93203.872
A41: 323 | B41: 45128.784 | C41: The Traveller UK | D41: Alcoholic Beverages | E41: Europe | F41: 0 | G41: Dewey North | H41: Dewey North 107º | I41: Last Station Group | J41: The Sophisticated Traveller | L41: Editorial | M41: The Traveller UK | N41: Fightclub_TheTravellerUK_Edit | O41: Original | P41: 116315.21 | Q41: firm-bid | BU41: 0 | BV41: 0 | BW41: 93203.872
A42: 323 | B42: 45128.784 | C42: The Traveller UK | D42: Alcoholic Beverages | E42: Europe | F42: 1 | G42: Dewey North | H42: Dewey North 107º | I42: Last Station Group | J42: The Sophisticated Traveller | K42: Harmony & Light | L42: Green Production Costs | M42: The Traveller UK | N42: harmony_and_Light_TheTravellerUK_Green | O42: Original | P42: 10250 | Q42: firm-bid | R42: 9606 | Z42: 0 | AA42: 0 | AI42: 0 | AL42: 0 | AN42: 0 | AP42: 0 | AR42: 0 | AW42: 0 | AY42: 8200 | BC42: 0 | BD42: 0 | BH42: 0 | BI42: 0 | BP42: 0 | BQ42: 0 | BR42: 0 | BU42: 0 | BV42: 0 | BW42: 9606
A43: 323 | B43: 45128.784 | C43: The Traveller UK | D43: Alcoholic Beverages | E43: Europe | F43: 0 | G43: Dewey North | H43: Dewey North 107º | I43: Last Station Group | J43: The Sophisticated Traveller | L43: Green Production Costs | M43: The Traveller UK | N43: Level12_TheTravellerUK_Green | O43: Original | P43: 8568 | Q43: firm-bid | S43: 1 | BU43: 8568 | BV43: 0 | BW43: 9606
A44: 323 | B44: 45128.784 | C44: The Traveller UK | D44: Alcoholic Beverages | E44: Europe | F44: 0 | G44: Dewey North | H44: Dewey North 107º | I44: Last Station Group | J44: The Sophisticated Traveller | L44: Green Production Costs | M44: The Traveller UK | N44: OpenFrameworks_TheTravellerUK_Green | O44: Original | P44: 10000 | Q44: firm-bid | S44: 1 | T44: 1 | BU44: 10000 | BV44: 0 | BW44: 9606
A45: 323 | B45: 45128.784 | C45: The Traveller UK | D45: Alcoholic Beverages | E45: Europe | F45: 1 | G45: Dewey North | H45: Dewey North 107º | I45: Last Station Group | J45: The Sophisticated Traveller | K45: Harmony & Light | L45: Sanitary Production Costs | M45: The Traveller UK | N45: harmony_and_Light_TheTravellerUK_Covid | O45: Original | P45: 7200.035 | Q45: firm-bid | R45: 9810.1133 | AF45: 3400 | BE45: 1170 | BU45: 0 | BV45: 0 | BW45: 9810.1133
A46: 323 | B46: 45128.784 | C46: The Traveller UK | D46: Alcoholic Beverages | E46: Europe | F46: 0 | G46: Dewey North | H46: Dewey North 107º | I46: Last Station Group | J46: The Sophisticated Traveller | L46: Sanitary Production Costs | M46: The Traveller UK | N46: Level12_TheTravellerUK_Covid | O46: Original | P46: 12958.487 | Q46: firm-bid | S46: 1 | BU46: 12958.487 | BV46: 0 | BW46: 9810.1133
A47: 323 | B47: 45128.784 | C47: The Traveller UK | D47: Alcoholic Beverages | E47: Europe | F47: 0 | G47: Dewey North | H47: Dewey North 107º | I47: Last Station Group | J47: The Sophisticated Traveller | L47: Sanitary Production Costs | M47: The Traveller UK | N47: OpenFrameworks_TheTravellerUK_Covid | O47: Original | P47: 9271.8175 | Q47: firm-bid | S47: 1 | T47: 1 | BU47: 9271.8175 | BV47: 0 | BW47: 9810.1133
A48: 323 | B48: 45128.784 | C48: The Traveller UK | D48: Alcoholic Beverages | E48: Europe | F48: 1 | G48: Dewey North | H48: Dewey North 107º | I48: Last Station Group | J48: The Sophisticated Traveller | K48: Harmony & Light | L48: Film & Video Production | M48: The Traveller UK | N48: harmony_and_Light_TheTravellerUK_LiveAction | O48: Original | P48: 685626.9 | Q48: firm-bid | R48: 649602.48 | Z48: 38109.5 | AA48: 73200 | AI48: 80000 | AL48: 0 | AN48: 0 | AP48: 22500 | AR48: 3500 | AW48: 28078 | AY48: 16100 | BC48: 18625 | BD48: 86050.25 | BH48: 7500 | BI48: 143742.17 | BP48: 35520 | BQ48: 0 | BR48: 0 | BU48: 0 | BV48: 0 | BW48: 649602.48
A49: 323 | B49: 45128.784 | C49: The Traveller UK | D49: Alcoholic Beverages | E49: Europe | F49: 0 | G49: Dewey North | H49: Dewey North 107º | I49: Last Station Group | J49: The Sophisticated Traveller | L49: Film & Video Production | M49: The Traveller UK | N49: Level12_TheTravellerUK_LiveAction | O49: Original | P49: 673878.44 | Q49: firm-bid | S49: 1 | BU49: 673878.44 | BV49: 0 | BW49: 649602.48
A50: 323 | B50: 45128.784 | C50: The Traveller UK | D50: Alcoholic Beverages | E50: Europe | F50: 0 | G50: Dewey North | H50: Dewey North 107º | I50: Last Station Group | J50: The Sophisticated Traveller | L50: Film & Video Production | M50: The Traveller UK | N50: OpenFrameworks_TheTravellerUK_LiveAction | O50: Original | P50: 589302.09 | Q50: firm-bid | S50: 1 | T50: 1 | BU50: 589302.09 | BV50: 0 | BW50: 649602.48
A51: 324 | B51: 45128.785 | C51: The Traveller US | D51: Alcoholic Beverages | E51: North America | F51: 0 | G51: Dewey North | H51: Dewey North 107º | I51: Top Notch Creative | J51: The Sophisticated Traveller | L51: Audio Post | M51: Earwax "The Traveller US" | N51: Earwax | O51: Original | P51: 29320 | Q51: firm-bid | BU51: 0 | BV51: 0 | BW51: 48990
A52: 324 | B52: 45128.785 | C52: The Traveller US | D52: Alcoholic Beverages | E52: North America | F52: 1 | G52: Dewey North | H52: Dewey North 107º | I52: Top Notch Creative | J52: The Sophisticated Traveller | K52: Audio Lab Technologies | L52: Audio Post | M52: Audio Lab"The Traveller US" | N52: Audio_85 | O52: Original | P52: 68660 | Q52: firm-bid | R52: 48990 | U52: 1 | W52: 1 | AB52: 68660 | BU52: 0 | BV52: 0 | BW52: 48990
A53: 324 | B53: 45128.785 | C53: The Traveller US | D53: Alcoholic Beverages | E53: North America | F53: 0 | G53: Dewey North | H53: Dewey North 107º | I53: Top Notch Creative | J53: The Sophisticated Traveller | L53: Behind The Scenes (BTS) | M53: The Traveller (US Version) | N53: Club101_SummerFun_BTS | O53: Original | P53: 22844.75 | Q53: firm-bid | BU53: 0 | BV53: 0 | BW53: 18774.708
A54: 324 | B54: 45128.785 | C54: The Traveller US | D54: Alcoholic Beverages | E54: North America | F54: 1 | G54: Dewey North | H54: Dewey North 107º | I54: Top Notch Creative | J54: The Sophisticated Traveller | K54: Test Flight Productions | L54: Behind The Scenes (BTS) | M54: The Traveller (for US) | N54: TestFlight_TheTravellerUS_BTS | O54: Original | P54: 19457.425 | Q54: firm-bid | R54: 18774.708 | X54: 1 | AC54: 12350 | BU54: 0 | BV54: 0 | BW54: 18774.708
A55: 324 | B55: 45128.785 | C55: The Traveller US | D55: Alcoholic Beverages | E55: North America | F55: 0 | G55: Dewey North | H55: Dewey North 107º | I55: Top Notch Creative | J55: The Sophisticated Traveller | L55: Behind The Scenes (BTS) | M55: The Traveller US V2 | N55: CHAW_TheTravellerUS_BTSv2 | O55: Original | P55: 14021.95 | Q55: firm-bid | T55: 1 | X55: 1 | BU55: 0 | BV55: 0 | BW55: 18774.708
A56: 324 | B56: 45128.785 | C56: The Traveller US | D56: Alcoholic Beverages | E56: North America | F56: 1 | G56: Dewey North | H56: Dewey North 107º | I56: Top Notch Creative | J56: The Sophisticated Traveller | K56: Tone & Logic | L56: Music | M56: T+L for "Dewey North - The Traveller (US)" | N56: ToneandLogic_TheTravellerUS_Music | O56: Original | P56: 15950 | Q56: firm-bid | R56: 30350 | X56: 1 | AZ56: 15950 | BU56: 0 | BV56: 0 | BW56: 30350
A57: 324 | B57: 45128.785 | C57: The Traveller US | D57: Alcoholic Beverages | E57: North America | F57: 0 | G57: Dewey North | H57: Dewey North 107º | I57: Top Notch Creative | J57: The Sophisticated Traveller | L57: Music | M57: Love Language "The Traveller US" v2 | N57: LoveLanguage_TheTravellerUS_Music | O57: Original | P57: 34650 | Q57: firm-bid | BU57: 0 | BV57: 0 | BW57: 30350
A58: 324 | B58: 45128.785 | C58: The Traveller US | D58: Alcoholic Beverages | E58: North America | F58: 0 | G58: Dewey North | H58: Dewey North 107º | I58: Top Notch Creative | J58: The Sophisticated Traveller | L58: Music | M58: Frequency Presentation for "The Traveller US " | N58: Frequency_TheTravellerUS_Music | O58: Original | P58: 40450 | Q58: firm-bid | BU58: 0 | BV58: 0 | BW58: 30350
A59: 324 | B59: 45128.785 | C59: The Traveller US | D59: Alcoholic Beverages | E59: North America | F59: 0 | G59: Dewey North | H59: Dewey North 107º | I59: Top Notch Creative | J59: The Sophisticated Traveller | L59: Finishing | M59: ‚ÄúThe Traveller US ‚Äù - POI | N59: PersonsofInterest_TheTravellerUS_Finishing | O59: Original | P59: 14900 | Q59: firm-bid | V59: 1 | BU59: 0 | BV59: 0 | BW59: 27083.333
A60: 324 | B60: 45128.785 | C60: The Traveller US | D60: Alcoholic Beverages | E60: North America | F60: 0 | G60: Dewey North | H60: Dewey North 107º | I60: Top Notch Creative | J60: The Sophisticated Traveller | L60: Finishing | M60: EB "The Traveller US" | N60: EvanBanderLLC_TheTravellerUS_Finishing | O60: Original | P60: 47450 | Q60: firm-bid | V60: 1 | X60: 1 | BU60: 0 | BV60: 0 | BW60: 27083.333
A61: 324 | B61: 45128.785 | C61: The Traveller US | D61: Alcoholic Beverages | E61: North America | F61: 1 | G61: Dewey North | H61: Dewey North 107º | I61: Top Notch Creative | J61: The Sophisticated Traveller | K61: The Dub House | L61: Finishing | M61: ‚ÄúThe Traveller US‚Äù | Dub House | N61: TheDubHouse_TheTravellerUS_Finishing | O61: Original | P61: 18900 | Q61: firm-bid | R61: 27083.333 | AS61: 18900 | BU61: 0 | BV61: 0 | BW61: 27083.333
A62: 324 | B62: 45128.785 | C62: The Traveller US | D62: Alcoholic Beverages | E62: North America | F62: 0 | G62: Dewey North | H62: Dewey North 107º | I62: Top Notch Creative | J62: The Sophisticated Traveller | L62: Editorial | M62: The Traveller US | N62: TotalCuts_TheTravellerUS_Edit | O62: Original | P62: 56933.45 | Q62: firm-bid | U62: 1 | BU62: 0 | BV62: 0 | BW62: 93441.483
A63: 324 | B63: 45128.785 | C63: The Traveller US | D63: Alcoholic Beverages | E63: North America | F63: 1 | G63: Dewey North | H63: Dewey North 107º | I63: Top Notch Creative | J63: The Sophisticated Traveller | K63: The Closet | L63: Editorial | M63: The Traveller US | N63: TheCloset_TheTravellerUS_Edit | O63: Original | P63: 100975.58 | Q63: firm-bid | R63: 93441.483 | W63: 1 | X63: 1 | AL63: 13300 | AM63: 35300 | AN63: 13700 | AO63: 11360 | BU63: 0 | BV63: 0 | BW63: 93441.483
A64: 324 | B64: 45128.785 | C64: The Traveller US | D64: Alcoholic Beverages | E64: North America | F64: 0 | G64: Dewey North | H64: Dewey North 107º | I64: Top Notch Creative | J64: The Sophisticated Traveller | L64: Editorial | M64: The Traveller US | N64: SaksStreetEdit_TheTravellerUS_Edit | O64: Original | P64: 122415.42 | Q64: firm-bid | X64: 1 | BU64: 0 | BV64: 0 | BW64: 93441.483
A65: 324 | B65: 45128.785 | C65: The Traveller US | D65: Alcoholic Beverages | E65: North America | F65: 0 | G65: Dewey North | H65: Dewey North 107º | I65: Top Notch Creative | J65: The Sophisticated Traveller | L65: Green Production Costs | M65: The Traveller (US Version) | N65: Club101_SummerFun_Green | O65: Original | P65: 12400 | Q65: firm-bid | BU65: 0 | BV65: 0 | BW65: 11703.333
A66: 324 | B66: 45128.785 | C66: The Traveller US | D66: Alcoholic Beverages | E66: North America | F66: 1 | G66: Dewey North | H66: Dewey North 107º | I66: Top Notch Creative | J66: The Sophisticated Traveller | K66: Test Flight Productions | L66: Green Production Costs | M66: The Traveller (for US) | N66: TestFlight_TheTravellerUS_Green | O66: Original | P66: 13750 | Q66: firm-bid | R66: 11703.333 | X66: 1 | Z66: 0 | AA66: 0 | AI66: 0 | AL66: 0 | AN66: 0 | AP66: 0 | AR66: 0 | AW66: 0 | AY66: 11000 | BC66: 0 | BD66: 0 | BH66: 0 | BI66: 0 | BP66: 0 | BQ66: 0 | BR66: 0 | BU66: 0 | BV66: 0 | BW66: 11703.333
A67: 324 | B67: 45128.785 | C67: The Traveller US | D67: Alcoholic Beverages | E67: North America | F67: 0 | G67: Dewey North | H67: Dewey North 107º | I67: Top Notch Creative | J67: The Sophisticated Traveller | L67: Green Production Costs | M67: The Traveller US V2 | N67: CHAW_TheTravellersFriend_Green | O67: Original | P67: 8960 | Q67: firm-bid | T67: 1 | X67: 1 | BU67: 0 | BV67: 0 | BW67: 11703.333
A68: 324 | B68: 45128.785 | C68: The Traveller US | D68: Alcoholic Beverages | E68: North America | F68: 0 | G68: Dewey North | H68: Dewey North 107º | I68: Top Notch Creative | J68: The Sophisticated Traveller | L68: Sanitary Production Costs | M68: The Traveller (US Version) | N68: Club101_TheTravellerUS_Covid | O68: Original | P68: 7010.975 | Q68: firm-bid | BU68: 0 | BV68: 0 | BW68: 7058.24
A69: 324 | B69: 45128.785 | C69: The Traveller US | D69: Alcoholic Beverages | E69: North America | F69: 1 | G69: Dewey North | H69: Dewey North 107º | I69: Top Notch Creative | J69: The Sophisticated Traveller | K69: Test Flight Productions | L69: Sanitary Production Costs | M69: The Traveller (for US) | N69: TestFlight_TheTravellerUS_Covid | O69: Original | P69: 5317.3125 | Q69: firm-bid | R69: 7058.24 | X69: 1 | AF69: 1850 | BE69: 1525 | BU69: 0 | BV69: 0 | BW69: 7058.24
A70: 324 | B70: 45128.785 | C70: The Traveller US | D70: Alcoholic Beverages | E70: North America | F70: 0 | G70: Dewey North | H70: Dewey North 107º | I70: Top Notch Creative | J70: The Sophisticated Traveller | L70: Sanitary Production Costs | M70: The Traveller US V2 | N70: CHAW_TheTravellerUS_Covid | O70: Original | P70: 8846.4325 | Q70: firm-bid | T70: 1 | X70: 1 | BU70: 0 | BV70: 0 | BW70: 7058.24
A71: 324 | B71: 45128.785 | C71: The Traveller US | D71: Alcoholic Beverages | E71: North America | F71: 0 | G71: Dewey North | H71: Dewey North 107º | I71: Top Notch Creative | J71: The Sophisticated Traveller | L71: Film & Video Production | M71: The Traveller (US Version) | N71: Club101_TheTravellerUS_LiveAction | O71: Original | P71: 748472.66 | Q71: firm-bid | BU71: 0 | BV71: 0 | BW71: 835635.38
A72: 324 | B72: 45128.785 | C72: The Traveller US | D72: Alcoholic Beverages | E72: North America | F72: 1 | G72: Dewey North | H72: Dewey North 107º | I72: Top Notch Creative | J72: The Sophisticated Traveller | K72: Test Flight Productions | L72: Film & Video Production | M72: The Traveller (for US) | N72: TestFlight_TheTravellerUS_LiveAction | O72: Original | P72: 856318.5 | Q72: firm-bid | R72: 835635.38 | X72: 1 | Z72: 36536.5 | AA72: 52700 | AI72: 125000 | AL72: 0 | AN72: 0 | AP72: 128200 | AR72: 2800 | AW72: 39121 | AY72: 12200 | BC72: 24500 | BD72: 121514.25 | BH72: 0 | BI72: 113163.05 | BP72: 29320 | BQ72: 0 | BR72: 0 | BU72: 0 | BV72: 0 | BW72: 835635.38
A73: 324 | B73: 45128.785 | C73: The Traveller US | D73: Alcoholic Beverages | E73: North America | F73: 0 | G73: Dewey North | H73: Dewey North 107º | I73: Top Notch Creative | J73: The Sophisticated Traveller | L73: Film & Video Production | M73: The Traveller US V2 | N73: CHAW_TheTravellerUS_LiveAction | O73: Original | P73: 902114.97 | Q73: firm-bid | T73: 1 | X73: 1 | BU73: 0 | BV73: 0 | BW73: 835635.38
A74: 326 | B74: 45128.786 | C74: The Traveller Settles Down | D74: Alcoholic Beverages | E74: North America | F74: 0 | G74: Dewey North | H74: Dewey North 80¬∫ | I74: Top Notch Creative | J74: The Sophisticated Traveller | L74: Audio Post | M74: Earwax "The Traveller Settles Down" | N74: Earwax | O74: Original | P74: 35540 | Q74: firm-bid | BU74: 0 | BV74: 0 | BW74: 52025
A75: 326 | B75: 45128.786 | C75: The Traveller Settles Down | D75: Alcoholic Beverages | E75: North America | F75: 1 | G75: Dewey North | H75: Dewey North 80¬∫ | I75: Top Notch Creative | J75: The Sophisticated Traveller | K75: Sound Monster | L75: Audio Post | M75: Sound Monster"The Traveller Settles Down" | N75: Sound Monster | O75: Original | P75: 68510 | Q75: firm-bid | R75: 52025 | V75: 1 | AB75: 68510 | BU75: 0 | BV75: 0 | BW75: 52025
A76: 326 | B76: 45128.786 | C76: The Traveller Settles Down | D76: Alcoholic Beverages | E76: North America | F76: 0 | G76: Dewey North | H76: Dewey North 80¬∫ | I76: Top Notch Creative | J76: The Sophisticated Traveller | L76: Music | M76: "The Traveller Settles Down" v2 | N76: M52_TheTravellerSettlesDown_Music | O76: Original | P76: 8600 | Q76: firm-bid | S76: 1 | W76: 1 | BU76: 8600 | BV76: 0 | BW76: 40166.667
A77: 326 | B77: 45128.786 | C77: The Traveller Settles Down | D77: Alcoholic Beverages | E77: North America | F77: 1 | G77: Dewey North | H77: Dewey North 80¬∫ | I77: Top Notch Creative | J77: The Sophisticated Traveller | K77: Love Language | L77: Music | M77: Love Language "The Traveller Settles Down" v2 | N77: LoveLanguage_TheTravellerSettlesDown_Music | O77: Original | P77: 52150 | Q77: firm-bid | R77: 40166.667 | AZ77: 52150 | BU77: 0 | BV77: 0 | BW77: 40166.667
A78: 326 | B78: 45128.786 | C78: The Traveller Settles Down | D78: Alcoholic Beverages | E78: North America | F78: 0 | G78: Dewey North | H78: Dewey North 80¬∫ | I78: Top Notch Creative | J78: The Sophisticated Traveller | L78: Music | M78: T+L for "Dewey North - The Traveller Settles Down" | N78: ToneandLogic_TheTravellerSettlesDown_Music | O78: Original | P78: 59750 | Q78: firm-bid | X78: 1 | BU78: 0 | BV78: 0 | BW78: 40166.667
A79: 326 | B79: 45128.786 | C79: The Traveller Settles Down | D79: Alcoholic Beverages | E79: North America | F79: 1 | G79: Dewey North | H79: Dewey North 80¬∫ | I79: Top Notch Creative | J79: The Sophisticated Traveller | K79: Sorcery | L79: VFX | M79: v5 - "The Traveller Settles Down" //SORCERY | N79: Sorcery_TheTravellerSettlesDown_VFX | O79: Original | P79: 80541.5 | Q79: firm-bid | R79: 79204.667 | Y79: 44625 | AR79: 6500 | AS79: 5250 | AY79: 0 | BF79: 5580 | BU79: 0 | BV79: 0 | BW79: 79204.667
A80: 326 | B80: 45128.786 | C80: The Traveller Settles Down | D80: Alcoholic Beverages | E80: North America | F80: 0 | G80: Dewey North | H80: Dewey North 80¬∫ | I80: Top Notch Creative | J80: The Sophisticated Traveller | L80: VFX | M80: "The Traveller Settles Down" JOB #4001 | N80: TerminalOutput_TheTravellerSettlesDown_VFX | O80: Original | P80: 92170 | Q80: firm-bid | BU80: 0 | BV80: 0 | BW80: 79204.667
A81: 326 | B81: 45128.786 | C81: The Traveller Settles Down | D81: Alcoholic Beverages | E81: North America | F81: 0 | G81: Dewey North | H81: Dewey North 80¬∫ | I81: Top Notch Creative | J81: The Sophisticated Traveller | L81: VFX | M81: "The Traveller Settles Down" by CJ #4 | N81: CalamityJane_TheTravellerSettlesDown_VFX | O81: Original | P81: 64902.5 | Q81: firm-bid | W81: 1 | BU81: 0 | BV81: 0 | BW81: 79204.667
A82: 326 | B82: 45128.786 | C82: The Traveller Settles Down | D82: Alcoholic Beverages | E82: North America | F82: 0 | G82: Dewey North | H82: Dewey North 80¬∫ | I82: Top Notch Creative | J82: The Sophisticated Traveller | L82: Finishing | M82: The Traveller Settles Down Burnish | N82: Burnish_TheTravellerSettlesDown_Finishing | O82: Original | P82: 8850 | Q82: firm-bid | W82: 1 | BU82: 0 | BV82: 0 | BW82: 18050
A83: 326 | B83: 45128.786 | C83: The Traveller Settles Down | D83: Alcoholic Beverages | E83: North America | F83: 1 | G83: Dewey North | H83: Dewey North 80¬∫ | I83: Top Notch Creative | J83: The Sophisticated Traveller | K83: Witness | L83: Finishing | M83: WITNESS:: The Traveller Settles Down V2 | N83: Witness_TheTravellerSettlesDown_Finishing | O83: Original | P83: 28600 | Q83: firm-bid | R83: 18050 | U83: 1 | V83: 1 | AS83: 28600 | BU83: 0 | BV83: 0 | BW83: 18050
A84: 326 | B84: 45128.786 | C84: The Traveller Settles Down | D84: Alcoholic Beverages | E84: North America | F84: 0 | G84: Dewey North | H84: Dewey North 80¬∫ | I84: Top Notch Creative | J84: The Sophisticated Traveller | L84: Finishing | M84: colorMaven "The Traveller Settles Down" | O84: Original | P84: 16700 | Q84: firm-bid | W84: 1 | BU84: 0 | BV84: 0 | BW84: 18050
A85: 326 | B85: 45128.786 | C85: The Traveller Settles Down | D85: Alcoholic Beverages | E85: North America | F85: 0 | G85: Dewey North | H85: Dewey North 80¬∫ | I85: Top Notch Creative | J85: The Sophisticated Traveller | L85: Editorial | M85: The Traveller Settles Down | N85: ToTo_TheTravellerSettlesDown_Edit | O85: Original | P85: 112476.88 | Q85: firm-bid | BU85: 0 | BV85: 0 | BW85: 100943.6
A86: 326 | B86: 45128.786 | C86: The Traveller Settles Down | D86: Alcoholic Beverages | E86: North America | F86: 1 | G86: Dewey North | H86: Dewey North 80¬∫ | I86: Top Notch Creative | J86: The Sophisticated Traveller | K86: Armistice Edit | L86: Editorial | M86: The Traveller Settles Down | N86: Armistace_TheTravellerSettlesDown_Edit | O86: Original | P86: 111615.99 | Q86: firm-bid | R86: 100943.6 | AL86: 34250 | AM86: 15700 | AN86: 10700 | AO86: 20772 | BU86: 0 | BV86: 0 | BW86: 100943.6
A87: 326 | B87: 45128.786 | C87: The Traveller Settles Down | D87: Alcoholic Beverages | E87: North America | F87: 0 | G87: Dewey North | H87: Dewey North 80¬∫ | I87: Top Notch Creative | J87: The Sophisticated Traveller | L87: Editorial | M87: The Traveller Settles Down | N87: MyrtleRow_TheTravellerSettlesDown_Edit | O87: Original | P87: 78737.925 | Q87: firm-bid | X87: 1 | BU87: 0 | BV87: 0 | BW87: 100943.6
A88: 326 | B88: 45128.786 | C88: The Traveller Settles Down | D88: Alcoholic Beverages | E88: North America | F88: 0 | G88: Dewey North | H88: Dewey North 80¬∫ | I88: Top Notch Creative | J88: The Sophisticated Traveller | L88: Green Production Costs | M88: TTSD | N88: Interstate_TheTravellerSettlesDown_Green | O88: Original | P88: 6875 | Q88: firm-bid | W88: 1 | BU88: 0 | BV88: 0 | BW88: 8766.3333
A89: 326 | B89: 45128.786 | C89: The Traveller Settles Down | D89: Alcoholic Beverages | E89: North America | F89: 1 | G89: Dewey North | H89: Dewey North 80¬∫ | I89: Top Notch Creative | J89: The Sophisticated Traveller | K89: Open Frameworks Image Creation | L89: Green Production Costs | M89: The Traveller Settles Down | N89: OpenFrameworks_TheTravellerSettlesDown_Green | O89: Original | P89: 8928 | Q89: firm-bid | R89: 8766.3333 | S89: 1 | T89: 1 | Z89: 0 | AA89: 0 | AI89: 0 | AL89: 0 | AN89: 0 | AP89: 0 | AR89: 0 | AW89: 0 | AY89: 7200 | BC89: 0 | BD89: 0 | BH89: 0 | BI89: 0 | BP89: 0 | BQ89: 0 | BR89: 0 | BU89: 8928 | BV89: 8928 | BW89: 8766.3333
A90: 326 | B90: 45128.786 | C90: The Traveller Settles Down | D90: Alcoholic Beverages | E90: North America | F90: 0 | G90: Dewey North | H90: Dewey North 80¬∫ | I90: Top Notch Creative | J90: The Sophisticated Traveller | L90: Green Production Costs | M90: TTSD | N90: Petulant_TheTravellerSettlesDown_Green | O90: Original | P90: 10496 | Q90: firm-bid | S90: 1 | BU90: 10496 | BV90: 0 | BW90: 8766.3333
A91: 326 | B91: 45128.786 | C91: The Traveller Settles Down | D91: Alcoholic Beverages | E91: North America | F91: 0 | G91: Dewey North | H91: Dewey North 80¬∫ | I91: Top Notch Creative | J91: The Sophisticated Traveller | L91: Sanitary Production Costs | M91: TTSD | N91: Interstate_TheTravellerSettlesDown_Covid | O91: Original | P91: 10484.952 | Q91: firm-bid | W91: 1 | BU91: 0 | BV91: 0 | BW91: 7291.9392
A92: 326 | B92: 45128.786 | C92: The Traveller Settles Down | D92: Alcoholic Beverages | E92: North America | F92: 1 | G92: Dewey North | H92: Dewey North 80¬∫ | I92: Top Notch Creative | J92: The Sophisticated Traveller | K92: Open Frameworks Image Creation | L92: Sanitary Production Costs | M92: The Traveller Settles Down | N92: OpenFrameworks_TheTravellerSettlesDown_Covid | O92: Original | P92: 6664.365 | Q92: firm-bid | R92: 7291.9392 | S92: 1 | T92: 1 | AF92: 2700 | BE92: 1530 | BU92: 6664.365 | BV92: 6664.365 | BW92: 7291.9392
A93: 326 | B93: 45128.786 | C93: The Traveller Settles Down | D93: Alcoholic Beverages | E93: North America | F93: 0 | G93: Dewey North | H93: Dewey North 80¬∫ | I93: Top Notch Creative | J93: The Sophisticated Traveller | L93: Sanitary Production Costs | M93: TTSD | N93: Petulant_TheTravellerSettlesDown_Covid | O93: Original | P93: 4726.5 | Q93: firm-bid | S93: 1 | BU93: 4726.5 | BV93: 0 | BW93: 7291.9392
A94: 326 | B94: 45128.786 | C94: The Traveller Settles Down | D94: Alcoholic Beverages | E94: North America | F94: 0 | G94: Dewey North | H94: Dewey North 80¬∫ | I94: Top Notch Creative | J94: The Sophisticated Traveller | L94: Film & Video Production | M94: TTSD | N94: Interstate_TheTravellerSettlesDown_LiveAction | O94: Original | P94: 702418.88 | Q94: firm-bid | W94: 1 | BU94: 0 | BV94: 0 | BW94: 656708.29
A95: 326 | B95: 45128.786 | C95: The Traveller Settles Down | D95: Alcoholic Beverages | E95: North America | F95: 1 | G95: Dewey North | H95: Dewey North 80¬∫ | I95: Top Notch Creative | J95: The Sophisticated Traveller | K95: Open Frameworks Image Creation | L95: Film & Video Production | M95: The Traveller Settles Down | N95: OpenFrameworks_TheTravellerSettlesDown_LiveAction | O95: Original | P95: 621332.43 | Q95: firm-bid | R95: 656708.29 | S95: 1 | T95: 1 | Z95: 31924.75 | AA95: 33650 | AI95: 90000 | AL95: 0 | AN95: 0 | AP95: 29700 | AR95: 4200 | AW95: 41424 | AY95: 1200 | BC95: 31500 | BD95: 97204.25 | BH95: 10000 | BI95: 87332.96 | BP95: 27280 | BQ95: 0 | BR95: 0 | BU95: 621332.43 | BV95: 621332.43 | BW95: 656708.29
A96: 326 | B96: 45128.786 | C96: The Traveller Settles Down | D96: Alcoholic Beverages | E96: North America | F96: 0 | G96: Dewey North | H96: Dewey North 80¬∫ | I96: Top Notch Creative | J96: The Sophisticated Traveller | L96: Film & Video Production | M96: TTSD | N96: Petulant_TheTravellerSettlesDown_LiveAction | O96: Original | P96: 646373.56 | Q96: firm-bid | S96: 1 | BU96: 646373.56 | BV96: 0 | BW96: 656708.29
A97: 330 | B97: 45128.79 | C97: Designated Dad | D97: Alcoholic Beverages | E97: North America | F97: 0 | G97: Walker's | H97: Walker's N/A | I97: Aster PPK | J97: Party Light | L97: Audio Post | M97: Sound Monster "Designated Dad" | N97: Sound Monster | O97: Original | P97: 50580 | Q97: firm-bid | BU97: 0 | BV97: 0 | BW97: 36220
A98: 330 | B98: 45128.79 | C98: Designated Dad | D98: Alcoholic Beverages | E98: North America | F98: 0 | G98: Walker's | H98: Walker's N/A | I98: Aster PPK | J98: Party Light | L98: Audio Post | M98: Funny Rabbit "Designated Dad" | N98: Funny Rabbit | O98: Original | P98: 18410 | Q98: firm-bid | S98: 1 | T98: 1 | V98: 1 | W98: 1 | BU98: 18410 | BV98: 0 | BW98: 36220
A99: 330 | B99: 45128.79 | C99: Designated Dad | D99: Alcoholic Beverages | E99: North America | F99: 1 | G99: Walker's | H99: Walker's N/A | I99: Aster PPK | J99: Party Light | K99: Earwax | L99: Audio Post | M99: Earwax | N99: Earwax | O99: Original | P99: 39670 | Q99: firm-bid | R99: 36220 | AB99: 39670 | BU99: 0 | BV99: 0 | BW99: 36220
A100: 330 | B100: 45128.79 | C100: Designated Dad | D100: Alcoholic Beverages | E100: North America | F100: 0 | G100: Walker's | H100: Walker's N/A | I100: Aster PPK | J100: Party Light | L100: Photo Retouching & Post | M100: DesDad | N100: Interstate_DesignatedDad_Retouching | O100: Original | P100: 21700 | Q100: firm-bid | W100: 1 | BU100: 0 | BV100: 0 | BW100: 25166.667
...

Sheet AvgBidPrice LUT
A1: PROJECT ID | B1: PROJECT NAME | C1: PHASE | D1: Average Bid Price
A2: 318 | B2: Summer Fun | C2: Film & Video Production | D2: 745866.47
A3: 318 | B3: Summer Fun | C3: Editorial | D3: 109194.19
A4: 318 | B4: Summer Fun | C4: Audio Post | D4: 21656.667
A5: 318 | B5: Summer Fun | C5: Finishing | D5: 37833.333
A6: 318 | B6: Summer Fun | C6: Sanitary Production Costs | D6: 7050.3625
A7: 318 | B7: Summer Fun | C7: Green Production Costs | D7: 14980
A8: 318 | B8: Summer Fun | C8: Photo Retouching & Post | D8: 37483.333
A9: 318 | B9: Summer Fun | C9: Still Photography Production | D9: 145472.98
A10: 318 | B10: Summer Fun | C10: Music | D10: 38916.667
A11: 323 | B11: The Traveller UK | C11: Audio Post | D11: 33935
A12: 323 | B12: The Traveller UK | C12: Music | D12: 40150
A13: 323 | B13: The Traveller UK | C13: VFX | D13: 104828.75
... A203: 383 | B203: Alerts | C203: Photo Retouching & Post | D203: 30533.333

Sheet Phase per Agency (2)
A1: AWARDED | B1: AGENCY | C1: PHASE | D1: BID TOTAL | E1: SPEND:: ANIMATION | F1: SPEND:: ART DEPARTMENT LABOR | G1: SPEND:: ART DEPARTMENT MATERIALS | H1: SPEND:: AUDIO POST | I1: SPEND:: CATERING / CRAFT SERVICE | J1: SPEND:: COLOR GRADING | K1: SPEND:: COVID LABOR | L1: SPEND:: DESIGN | M1: SPEND:: DIRECTOR/ CREATIVE FEES | N1: SPEND:: EDITORIAL GRAPHICS | O1: SPEND:: EDITORIAL LABOR | P1: SPEND:: EDITORIAL MISC | Q1: SPEND:: EDITORIAL OFFLINE | R1: SPEND:: EDITORIAL PREP | S1: SPEND:: EQUIPMENT COSTS | T1: SPEND:: EXPENDABLES | U1: SPEND:: FILM STOCK & DIGITAL MEDIA | V1: SPEND:: FINISHING | W1: SPEND:: FOREIGN PRODUCTION SERVICES | X1: SPEND:: HAIR & MAKEUP | Y1: SPEND:: INTERACTIVE | Z1: SPEND:: LOCATION & TRAVEL EXPENSES | AA1: SPEND:: MEALS | AB1: SPEND:: MISCELLANEOUS | AC1: SPEND:: MUSIC | AD1: SPEND:: PRE-PRODUCTION EXPENSES | AE1: SPEND:: PRE-PRODUCTION LABOR | AF1: SPEND:: PRODUCTION COVID 19 COSTS | AG1: SPEND:: PRODUCTION STAFF | AH1: SPEND:: PRODUCTION SUSTAINABILITY | AI1: SPEND:: PROPS, WARDROBE, ANIMALS | AJ1: SPEND:: SHOOTING CREW LABOR | AK1: SPEND:: SOCIAL MEDIA | AL1: SPEND:: SPECIAL INSURANCE | AM1: SPEND:: STILL PHOTOGRAPHER FEES | AN1: SPEND:: STILL PHOTOGRAPHY PRODUCTION | AO1: SPEND:: STILLS POST PRODUCTION | AP1: SPEND:: STUDIO & LOCATIONS COMBINED | AQ1: SPEND:: STUDIO RENTAL & STAGE EXPENSES | AR1: SPEND:: TALENT | AS1: SPEND:: TALENT EXPENSES | AT1: SPEND:: VFX | AU1: SPEND:: WARDROBE | AV1: AvgBidPrice LUT.Average Bid Price
A2: 1 | B2: Korea SMB | C2: Film & Video Production | D2: 960207.05 | F2: 36250.5 | G2: 4200 | M2: 240000 | O2: 0 | Q2: 0 | S2: 16550 | U2: 3000 | Z2: 37115 | AB2: 5000 | AD2: 25950 | AE2: 141212.5 | AI2: 48000 | AJ2: 163923.76 | AQ2: 28960 | AR2: 0 | AS2: 0 | AV2: 745866.47
A3: 0 | B3: Korea SMB | C3: Film & Video Production | D3: 662457.18 | AV3: 745866.47
A4: 0 | B4: Korea SMB | C4: Film & Video Production | D4: 614935.17 | AV4: 745866.47
A5: 0 | B5: Korea SMB | C5: Editorial | D5: 107610.42 | AV5: 109194.19
A6: 0 | B6: Korea SMB | C6: Editorial | D6: 133998.96 | AV6: 109194.19
A7: 1 | B7: Korea SMB | C7: Editorial | D7: 85973.183 | O7: 13200 | P7: 28800 | Q7: 10550 | R7: 10166 | AV7: 109194.19
A8: 0 | B8: Korea SMB | C8: Audio Post | D8: 14510 | AV8: 21656.667
A9: 1 | B9: Korea SMB | C9: Audio Post | D9: 21040 | H9: 21040 | AV9: 21656.667
A10: 0 | B10: Korea SMB | C10: Audio Post | D10: 29420 | AV10: 21656.667
A11: 0 | B11: Korea SMB | C11: Finishing | D11: 52850 | AV11: 37833.333
A12: 0 | B12: Korea SMB | C12: Finishing | D12: 20700 | AV12: 37833.333
A13: 1 | B13: Korea SMB | C13: Finishing | D13: 39950 | V13: 39950 | AV13: 37833.333
A14: 1 | B14: Korea SMB | C14: Sanitary Production Costs | D14: 4805.275 | K14: 2000 | AF14: 1050 | AV14: 7050.3625
A15: 0 | B15: Korea SMB | C15: Sanitary Production Costs | D15: 10043.812 | AV15: 7050.3625
A16: 0 | B16: Korea SMB | C16: Sanitary Production Costs | D16: 6302 | AV16: 7050.3625
A17: 1 | B17: Korea SMB | C17: Green Production Costs | D17: 18176 | F17: 0 | G17: 0 | M17: 0 | O17: 0 | Q17: 0 | S17: 0 | U17: 0 | Z17: 0 | AB17: 14200 | AD17: 0 | AE17: 0 | AI17: 0 | AJ17: 0 | AQ17: 0 | AR17: 0 | AS17: 0 | AV17: 14980
A18: 0 | B18: Korea SMB | C18: Green Production Costs | D18: 14364 | AV18: 14980
A19: 0 | B19: Korea SMB | C19: Green Production Costs | D19: 12400 | AV19: 14980
A20: 0 | B20: Korea SMB | C20: Photo Retouching & Post | D20: 39250 | AV20: 37483.333
A21: 0 | B21: Korea SMB | C21: Photo Retouching & Post | D21: 36200 | AV21: 37483.333
A22: 1 | B22: Korea SMB | C22: Photo Retouching & Post | D22: 37000 | AO22: 37000 | AV22: 37483.333
A23: 0 | B23: Korea SMB | C23: Still Photography Production | D23: 161541.3 | AV23: 145472.98
A24: 0 | B24: Korea SMB | C24: Still Photography Production | D24: 138331.55 | AV24: 145472.98
A25: 1 | B25: Korea SMB | C25: Still Photography Production | D25: 136546.09 | G25: 0 | I25: 8053 | S25: 2816 | U25: 7357 | AB25: 0 | AD25: 15030 | AG25: 7639 | AI25: 3398 | AJ25: 33713 | AM25: 11876 | AP25: 3905 | AR25: 4610 | AS25: 1189 | AV25: 145472.98
A26: 0 | B26: Korea SMB | C26: Music | D26: 8700 | AV26: 38916.667
A27: 0 | B27: Korea SMB | C27: Music | D27: 69900 | AV27: 38916.667
A28: 1 | B28: Korea SMB | C28: Music | D28: 38150 | AC28: 38150 | AV28: 38916.667
A29: 0 | B29: Last Station Group | C29: Audio Post | D29: 24800 | AV29: 33935
A30: 1 | B30: Last Station Group | C30: Audio Post | D30: 43070 | H30: 43070 | AV30: 33935
A31: 1 | B31: Last Station Group | C31: Music | D31: 20800 | AC31: 20800 | AV31: 40150
A32: 0 | B32: Last Station Group | C32: Music | D32: 49050 | AV32: 40150
A33: 0 | B33: Last Station Group | C33: Music | D33: 50600 | AV33: 40150
A34: 1 | B34: Last Station Group | C34: VFX | D34: 116454 | E34: 56750 | U34: 750 | V34: 7500 | AB34: 7900 | AG34: 16680 | AV34: 104828.75
A35: 0 | B35: Last Station Group | C35: VFX | D35: 93203.5 | AV35: 104828.75
A36: 0 | B36: Last Station Group | C36: Finishing | D36: 17500 | AV36: 32250
A37: 1 | B37: Last Station Group | C37: Finishing | D37: 49250 | V37: 49250 | AV37: 32250
A38: 0 | B38: Last Station Group | C38: Finishing | D38: 30000 | AV38: 32250
A39: 1 | B39: Last Station Group | C39: Editorial | D39: 95889.792 | O39: 16650 | P39: 13100 | Q39: 32950 | R39: 7250 | AV39: 93203.872
A40: 0 | B40: Last Station Group | C40: Editorial | D40: 67406.617 | AV40: 93203.872
A41: 0 | B41: Last Station Group | C41: Editorial | D41: 116315.21 | AV41: 93203.872
A42: 1 | B42: Last Station Group | C42: Green Production Costs | D42: 10250 | F42: 0 | G42: 0 | M42: 0 | O42: 0 | Q42: 0 | S42: 0 | U42: 0 | Z42: 0 | AB42: 8200 | AD42: 0 | AE42: 0 | AI42: 0 | AJ42: 0 | AQ42: 0 | AR42: 0 | AS42: 0 | AV42: 9606
A43: 0 | B43: Last Station Group | C43: Green Production Costs | D43: 8568 | AV43: 9606
A44: 0 | B44: Last Station Group | C44: Green Production Costs | D44: 10000 | AV44: 9606
A45: 1 | B45: Last Station Group | C45: Sanitary Production Costs | D45: 7200.035 | K45: 3400 | AF45: 1170 | AV45: 9810.1133
A46: 0 | B46: Last Station Group | C46: Sanitary Production Costs | D46: 12958.487 | AV46: 9810.1133
A47: 0 | B47: Last Station Group | C47: Sanitary Production Costs | D47: 9271.8175 | AV47: 9810.1133
A48: 1 | B48: Last Station Group | C48: Film & Video Production | D48: 685626.9 | F48: 38109.5 | G48: 73200 | M48: 80000 | O48: 0 | Q48: 0 | S48: 22500 | U48: 3500 | Z48: 28078 | AB48: 16100 | AD48: 18625 | AE48: 86050.25 | AI48: 7500 | AJ48: 143742.17 | AQ48: 35520 | AR48: 0 | AS48: 0 | AV48: 649602.48
A49: 0 | B49: Last Station Group | C49: Film & Video Production | D49: 673878.44 | AV49: 649602.48
A50: 0 | B50: Last Station Group | C50: Film & Video Production | D50: 589302.09 | AV50: 649602.48
A51: 0 | B51: Top Notch Creative | C51: Audio Post | D51: 29320 | AV51: 48990
A52: 1 | B52: Top Notch Creative | C52: Audio Post | D52: 68660 | H52: 68660 | AV52: 48990
A53: 0 | B53: Top Notch Creative | C53: Behind The Scenes (BTS) | D53: 22844.75 | AV53: 18774.708
A54: 1 | B54: Top Notch Creative | C54: Behind The Scenes (BTS) | D54: 19457.425 | AV54: 18774.708
A55: 0 | B55: Top Notch Creative | C55: Behind The Scenes (BTS) | D55: 14021.95 | AV55: 18774.708
A56: 1 | B56: Top Notch Creative | C56: Music | D56: 15950 | AC56: 15950 | AV56: 30350
A57: 0 | B57: Top Notch Creative | C57: Music | D57: 34650 | AV57: 30350
A58: 0 | B58: Top Notch Creative | C58: Music | D58: 40450 | AV58: 30350
A59: 0 | B59: Top Notch Creative | C59: Finishing | D59: 14900 | AV59: 27083.333
A60: 0 | B60: Top Notch Creative | C60: Finishing | D60: 47450 | AV60: 27083.333
A61: 1 | B61: Top Notch Creative | C61: Finishing | D61: 18900 | V61: 18900 | AV61: 27083.333
A62: 0 | B62: Top Notch Creative | C62: Editorial | D62: 56933.45 | AV62: 93441.483
A63: 1 | B63: Top Notch Creative | C63: Editorial | D63: 100975.58 | O63: 13300 | P63: 35300 | Q63: 13700 | R63: 11360 | AV63: 93441.483
A64: 0 | B64: Top Notch Creative | C64: Editorial | D64: 122415.42 | AV64: 93441.483
A65: 0 | B65: Top Notch Creative | C65: Green Production Costs | D65: 12400 | AV65: 11703.333
A66: 1 | B66: Top Notch Creative | C66: Green Production Costs | D66: 13750 | F66: 0 | G66: 0 | M66: 0 | O66: 0 | Q66: 0 | S66: 0 | U66: 0 | Z66: 0 | AB66: 11000 | AD66: 0 | AE66: 0 | AI66: 0 | AJ66: 0 | AQ66: 0 | AR66: 0 | AS66: 0 | AV66: 11703.333
A67: 0 | B67: Top Notch Creative | C67: Green Production Costs | D67: 8960 | AV67: 11703.333
A68: 0 | B68: Top Notch Creative | C68: Sanitary Production Costs | D68: 7010.975 | AV68: 7058.24
A69: 1 | B69: Top Notch Creative | C69: Sanitary Production Costs | D69: 5317.3125 | K69: 1850 | AF69: 1525 | AV69: 7058.24
A70: 0 | B70: Top Notch Creative | C70: Sanitary Production Costs | D70: 8846.4325 | AV70: 7058.24
A71: 0 | B71: Top Notch Creative | C71: Film & Video Production | D71: 748472.66 | AV71: 835635.38
A72: 1 | B72: Top Notch Creative | C72: Film & Video Production | D72: 856318.5 | F72: 36536.5 | G72: 52700 | M72: 125000 | O72: 0 | Q72: 0 | S72: 128200 | U72: 2800 | Z72: 39121 | AB72: 12200 | AD72: 24500 | AE72: 121514.25 | AI72: 0 | AJ72: 113163.05 | AQ72: 29320 | AR72: 0 | AS72: 0 | AV72: 835635.38
A73: 0 | B73: Top Notch Creative | C73: Film & Video Production | D73: 902114.97 | AV73: 835635.38
A74: 0 | B74: Top Notch Creative | C74: Audio Post | D74: 35540 | AV74: 52025
A75: 1 | B75: Top Notch Creative | C75: Audio Post | D75: 68510 | H75: 68510 | AV75: 52025
A76: 0 | B76: Top Notch Creative | C76: Music | D76: 8600 | AV76: 40166.667
A77: 1 | B77: Top Notch Creative | C77: Music | D77: 52150 | AC77: 52150 | AV77: 40166.667
A78: 0 | B78: Top Notch Creative | C78: Music | D78: 59750 | AV78: 40166.667
A79: 1 | B79: Top Notch Creative | C79: VFX | D79: 80541.5 | E79: 44625 | U79: 6500 | V79: 5250 | AB79: 0 | AG79: 5580 | AV79: 79204.667
A80: 0 | B80: Top Notch Creative | C80: VFX | D80: 92170 | AV80: 79204.667
A81: 0 | B81: Top Notch Creative | C81: VFX | D81: 64902.5 | AV81: 79204.667
A82: 0 | B82: Top Notch Creative | C82: Finishing | D82: 8850 | AV82: 18050
A83: 1 | B83: Top Notch Creative | C83: Finishing | D83: 28600 | V83: 28600 | AV83: 18050
A84: 0 | B84: Top Notch Creative | C84: Finishing | D84: 16700 | AV84: 18050
A85: 0 | B85: Top Notch Creative | C85: Editorial | D85: 112476.88 | AV85: 100943.6
A86: 1 | B86: Top Notch Creative | C86: Editorial | D86: 111615.99 | O86: 34250 | P86: 15700 | Q86: 10700 | R86: 20772 | AV86: 100943.6
A87: 0 | B87: Top Notch Creative | C87: Editorial | D87: 78737.925 | AV87: 100943.6
A88: 0 | B88: Top Notch Creative | C88: Green Production Costs | D88: 6875 | AV88: 8766.3333
A89: 1 | B89: Top Notch Creative | C89: Green Production Costs | D89: 8928 | F89: 0 | G89: 0 | M89: 0 | O89: 0 | Q89: 0 | S89: 0 | U89: 0 | Z89: 0 | AB89: 7200 | AD89: 0 | AE89: 0 | AI89: 0 | AJ89: 0 | AQ89: 0 | AR89: 0 | AS89: 0 | AV89: 8766.3333
A90: 0 | B90: Top Notch Creative | C90: Green Production Costs | D90: 10496 | AV90: 8766.3333
A91: 0 | B91: Top Notch Creative | C91: Sanitary Production Costs | D91: 10484.952 | AV91: 7291.9392
A92: 1 | B92: Top Notch Creative | C92: Sanitary Production Costs | D92: 6664.365 | K92: 2700 | AF92: 1530 | AV92: 7291.9392
A93: 0 | B93: Top Notch Creative | C93: Sanitary Production Costs | D93: 4726.5 | AV93: 7291.9392
A94: 0 | B94: Top Notch Creative | C94: Film & Video Production | D94: 702418.88 | AV94: 656708.29
A95: 1 | B95: Top Notch Creative | C95: Film & Video Production | D95: 621332.43 | F95: 31924.75 | G95: 33650 | M95: 90000 | O95: 0 | Q95: 0 | S95: 29700 | U95: 4200 | Z95: 41424 | AB95: 1200 | AD95: 31500 | AE95: 97204.25 | AI95: 10000 | AJ95: 87332.96 | AQ95: 27280 | AR95: 0 | AS95: 0 | AV95: 656708.29
A96: 0 | B96: Top Notch Creative | C96: Film & Video Production | D96: 646373.56 | AV96: 656708.29
A97: 0 | B97: Aster PPK | C97: Audio Post | D97: 50580 | AV97: 36220
A98: 0 | B98: Aster PPK | C98: Audio Post | D98: 18410 | AV98: 36220
A99: 1 | B99: Aster PPK | C99: Audio Post | D99: 39670 | H99: 39670 | AV99: 36220
A100: 0 | B100: Aster PPK | C100: Photo Retouching & Post | D100: 21700 | AV100: 25166.667
...

Sheet Sheet1
A1: Row Labels | B1: Count of PHASE
A2: Big Chew | B2: 46
A3: The Seven Deadly Sins | B3: 46
A4: Top Notch Creative | B4: 46
A5: Color Guard | B5: 30
A6: Dirty John | B6: 30
A7: Cantor Asia Media | B7: 27
A8: Geoffrey Monty Allen | B8: 3
A9: Dewey North | B9: 68
A10: The Sophisticated Traveller | B10: 68
A11: Last Station Group | B11: 22
A12: Top Notch Creative | B12: 46
A13: Giggles | B13: 41
... A45: Grand Total | B45: 552

Sheet Sheet3
A1: PROJECT ID | B1: PROJECT NAME | C1: AWARDED | D1: AGENCY | E1: VENDOR | F1: PHASE | G1: BID TOTAL | H1: AVERAGE BID | I1: DIVERSITY:: WOMAN DIRECTOR | J1: DIVERSITY:: MIINORITY DIRECTOR | K1: DIVERSITY:: WOMAN EDITOR | L1: DIVERSITY:: MIINORITY EDITOR | M1: DIVERSITY:: WOMAN OWNED | N1: DIVERSITY:: MINORITY OWNED | O1: Women Work Pitched | P1: Women Work Awarded | Q1: AvgBidPrice LUT.Average Bid Price | R1: AVG ADJUSTED | S1: Awarded Total | T1: Variance | U1: Variance Perc
A2: 330 | B2: Designated Dad | C2: 0 | D2: Aster PPK | F2: Audio Post | G2: 50580 | O2: 0 | P2: 0 | Q2: 36220
A3: 330 | B3: Designated Dad | C3: 0 | D3: Aster PPK | F3: Photo Retouching & Post | G3: 21700 | M3: 1 | O3: 0 | P3: 0 | Q3: 25166.667
A4: 330 | B4: Designated Dad | C4: 0 | D4: Aster PPK | F4: Photo Retouching & Post | G4: 35450 | O4: 0 | P4: 0 | Q4: 25166.667
A5: 330 | B5: Designated Dad | C5: 0 | D5: Aster PPK | F5: Still Photography Production | G5: 151338.11 | M5: 1 | O5: 0 | P5: 0 | Q5: 149975.39
A6: 330 | B6: Designated Dad | C6: 0 | D6: Aster PPK | F6: Still Photography Production | G6: 152418.7 | O6: 0 | P6: 0 | Q6: 149975.39
A7: 330 | B7: Designated Dad | C7: 0 | D7: Aster PPK | F7: Film & Video Production | G7: 836827.74 | J7: 1 | N7: 1 | O7: 0 | P7: 0 | Q7: 689735.13
A8: 330 | B8: Designated Dad | C8: 0 | D8: Aster PPK | F8: Sanitary Production Costs | G8: 5136.13 | J8: 1 | N8: 1 | O8: 0 | P8: 0 | Q8: 5600.9025
A9: 330 | B9: Designated Dad | C9: 0 | D9: Aster PPK | F9: Green Production Costs | G9: 7182 | J9: 1 | N9: 1 | O9: 0 | P9: 0 | Q9: 5023.3333
A10: 330 | B10: Designated Dad | C10: 0 | D10: Aster PPK | F10: Editorial | G10: 123512.08 | O10: 0 | P10: 0 | Q10: 123349.41
A11: 330 | B11: Designated Dad | C11: 0 | D11: Aster PPK | F11: Editorial | G11: 122612.82 | O11: 0 | P11: 0 | Q11: 123349.41
A12: 330 | B12: Designated Dad | C12: 0 | D12: Aster PPK | F12: Finishing | G12: 53600 | O12: 0 | P12: 0 | Q12: 38500
A13: 330 | B13: Designated Dad | C13: 0 | D13: Aster PPK | F13: Finishing | G13: 20600 | O13: 0 | P13: 0 | Q13: 38500
A14: 332 | B14: Sunday Night Lights | C14: 0 | D14: Aster PPK | F14: Audio Post | G14: 21500 | O14: 0 | P14: 0 | Q14: 31766.667
A15: 332 | B15: Sunday Night Lights | C15: 0 | D15: Aster PPK | F15: Film & Video Production | G15: 804309.03 | M15: 1 | O15: 0 | P15: 0 | Q15: 827429.73
A16: 332 | B16: Sunday Night Lights | C16: 0 | D16: Aster PPK | F16: Sanitary Production Costs | G16: 11871.392 | M16: 1 | O16: 0 | P16: 0 | Q16: 7782.97
A17: 332 | B17: Sunday Night Lights | C17: 0 | D17: Aster PPK | F17: Green Production Costs | G17: 6750 | M17: 1 | O17: 0 | P17: 0 | Q17: 11750
A18: 332 | B18: Sunday Night Lights | C18: 0 | D18: Aster PPK | F18: Editorial | G18: 94579.275 | M18: 1 | N18: 1 | O18: 0 | P18: 0 | Q18: 114895.94
A19: 332 | B19: Sunday Night Lights | C19: 0 | D19: Aster PPK | F19: Finishing | G19: 29850 | O19: 0 | P19: 0 | Q19: 36283.333
A20: 332 | B20: Sunday Night Lights | C20: 0 | D20: Aster PPK | F20: Finishing | G20: 16900 | O20: 0 | P20: 0 | Q20: 36283.333
A21: 332 | B21: Sunday Night Lights | C21: 0 | D21: Aster PPK | F21: Still Photography Production | G21: 192655.61 | M21: 1 | O21: 0 | P21: 0 | Q21: 158633.04
A22: 332 | B22: Sunday Night Lights | C22: 0 | D22: Aster PPK | F22: Still Photography Production | G22: 143694.28 | J22: 1 | O22: 0 | P22: 0 | Q22: 158633.04
A23: 332 | B23: Sunday Night Lights | C23: 0 | D23: Aster PPK | F23: Photo Retouching & Post | G23: 38300 | M23: 1 | O23: 0 | P23: 0 | Q23: 29616.667
A24: 332 | B24: Sunday Night Lights | C24: 0 | D24: Aster PPK | F24: Photo Retouching & Post | G24: 27550 | J24: 1 | O24: 0 | P24: 0 | Q24: 29616.667
A25: 332 | B25: Sunday Night Lights | C25: 0 | D25: Aster PPK | F25: Behind The Scenes (BTS) | G25: 17251.725 | M25: 1 | O25: 0 | P25: 0 | Q25: 18144.508
A26: 334 | B26: Trapeze | C26: 0 | D26: Aster PPK | F26: Music | G26: 52050 | N26: 1 | O26: 0 | P26: 0 | Q26: 45025
A27: 334 | B27: Trapeze | C27: 0 | D27: Aster PPK | F27: Behind The Scenes (BTS) | G27: 19693.75 | N27: 1 | O27: 0 | P27: 0 | Q27: 15807.517
A28: 334 | B28: Trapeze | C28: 0 | D28: Aster PPK | F28: Behind The Scenes (BTS) | G28: 14573.375 | O28: 0 | P28: 0 | Q28: 15807.517
A29: 336 | B29: New Parachute | C29: 0 | D29: Aster PPK | F29: Audio Post | G29: 68240 | O29: 0 | P29: 0 | Q29: 42320
A30: 336 | B30: New Parachute | C30: 0 | D30: Aster PPK | F30: Audio Post | G30: 30200 | O30: 0 | P30: 0 | Q30: 42320
A31: 336 | B31: New Parachute | C31: 0 | D31: Aster PPK | F31: Film & Video Production | G31: 828919.12 | O31: 0 | P31: 0 | Q31: 786422.47
A32: 336 | B32: New Parachute | C32: 0 | D32: Aster PPK | F32: Sanitary Production Costs | G32: 12273.145 | O32: 0 | P32: 0 | Q32: 8015.3563
A33: 336 | B33: New Parachute | C33: 0 | D33: Aster PPK | F33: Green Production Costs | G33: 17766 | O33: 0 | P33: 0 | Q33: 15561
A34: 336 | B34: New Parachute | C34: 0 | D34: Aster PPK | F34: Editorial | G34: 111646.15 | O34: 0 | P34: 0 | Q34: 131253.18
A35: 338 | B35: The Big Guy | C35: 0 | D35: Aster PPK | F35: Audio Post | G35: 31420 | O35: 0 | P35: 0 | Q35: 26493.333
A36: 338 | B36: The Big Guy | C36: 0 | D36: Aster PPK | F36: Music | G36: 41950 | O36: 0 | P36: 0 | Q36: 33925
A37: 338 | B37: The Big Guy | C37: 0 | D37: Aster PPK | F37: Still Photography Production | G37: 175300.41 | O37: 0 | P37: 0 | Q37: 169276.77
A38: 338 | B38: The Big Guy | C38: 0 | D38: Aster PPK | F38: Still Photography Production | G38: 147033.44 | O38: 0 | P38: 0 | Q38: 169276.77
A39: 338 | B39: The Big Guy | C39: 0 | D39: Aster PPK | F39: VFX | G39: 131202.5 | O39: 0 | P39: 0 | Q39: 116983.75
A40: 338 | B40: The Big Guy | C40: 0 | D40: Aster PPK | F40: Film & Video Production | G40: 651508.09 | J40: 1 | N40: 1 | O40: 0 | P40: 0 | Q40: 758314.42
A41: 338 | B41: The Big Guy | C41: 0 | D41: Aster PPK | F41: Film & Video Production | G41: 876794.62 | J41: 1 | N41: 1 | O41: 0 | P41: 0 | Q41: 758314.42
A42: 338 | B42: The Big Guy | C42: 0 | D42: Aster PPK | F42: Sanitary Production Costs | G42: 6207.47 | J42: 1 | N42: 1 | O42: 0 | P42: 0 | Q42: 4912.9342
A43: 338 | B43: The Big Guy | C43: 0 | D43: Aster PPK | F43: Sanitary Production Costs | G43: 3174.6325 | J43: 1 | N43: 1 | O43: 0 | P43: 0 | Q43: 4912.9342
A44: 338 | B44: The Big Guy | C44: 0 | D44: Aster PPK | F44: Green Production Costs | G44: 19592 | J44: 1 | N44: 1 | O44: 0 | P44: 0 | Q44: 14893
A45: 338 | B45: The Big Guy | C45: 0 | D45: Aster PPK | F45: Green Production Costs | G45: 16383 | J45: 1 | N45: 1 | O45: 0 | P45: 0 | Q45: 14893
A46: 338 | B46: The Big Guy | C46: 0 | D46: Aster PPK | F46: Photo Retouching & Post | G46: 38700 | O46: 0 | P46: 0 | Q46: 47966.667
A47: 338 | B47: The Big Guy | C47: 0 | D47: Aster PPK | F47: Photo Retouching & Post | G47: 50000 | O47: 0 | P47: 0 | Q47: 47966.667
A48: 340 | B48: A Better Birthday | C48: 0 | D48: Aster PPK | F48: Audio Post | G48: 32110 | O48: 0 | P48: 0 | Q48: 25766.667
A49: 340 | B49: A Better Birthday | C49: 0 | D49: Aster PPK | F49: Film & Video Production | G49: 783241.88 | J49: 1 | N49: 1 | O49: 0 | P49: 0 | Q49: 711043.51
A50: 340 | B50: A Better Birthday | C50: 0 | D50: Aster PPK | F50: Film & Video Production | G50: 736037.19 | M50: 1 | O50: 0 | P50: 0 | Q50: 711043.51
A51: 340 | B51: A Better Birthday | C51: 0 | D51: Aster PPK | F51: Sanitary Production Costs | G51: 3883.6075 | J51: 1 | N51: 1 | O51: 0 | P51: 0 | Q51: 5621.9092
A52: 340 | B52: A Better Birthday | C52: 0 | D52: Aster PPK | F52: Sanitary Production Costs | G52: 5774.2075 | M52: 1 | O52: 0 | P52: 0 | Q52: 5621.9092
A53: 340 | B53: A Better Birthday | C53: 0 | D53: Aster PPK | F53: Green Production Costs | G53: 9271 | J53: 1 | N53: 1 | O53: 0 | P53: 0 | Q53: 16903.667
A54: 340 | B54: A Better Birthday | C54: 0 | D54: Aster PPK | F54: Green Production Costs | G54: 21120 | M54: 1 | O54: 0 | P54: 0 | Q54: 16903.667
A55: 340 | B55: A Better Birthday | C55: 0 | D55: Aster PPK | F55: Editorial | G55: 115561.25 | N55: 1 | O55: 0 | P55: 0 | Q55: 147026.44
A56: 373 | B56: Suspicion | C56: 0 | D56: Aster PPK | F56: Audio Post | G56: 27510 | O56: 0 | P56: 0 | Q56: 28400
A57: 373 | B57: Suspicion | C57: 0 | D57: Aster PPK | F57: VFX | G57: 118137.5 | M57: 1 | O57: 0 | P57: 0 | Q57: 98628.833
A58: 373 | B58: Suspicion | C58: 0 | D58: Aster PPK | F58: VFX | G58: 75952.5 | O58: 0 | P58: 0 | Q58: 98628.833
A59: 373 | B59: Suspicion | C59: 0 | D59: Aster PPK | F59: Finishing | G59: 31800 | O59: 0 | P59: 0 | Q59: 38150
A60: 373 | B60: Suspicion | C60: 0 | D60: Aster PPK | F60: Finishing | G60: 17250 | M60: 1 | O60: 0 | P60: 0 | Q60: 38150
A61: 373 | B61: Suspicion | C61: 0 | D61: Aster PPK | F61: Editorial | G61: 124164.6 | N61: 1 | O61: 0 | P61: 0 | Q61: 127133.83
A62: 373 | B62: Suspicion | C62: 0 | D62: Aster PPK | F62: Green Production Costs | G62: 16380 | J62: 1 | O62: 0 | P62: 0 | Q62: 12223
A63: 373 | B63: Suspicion | C63: 0 | D63: Aster PPK | F63: Green Production Costs | G63: 10664 | O63: 0 | P63: 0 | Q63: 12223
A64: 373 | B64: Suspicion | C64: 0 | D64: Aster PPK | F64: Sanitary Production Costs | G64: 12036.82 | J64: 1 | O64: 0 | P64: 0 | Q64: 11025.874
A65: 373 | B65: Suspicion | C65: 0 | D65: Aster PPK | F65: Sanitary Production Costs | G65: 9216.675 | O65: 0 | P65: 0 | Q65: 11025.874
A66: 373 | B66: Suspicion | C66: 0 | D66: Aster PPK | F66: Film & Video Production | G66: 727670.19 | J66: 1 | O66: 0 | P66: 0 | Q66: 723920.4
A67: 373 | B67: Suspicion | C67: 0 | D67: Aster PPK | F67: Film & Video Production | G67: 645713.44 | O67: 0 | P67: 0 | Q67: 723920.4
A68: 375 | B68: You Suck! | C68: 0 | D68: Aster PPK | F68: Film & Video Production | G68: 923882.24 | J68: 1 | N68: 1 | O68: 0 | P68: 0 | Q68: 884250.97
A69: 375 | B69: You Suck! | C69: 0 | D69: Aster PPK | F69: Film & Video Production | G69: 773050.33 | O69: 0 | P69: 0 | Q69: 884250.97
A70: 375 | B70: You Suck! | C70: 0 | D70: Aster PPK | F70: Sanitary Production Costs | G70: 8578.5975 | J70: 1 | N70: 1 | O70: 0 | P70: 0 | Q70: 6467.4275
A71: 375 | B71: You Suck! | C71: 0 | D71: Aster PPK | F71: Sanitary Production Costs | G71: 2568.065 | O71: 0 | P71: 0 | Q71: 6467.4275
A72: 375 | B72: You Suck! | C72: 0 | D72: Aster PPK | F72: Green Production Costs | G72: 9198 | J72: 1 | N72: 1 | O72: 0 | P72: 0 | Q72: 9930
A73: 375 | B73: You Suck! | C73: 0 | D73: Aster PPK | F73: Green Production Costs | G73: 9000 | O73: 0 | P73: 0 | Q73: 9930
A74: 375 | B74: You Suck! | C74: 0 | D74: Aster PPK | F74: Editorial | G74: 124425.06 | M74: 1 | N74: 1 | O74: 0 | P74: 0 | Q74: 135828.56
A75: 375 | B75: You Suck! | C75: 0 | D75: Aster PPK | F75: Editorial | G75: 162512.29 | N75: 1 | O75: 0 | P75: 0 | Q75: 135828.56
A76: 375 | B76: You Suck! | C76: 0 | D76: Aster PPK | F76: Finishing | G76: 20650 | O76: 0 | P76: 0 | Q76: 21600
A77: 375 | B77: You Suck! | C77: 0 | D77: Aster PPK | F77: Still Photography Production | G77: 115654.91 | M77: 1 | O77: 0 | P77: 0 | Q77: 151739.27
A78: 375 | B78: You Suck! | C78: 0 | D78: Aster PPK | F78: Photo Retouching & Post | G78: 40000 | M78: 1 | O78: 0 | P78: 0 | Q78: 26250
A79: 324 | B79: The Traveller US | C79: 0 | D79: Top Notch Creative | F79: Behind The Scenes (BTS) | G79: 14021.95 | J79: 1 | N79: 1 | O79: 0 | P79: 0 | Q79: 18774.708
A80: 324 | B80: The Traveller US | C80: 0 | D80: Top Notch Creative | F80: Green Production Costs | G80: 8960 | J80: 1 | N80: 1 | O80: 0 | P80: 0 | Q80: 11703.333
A81: 324 | B81: The Traveller US | C81: 0 | D81: Top Notch Creative | F81: Sanitary Production Costs | G81: 8846.4325 | J81: 1 | N81: 1 | O81: 0 | P81: 0 | Q81: 7058.24
A82: 324 | B82: The Traveller US | C82: 0 | D82: Top Notch Creative | F82: Film & Video Production | G82: 902114.97 | J82: 1 | N82: 1 | O82: 0 | P82: 0 | Q82: 835635.38
A83: 367 | B83: ENVY | C83: 0 | D83: Top Notch Creative | F83: Photo Retouching & Post | G83: 27900 | J83: 1 | N83: 1 | O83: 0 | P83: 0 | Q83: 31316.667
